Workbook
Name k_coBillions: controlTables!$D$219
Name k_coMillions: controlTables!$D$220
Name k_coThousands: controlTables!$D$221
Name list_co_gcms: co_models[model_id]
Name list_coimpactYearOptions: OFFSET( INDIRECT( ADDRESS( ROW( co_impactYears[[#Headers],[row_id]] ), COLUMN(co_impactYears[[#Headers],[2090]]), , , "DropDownMenus" ) ), 1, 0, mv_coNum_impactYears, 1 )
Name loc_coAdaptations: co_variants[[#Headers],[row_id]]
Name loc_coConstants: co_constants[[#Headers],[row_id]]
Name loc_coImpactTypes: co_impactTypes[[#Headers],[row_id]]
Name loc_coImpactYears: co_impactYears[[#Headers],[row_id]]
Name loc_coInputScenarioInfo: co_inputScenarioInfo[[#Headers],[row_id]]
Name loc_colorLegend: controlTables!$C$16
Name loc_coModels: co_models[[#Headers],[row_id]]
Name loc_coModelTypes: co_modelTypes[[#Headers],[row_id]]
Name loc_controlTOC: controlTables!$B$1
Name loc_coRegions: co_regions[[#Headers],[row_id]]
Name loc_coScalars: co_scalarInfo[[#Headers],[row_id]]
Name loc_coSectors: co_sectors[[#Headers],[row_id]]
Name loc_coStates: co_impactYears[[#Headers],[row_id]]
Name loc_econMultipliers: co_econMultipliers[[#Headers],[row_id]]
Name num_gcms: MAX(co_models[row_id])
Name num_gcms: MAX(co_models[row_id])
Name SectorDropDown: controlTables!$D$21:$D$32
Name SectorDropDown_1: controlTables!$D$21:$D$37

Sheet ReadMe
B9: Worksheet | C9: Description
B10: tableNames | C10: Table for tracking of tables in "controlTables" tab, which is used by the R package to import function inputs. Additional notes are provided in the "notes" field.
B11: controlTables | C11: Tables used for documentation of sectors parameters and to define sector processing in the R package. The table of contents at the top of the worksheet lists all of the tables included in the worksheet. Narrative information for each sector and for general framework setup can be found in the Temperature Binning Framework documentation.
B12: defaultScenario | C12: Worksheet for user inputs to R tool. Expand group (see “+” to right) for field descriptions
C13: Field
C14: row_id
C15: year
C16: temp_C_conus
C17: gdp_usd
C18: pop_Midwest
C19: pop_Northeast
C20: pop_Northern.Plains
C21: pop_Northwest
C22: pop_Southeast
C23: pop_Southern.Plains
C24: pop_Southwest
B25: scalarData | C25: Scalars and adjustment factors applied to temperature or GMSL-binned data for inclusion of socioeconomic impact drivers or other time dependent factors. Expand group (see “+” to right) for field descriptions. See Appendix A of the Documentation Report for more information on these values.
C26: Field
C27: row_id
C28: scalarType
C29: scalarLabel
C30: scalarName
C31: region
C32: year
C33: value
B34: scaledImpacts | C34: Temperature or GMSL-binned data. Impacts estimates are scaled where appropriate to remove time-dependencies. Expand group (see “+” to right) for field descriptions. See Appendix A of the Documentation Report for more information on these values.
C35: Field
C36: row_id
C37: output_lookupID
C38: sector
C39: model
C40: modelUnitValue
C41: impactYear
C42: adaptation
C43: impactType
C44: outputRowID
C45: Midwest
C46: Northeast
... C51: Southwest

Sheet tableNames
A1: tableNames | B1: This worksheet contains the names of data tables to import into R
B3: ID | C3: Table Name | D3: Import | E3: Worksheet | F3: ID_columnName | G3: Header Row | H3: Number of Data Rows | I3: Last Row | J3: id_colIndex | K3: last_colIndex | L3: num_tableCols | M3: excludeCol_ids | N3: Notes
B4: =ROW( doc_tablesList[[#This Row],[ID]] ) - ROW(doc_tablesList[[#Headers],[ID]] ) -> 1 | C4: co_sectors | D4: 1 | E4: controlTables | F4: ="row_id" -> row_id | G4: {=INDEX( ROW( INDIRECT( _xlfn.TEXTJOIN( "", , doc_tablesList[[#This Row],[Table Name]], "[[#Headers],[", doc_tablesList[[#This Row],[ID_columnName]], "]]" ) ) ), 1 )} -> 20 | H4: =MAX( INDIRECT( _xlfn.TEXTJOIN( "", , doc_tablesList[[#This Row],[Table Name]], "[", doc_tablesList[[#This Row],[ID_columnName]], "]" ) ) ) -> 25 | I4: =doc_tablesList[[#This Row],[Number of Data Rows]] + doc_tablesList[[#This Row],[Header Row]] -> 45 | J4: {=INDEX( COLUMN( INDIRECT( doc_tablesList[[#This Row],[Table Name]] & "[" & doc_tablesList[[#This Row],[ID_columnName]] & "]" ) ), 1 )} -> 2 | K4: {=MAX( COLUMN( INDIRECT( doc_tablesList[[#This Row],[Table Name]] ) ) )} -> 17 | L4: =doc_tablesList[[#This Row],[last_colIndex]] - doc_tablesList[[#This Row],[id_colIndex]] + 1 -> 16 | M4: {=_xlfn.TEXTJOIN( ", ", , COLUMN( co_sectors[[#Headers],[interpolateEstimateYears]] ) - doc_tablesList[[#This Row],[id_colIndex]] + 1, COLUMN( co_sectors[[#Headers],[Number of variants]:[Number of scaled impact rows per region]] ) - doc_tablesList[[#This Row],[id_colIndex]] + 1 )} -> 7, 11, 12, 13, 14, 15, 16 | N4: Table of sector names and labels. Added variants impact years, and impact types list (columns 7-9), which the R Tool filters out.
B5: =ROW( doc_tablesList[[#This Row],[ID]] ) - ROW(doc_tablesList[[#Headers],[ID]] ) -> 2 | C5: scalarDataframe | D5: 1 | E5: scalarData | F5: ="row_id" -> row_id | G5: {=INDEX( ROW( INDIRECT( _xlfn.TEXTJOIN( "", , doc_tablesList[[#This Row],[Table Name]], "[[#Headers],[", doc_tablesList[[#This Row],[ID_columnName]], "]]" ) ) ), 1 )} -> 1 | H5: =MAX( INDIRECT( _xlfn.TEXTJOIN( "", , doc_tablesList[[#This Row],[Table Name]], "[", doc_tablesList[[#This Row],[ID_columnName]], "]" ) ) ) -> 1489 | I5: =doc_tablesList[[#This Row],[Number of Data Rows]] + doc_tablesList[[#This Row],[Header Row]] -> 1490 | J5: {=INDEX( COLUMN( INDIRECT( doc_tablesList[[#This Row],[Table Name]] & "[" & doc_tablesList[[#This Row],[ID_columnName]] & "]" ) ), 1 )} -> 1 | K5: {=MAX( COLUMN( INDIRECT( doc_tablesList[[#This Row],[Table Name]] ) ) )} -> 7 | L5: =doc_tablesList[[#This Row],[last_colIndex]] - doc_tablesList[[#This Row],[id_colIndex]] + 1 -> 7 | N5: Table of default economic scalars.
B6: =ROW( doc_tablesList[[#This Row],[ID]] ) - ROW(doc_tablesList[[#Headers],[ID]] ) -> 3 | C6: data_scaledImpacts | D6: 1 | E6: scaledImpacts | F6: ="row_id" -> row_id | G6: {=INDEX( ROW( INDIRECT( _xlfn.TEXTJOIN( "", , doc_tablesList[[#This Row],[Table Name]], "[[#Headers],[", doc_tablesList[[#This Row],[ID_columnName]], "]]" ) ) ), 1 )} -> 1 | H6: =MAX( INDIRECT( _xlfn.TEXTJOIN( "", , doc_tablesList[[#This Row],[Table Name]], "[", doc_tablesList[[#This Row],[ID_columnName]], "]" ) ) ) -> 3073 | I6: =doc_tablesList[[#This Row],[Number of Data Rows]] + doc_tablesList[[#This Row],[Header Row]] -> 3074 | J6: {=INDEX( COLUMN( INDIRECT( doc_tablesList[[#This Row],[Table Name]] & "[" & doc_tablesList[[#This Row],[ID_columnName]] & "]" ) ), 1 )} -> 1 | K6: {=MAX( COLUMN( INDIRECT( doc_tablesList[[#This Row],[Table Name]] ) ) )} -> 16 | L6: =doc_tablesList[[#This Row],[last_colIndex]] - doc_tablesList[[#This Row],[id_colIndex]] + 1 -> 16 | M6: =_xlfn.TEXTJOIN( ", ", , COLUMN( data_scaledImpacts[[#Headers],[output_lookupID]] ), COLUMN( data_scaledImpacts[[#Headers],[outputRowID]] ) - doc_tablesList[[#This Row],[id_colIndex]] + 1 ) -> 2, 9 | N6: Table with temperature-binned, scaled impacts
B7: =ROW( doc_tablesList[[#This Row],[ID]] ) - ROW(doc_tablesList[[#Headers],[ID]] ) -> 4 | C7: co_defaultScenario | D7: 1 | E7: defaultScenario | F7: ="row_id" -> row_id | G7: {=INDEX( ROW( INDIRECT( _xlfn.TEXTJOIN( "", , doc_tablesList[[#This Row],[Table Name]], "[[#Headers],[", doc_tablesList[[#This Row],[ID_columnName]], "]]" ) ) ), 1 )} -> 3 | H7: =MAX( INDIRECT( _xlfn.TEXTJOIN( "", , doc_tablesList[[#This Row],[Table Name]], "[", doc_tablesList[[#This Row],[ID_columnName]], "]" ) ) ) -> 17 | I7: =doc_tablesList[[#This Row],[Number of Data Rows]] + doc_tablesList[[#This Row],[Header Row]] -> 20 | J7: {=INDEX( COLUMN( INDIRECT( doc_tablesList[[#This Row],[Table Name]] & "[" & doc_tablesList[[#This Row],[ID_columnName]] & "]" ) ), 1 )} -> 2 | K7: {=MAX( COLUMN( INDIRECT( doc_tablesList[[#This Row],[Table Name]] ) ) )} -> 11 | L7: =doc_tablesList[[#This Row],[last_colIndex]] - doc_tablesList[[#This Row],[id_colIndex]] + 1 -> 10 | N7: Table with default values for CONUS temperatures, GDP, and regional population
B8: =ROW( doc_tablesList[[#This Row],[ID]] ) - ROW(doc_tablesList[[#Headers],[ID]] ) -> 5 | C8: co_defaultTemps | D8: 1 | E8: defaultScenario | F8: ="row_id" -> row_id | G8: {=INDEX( ROW( INDIRECT( _xlfn.TEXTJOIN( "", , doc_tablesList[[#This Row],[Table Name]], "[[#Headers],[", doc_tablesList[[#This Row],[ID_columnName]], "]]" ) ) ), 1 )} -> 22 | H8: =MAX( INDIRECT( _xlfn.TEXTJOIN( "", , doc_tablesList[[#This Row],[Table Name]], "[", doc_tablesList[[#This Row],[ID_columnName]], "]" ) ) ) -> 91 | I8: =doc_tablesList[[#This Row],[Number of Data Rows]] + doc_tablesList[[#This Row],[Header Row]] -> 113 | J8: {=INDEX( COLUMN( INDIRECT( doc_tablesList[[#This Row],[Table Name]] & "[" & doc_tablesList[[#This Row],[ID_columnName]] & "]" ) ), 1 )} -> 2 | K8: {=MAX( COLUMN( INDIRECT( doc_tablesList[[#This Row],[Table Name]] ) ) )} -> 4 | L8: =doc_tablesList[[#This Row],[last_colIndex]] - doc_tablesList[[#This Row],[id_colIndex]] + 1 -> 3 | N8: Table with default temperatures
B9: =ROW( doc_tablesList[[#This Row],[ID]] ) - ROW(doc_tablesList[[#Headers],[ID]] ) -> 6 | C9: co_variants | D9: 1 | E9: controlTables | F9: ="row_id" -> row_id | G9: {=INDEX( ROW( INDIRECT( _xlfn.TEXTJOIN( "", , doc_tablesList[[#This Row],[Table Name]], "[[#Headers],[", doc_tablesList[[#This Row],[ID_columnName]], "]]" ) ) ), 1 )} -> 80 | H9: =MAX( INDIRECT( _xlfn.TEXTJOIN( "", , doc_tablesList[[#This Row],[Table Name]], "[", doc_tablesList[[#This Row],[ID_columnName]], "]" ) ) ) -> 42 | I9: =doc_tablesList[[#This Row],[Number of Data Rows]] + doc_tablesList[[#This Row],[Header Row]] -> 122 | J9: {=INDEX( COLUMN( INDIRECT( doc_tablesList[[#This Row],[Table Name]] & "[" & doc_tablesList[[#This Row],[ID_columnName]] & "]" ) ), 1 )} -> 2 | K9: {=MAX( COLUMN( INDIRECT( doc_tablesList[[#This Row],[Table Name]] ) ) )} -> 11 | L9: =doc_tablesList[[#This Row],[last_colIndex]] - doc_tablesList[[#This Row],[id_colIndex]] + 1 -> 10 | M9: =_xlfn.TEXTJOIN( ", ", , COLUMN( co_variants[[#Headers],[check_data]] ) - doc_tablesList[[#This Row],[id_colIndex]] + 1, COLUMN( co_variants[[#Headers],[subImpacts]] ) - doc_tablesList[[#This Row],[id_colIndex]] + 1 ) -> 9, 10 | N9: Table with variant information
B10: =ROW( doc_tablesList[[#This Row],[ID]] ) - ROW(doc_tablesList[[#Headers],[ID]] ) -> 7 | C10: co_impactYears | D10: 1 | E10: controlTables | F10: ="row_id" -> row_id | G10: {=INDEX( ROW( INDIRECT( _xlfn.TEXTJOIN( "", , doc_tablesList[[#This Row],[Table Name]], "[[#Headers],[", doc_tablesList[[#This Row],[ID_columnName]], "]]" ) ) ), 1 )} -> 49 | H10: =MAX( INDIRECT( _xlfn.TEXTJOIN( "", , doc_tablesList[[#This Row],[Table Name]], "[", doc_tablesList[[#This Row],[ID_columnName]], "]" ) ) ) -> 25 | I10: =doc_tablesList[[#This Row],[Number of Data Rows]] + doc_tablesList[[#This Row],[Header Row]] -> 74 | J10: {=INDEX( COLUMN( INDIRECT( doc_tablesList[[#This Row],[Table Name]] & "[" & doc_tablesList[[#This Row],[ID_columnName]] & "]" ) ), 1 )} -> 2 | K10: {=MAX( COLUMN( INDIRECT( doc_tablesList[[#This Row],[Table Name]] ) ) )} -> 6 | L10: =doc_tablesList[[#This Row],[last_colIndex]] - doc_tablesList[[#This Row],[id_colIndex]] + 1 -> 5 | N10: Table with impact year information
B11: =ROW( doc_tablesList[[#This Row],[ID]] ) - ROW(doc_tablesList[[#Headers],[ID]] ) -> 8 | C11: co_impactTypes | D11: 1 | E11: controlTables | F11: ="row_id" -> row_id | G11: {=INDEX( ROW( INDIRECT( _xlfn.TEXTJOIN( "", , doc_tablesList[[#This Row],[Table Name]], "[[#Headers],[", doc_tablesList[[#This Row],[ID_columnName]], "]]" ) ) ), 1 )} -> 126 | H11: =MAX( INDIRECT( _xlfn.TEXTJOIN( "", , doc_tablesList[[#This Row],[Table Name]], "[", doc_tablesList[[#This Row],[ID_columnName]], "]" ) ) ) -> 43 | I11: =doc_tablesList[[#This Row],[Number of Data Rows]] + doc_tablesList[[#This Row],[Header Row]] -> 169 | J11: {=INDEX( COLUMN( INDIRECT( doc_tablesList[[#This Row],[Table Name]] & "[" & doc_tablesList[[#This Row],[ID_columnName]] & "]" ) ), 1 )} -> 2 | K11: {=MAX( COLUMN( INDIRECT( doc_tablesList[[#This Row],[Table Name]] ) ) )} -> 21 | L11: =doc_tablesList[[#This Row],[last_colIndex]] - doc_tablesList[[#This Row],[id_colIndex]] + 1 -> 20 | M11: {=_xlfn.TEXTJOIN( ", ", , COLUMN( co_impactTypes[[#Headers],[check_data]:[check_physScalar]] ) - doc_tablesList[[#This Row],[id_colIndex]] + 1 )} -> 17, 18, 19, 20 | N11: Table with impact type information
B12: =ROW( doc_tablesList[[#This Row],[ID]] ) - ROW(doc_tablesList[[#Headers],[ID]] ) -> 9 | C12: co_scalarInfo | D12: 1 | E12: controlTables | F12: ="row_id" -> row_id | G12: {=INDEX( ROW( INDIRECT( _xlfn.TEXTJOIN( "", , doc_tablesList[[#This Row],[Table Name]], "[[#Headers],[", doc_tablesList[[#This Row],[ID_columnName]], "]]" ) ) ), 1 )} -> 174 | H12: =MAX( INDIRECT( _xlfn.TEXTJOIN( "", , doc_tablesList[[#This Row],[Table Name]], "[", doc_tablesList[[#This Row],[ID_columnName]], "]" ) ) ) -> 31 | I12: =doc_tablesList[[#This Row],[Number of Data Rows]] + doc_tablesList[[#This Row],[Header Row]] -> 205 | J12: {=INDEX( COLUMN( INDIRECT( doc_tablesList[[#This Row],[Table Name]] & "[" & doc_tablesList[[#This Row],[ID_columnName]] & "]" ) ), 1 )} -> 2 | K12: {=MAX( COLUMN( INDIRECT( doc_tablesList[[#This Row],[Table Name]] ) ) )} -> 11 | L12: =doc_tablesList[[#This Row],[last_colIndex]] - doc_tablesList[[#This Row],[id_colIndex]] + 1 -> 10 | M12: {=_xlfn.TEXTJOIN( ", ", , COLUMN( co_scalarInfo[[#Headers],[dataType]:[scalar_rows]]) - doc_tablesList[[#This Row],[id_colIndex]] + 1 )} -> 8, 9, 10 | N12: Table with information about scalars
B13: =ROW( doc_tablesList[[#This Row],[ID]] ) - ROW(doc_tablesList[[#Headers],[ID]] ) -> 10 | C13: co_regions | D13: 1 | E13: controlTables | F13: ="row_id" -> row_id | G13: {=INDEX( ROW( INDIRECT( _xlfn.TEXTJOIN( "", , doc_tablesList[[#This Row],[Table Name]], "[[#Headers],[", doc_tablesList[[#This Row],[ID_columnName]], "]]" ) ) ), 1 )} -> 252 | H13: =MAX( INDIRECT( _xlfn.TEXTJOIN( "", , doc_tablesList[[#This Row],[Table Name]], "[", doc_tablesList[[#This Row],[ID_columnName]], "]" ) ) ) -> 7 | I13: =doc_tablesList[[#This Row],[Number of Data Rows]] + doc_tablesList[[#This Row],[Header Row]] -> 259 | J13: {=INDEX( COLUMN( INDIRECT( doc_tablesList[[#This Row],[Table Name]] & "[" & doc_tablesList[[#This Row],[ID_columnName]] & "]" ) ), 1 )} -> 2 | K13: {=MAX( COLUMN( INDIRECT( doc_tablesList[[#This Row],[Table Name]] ) ) )} -> 5 | L13: =doc_tablesList[[#This Row],[last_colIndex]] - doc_tablesList[[#This Row],[id_colIndex]] + 1 -> 4 | N13: Table with information about regions
B14: =ROW( doc_tablesList[[#This Row],[ID]] ) - ROW(doc_tablesList[[#Headers],[ID]] ) -> 11 | C14: co_models | D14: 1 | E14: controlTables | F14: ="row_id" -> row_id | G14: {=INDEX( ROW( INDIRECT( _xlfn.TEXTJOIN( "", , doc_tablesList[[#This Row],[Table Name]], "[[#Headers],[", doc_tablesList[[#This Row],[ID_columnName]], "]]" ) ) ), 1 )} -> 233 | H14: =MAX( INDIRECT( _xlfn.TEXTJOIN( "", , doc_tablesList[[#This Row],[Table Name]], "[", doc_tablesList[[#This Row],[ID_columnName]], "]" ) ) ) -> 14 | I14: =doc_tablesList[[#This Row],[Number of Data Rows]] + doc_tablesList[[#This Row],[Header Row]] -> 247 | J14: {=INDEX( COLUMN( INDIRECT( doc_tablesList[[#This Row],[Table Name]] & "[" & doc_tablesList[[#This Row],[ID_columnName]] & "]" ) ), 1 )} -> 2 | K14: {=MAX( COLUMN( INDIRECT( doc_tablesList[[#This Row],[Table Name]] ) ) )} -> 8 | L14: =doc_tablesList[[#This Row],[last_colIndex]] - doc_tablesList[[#This Row],[id_colIndex]] + 1 -> 7 | N14: Table with information about GCMs
B15: =ROW( doc_tablesList[[#This Row],[ID]] ) - ROW(doc_tablesList[[#Headers],[ID]] ) -> 12 | C15: co_econMultipliers | D15: 1 | E15: controlTables | F15: ="row_id" -> row_id | G15: {=INDEX( ROW( INDIRECT( _xlfn.TEXTJOIN( "", , doc_tablesList[[#This Row],[Table Name]], "[[#Headers],[", doc_tablesList[[#This Row],[ID_columnName]], "]]" ) ) ), 1 )} -> 210 | H15: =MAX( INDIRECT( _xlfn.TEXTJOIN( "", , doc_tablesList[[#This Row],[Table Name]], "[", doc_tablesList[[#This Row],[ID_columnName]], "]" ) ) ) -> 3 | I15: =doc_tablesList[[#This Row],[Number of Data Rows]] + doc_tablesList[[#This Row],[Header Row]] -> 213 | J15: {=INDEX( COLUMN( INDIRECT( doc_tablesList[[#This Row],[Table Name]] & "[" & doc_tablesList[[#This Row],[ID_columnName]] & "]" ) ), 1 )} -> 2 | K15: {=MAX( COLUMN( INDIRECT( doc_tablesList[[#This Row],[Table Name]] ) ) )} -> 5 | L15: =doc_tablesList[[#This Row],[last_colIndex]] - doc_tablesList[[#This Row],[id_colIndex]] + 1 -> 4 | M15: =_xlfn.TEXTJOIN( ", ", , COLUMN( co_econMultipliers[[#Headers],[valueYear]] ) - doc_tablesList[[#This Row],[id_colIndex]] + 1 ) -> 4 | N15: Table with information about economic multipliers
B16: =ROW( doc_tablesList[[#This Row],[ID]] ) - ROW(doc_tablesList[[#Headers],[ID]] ) -> 13 | C16: co_modelTypes | D16: 1 | E16: controlTables | F16: ="row_id" -> row_id | G16: {=INDEX( ROW( INDIRECT( _xlfn.TEXTJOIN( "", , doc_tablesList[[#This Row],[Table Name]], "[[#Headers],[", doc_tablesList[[#This Row],[ID_columnName]], "]]" ) ) ), 1 )} -> 226 | H16: =MAX( INDIRECT( _xlfn.TEXTJOIN( "", , doc_tablesList[[#This Row],[Table Name]], "[", doc_tablesList[[#This Row],[ID_columnName]], "]" ) ) ) -> 2 | I16: =doc_tablesList[[#This Row],[Number of Data Rows]] + doc_tablesList[[#This Row],[Header Row]] -> 228 | J16: {=INDEX( COLUMN( INDIRECT( doc_tablesList[[#This Row],[Table Name]] & "[" & doc_tablesList[[#This Row],[ID_columnName]] & "]" ) ), 1 )} -> 2 | K16: {=MAX( COLUMN( INDIRECT( doc_tablesList[[#This Row],[Table Name]] ) ) )} -> 14 | L16: =doc_tablesList[[#This Row],[last_colIndex]] - doc_tablesList[[#This Row],[id_colIndex]] + 1 -> 13 | M16: {=_xlfn.TEXTJOIN( ", ", , COLUMN( co_modelTypes[[#Headers],[Number of levels]:[Number of models]] ) - doc_tablesList[[#This Row],[id_colIndex]] + 1 )} -> 12, 13 | N16: Table with information about model types (GCM vs SLR)
B17: =ROW( doc_tablesList[[#This Row],[ID]] ) - ROW(doc_tablesList[[#Headers],[ID]] ) -> 14 | C17: co_inputScenarioInfo | D17: 1 | E17: controlTables | F17: ="row_id" -> row_id | G17: {=INDEX( ROW( INDIRECT( _xlfn.TEXTJOIN( "", , doc_tablesList[[#This Row],[Table Name]], "[[#Headers],[", doc_tablesList[[#This Row],[ID_columnName]], "]]" ) ) ), 1 )} -> 264 | H17: =MAX( INDIRECT( _xlfn.TEXTJOIN( "", , doc_tablesList[[#This Row],[Table Name]], "[", doc_tablesList[[#This Row],[ID_columnName]], "]" ) ) ) -> 4 | I17: =doc_tablesList[[#This Row],[Number of Data Rows]] + doc_tablesList[[#This Row],[Header Row]] -> 268 | J17: {=INDEX( COLUMN( INDIRECT( doc_tablesList[[#This Row],[Table Name]] & "[" & doc_tablesList[[#This Row],[ID_columnName]] & "]" ) ), 1 )} -> 2 | K17: {=MAX( COLUMN( INDIRECT( doc_tablesList[[#This Row],[Table Name]] ) ) )} -> 12 | L17: =doc_tablesList[[#This Row],[last_colIndex]] - doc_tablesList[[#This Row],[id_colIndex]] + 1 -> 11 | N17: Table with information about input scenarios
B18: =ROW( doc_tablesList[[#This Row],[ID]] ) - ROW(doc_tablesList[[#Headers],[ID]] ) -> 15 | C18: slr_cm | D18: 1 | E18: slr_cm | F18: ="row_id" -> row_id | G18: {=INDEX( ROW( INDIRECT( _xlfn.TEXTJOIN( "", , doc_tablesList[[#This Row],[Table Name]], "[[#Headers],[", doc_tablesList[[#This Row],[ID_columnName]], "]]" ) ) ), 1 )} -> 1 | H18: =MAX( INDIRECT( _xlfn.TEXTJOIN( "", , doc_tablesList[[#This Row],[Table Name]], "[", doc_tablesList[[#This Row],[ID_columnName]], "]" ) ) ) -> 101 | I18: =doc_tablesList[[#This Row],[Number of Data Rows]] + doc_tablesList[[#This Row],[Header Row]] -> 102 | J18: {=INDEX( COLUMN( INDIRECT( doc_tablesList[[#This Row],[Table Name]] & "[" & doc_tablesList[[#This Row],[ID_columnName]] & "]" ) ), 1 )} -> 1 | K18: {=MAX( COLUMN( INDIRECT( doc_tablesList[[#This Row],[Table Name]] ) ) )} -> 9 | L18: =doc_tablesList[[#This Row],[last_colIndex]] - doc_tablesList[[#This Row],[id_colIndex]] + 1 -> 9 | N18: Table with heights in cm of SLR scenarios
B19: =ROW( doc_tablesList[[#This Row],[ID]] ) - ROW(doc_tablesList[[#Headers],[ID]] ) -> 16 | C19: slrImpacts | D19: 1 | E19: slrImpacts | F19: ="row_id" -> row_id | G19: {=INDEX( ROW( INDIRECT( _xlfn.TEXTJOIN( "", , doc_tablesList[[#This Row],[Table Name]], "[[#Headers],[", doc_tablesList[[#This Row],[ID_columnName]], "]]" ) ) ), 1 )} -> 1 | H19: =MAX( INDIRECT( _xlfn.TEXTJOIN( "", , doc_tablesList[[#This Row],[Table Name]], "[", doc_tablesList[[#This Row],[ID_columnName]], "]" ) ) ) -> 606 | I19: =doc_tablesList[[#This Row],[Number of Data Rows]] + doc_tablesList[[#This Row],[Header Row]] -> 607 | J19: {=INDEX( COLUMN( INDIRECT( doc_tablesList[[#This Row],[Table Name]] & "[" & doc_tablesList[[#This Row],[ID_columnName]] & "]" ) ), 1 )} -> 1 | K19: {=MAX( COLUMN( INDIRECT( doc_tablesList[[#This Row],[Table Name]] ) ) )} -> 48 | L19: =doc_tablesList[[#This Row],[last_colIndex]] - doc_tablesList[[#This Row],[id_colIndex]] + 1 -> 48 | N19: Table with SLR scaled impacts
B20: =ROW( doc_tablesList[[#This Row],[ID]] ) - ROW(doc_tablesList[[#Headers],[ID]] ) -> 17 | C20: testDev | D20: 1 | E20: testDev | F20: ="row_id" -> row_id | G20: {=INDEX( ROW( INDIRECT( _xlfn.TEXTJOIN( "", , doc_tablesList[[#This Row],[Table Name]], "[[#Headers],[", doc_tablesList[[#This Row],[ID_columnName]], "]]" ) ) ), 1 )} -> 3 | H20: =MAX( INDIRECT( _xlfn.TEXTJOIN( "", , doc_tablesList[[#This Row],[Table Name]], "[", doc_tablesList[[#This Row],[ID_columnName]], "]" ) ) ) -> 25 | I20: =doc_tablesList[[#This Row],[Number of Data Rows]] + doc_tablesList[[#This Row],[Header Row]] -> 28 | J20: {=INDEX( COLUMN( INDIRECT( doc_tablesList[[#This Row],[Table Name]] & "[" & doc_tablesList[[#This Row],[ID_columnName]] & "]" ) ), 1 )} -> 2 | K20: {=MAX( COLUMN( INDIRECT( doc_tablesList[[#This Row],[Table Name]] ) ) )} -> 5 | L20: =doc_tablesList[[#This Row],[last_colIndex]] - doc_tablesList[[#This Row],[id_colIndex]] + 1 -> 4 | N20: Table with information about tests
B21: =ROW( doc_tablesList[[#This Row],[ID]] ) - ROW(doc_tablesList[[#Headers],[ID]] ) -> 18 | C21: co_states | D21: 1 | E21: controlTables | F21: ="row_id" -> row_id | G21: {=INDEX( ROW( INDIRECT( _xlfn.TEXTJOIN( "", , doc_tablesList[[#This Row],[Table Name]], "[[#Headers],[", doc_tablesList[[#This Row],[ID_columnName]], "]]" ) ) ), 1 )} -> 273 | H21: =MAX( INDIRECT( _xlfn.TEXTJOIN( "", , doc_tablesList[[#This Row],[Table Name]], "[", doc_tablesList[[#This Row],[ID_columnName]], "]" ) ) ) -> 49 | I21: =doc_tablesList[[#This Row],[Number of Data Rows]] + doc_tablesList[[#This Row],[Header Row]] -> 322 | J21: {=INDEX( COLUMN( INDIRECT( doc_tablesList[[#This Row],[Table Name]] & "[" & doc_tablesList[[#This Row],[ID_columnName]] & "]" ) ), 1 )} -> 2 | K21: {=MAX( COLUMN( INDIRECT( doc_tablesList[[#This Row],[Table Name]] ) ) )} -> 6 | L21: =doc_tablesList[[#This Row],[last_colIndex]] - doc_tablesList[[#This Row],[id_colIndex]] + 1 -> 5 | N21: Table with information about states
B22: =ROW( doc_tablesList[[#This Row],[ID]] ) - ROW(doc_tablesList[[#Headers],[ID]] ) -> 19 | C22: co_slrScalars | D22: 1 | E22: controlTables | F22: row_id | G22: {=INDEX( ROW( INDIRECT( _xlfn.TEXTJOIN( "", , doc_tablesList[[#This Row],[Table Name]], "[[#Headers],[", doc_tablesList[[#This Row],[ID_columnName]], "]]" ) ) ), 1 )} -> 328 | H22: =MAX( INDIRECT( _xlfn.TEXTJOIN( "", , doc_tablesList[[#This Row],[Table Name]], "[", doc_tablesList[[#This Row],[ID_columnName]], "]" ) ) ) -> 2 | I22: =doc_tablesList[[#This Row],[Number of Data Rows]] + doc_tablesList[[#This Row],[Header Row]] -> 330 | J22: {=INDEX( COLUMN( INDIRECT( doc_tablesList[[#This Row],[Table Name]] & "[" & doc_tablesList[[#This Row],[ID_columnName]] & "]" ) ), 1 )} -> 2 | K22: {=MAX( COLUMN( INDIRECT( doc_tablesList[[#This Row],[Table Name]] ) ) )} -> 10 | L22: =doc_tablesList[[#This Row],[last_colIndex]] - doc_tablesList[[#This Row],[id_colIndex]] + 1 -> 9 | N22: Table with info about SLR scalars past 2090

Sheet testDev
A1: tableNames | B1: This worksheet contains the names of data tables to import into R
B3: row_id | C3: Table Name | D3: Changes if new sector added | E3: New sector changes
B4: =ROW( testDev[[#This Row],[row_id]] ) - ROW(testDev[[#Headers],[row_id]] ) -> 1 | C4: co_sectors | D4: Yes | E4: New rows for each new sector
B5: =ROW( testDev[[#This Row],[row_id]] ) - ROW(testDev[[#Headers],[row_id]] ) -> 2 | C5: scalarDataframe | D5: Maybe | E5: New rows if a new sector uses a new type of scalar. Can check if the new `co_impactTypes` has any scalars that aren't in the reference `co_scalarInfo` and, if so, we expect the new `scalarDataframe` to have new rows. Each new scalar will have at least one new row. Minimum number of new rows depends on the attributes of the scalar (e.g., whether national or regional, etc.)
B6: =ROW( testDev[[#This Row],[row_id]] ) - ROW(testDev[[#Headers],[row_id]] ) -> 3 | C6: data_scaledImpacts | D6: Yes | E6: New rows associated with the new sector if a sector is temperature-driven. Can check info from `co_sectors` to see if sector is temperature-driven (in which case, scaled impacts added to `data_scaledImpacts`) or SLR-driven (in which case, scaled impacts added to `slrImpacts`). Number of new rows will equal: Number of variants * Number of impact types * Number of impact years * Number of GCM models * Number of degrees (6)
B7: =ROW( testDev[[#This Row],[row_id]] ) - ROW(testDev[[#Headers],[row_id]] ) -> 4 | C7: co_defaultScenario | D7: No | E7: No changes expected for a new sector
B8: =ROW( testDev[[#This Row],[row_id]] ) - ROW(testDev[[#Headers],[row_id]] ) -> 5 | C8: co_defaultTemps | D8: No | E8: No changes expected for a new sector
B9: =ROW( testDev[[#This Row],[row_id]] ) - ROW(testDev[[#Headers],[row_id]] ) -> 6 | C9: co_variants | D9: Yes | E9: New rows for each new sector for each variant type (a sector without a named variant will still add a new row in this table)
B10: =ROW( testDev[[#This Row],[row_id]] ) - ROW(testDev[[#Headers],[row_id]] ) -> 7 | C10: co_impactYears | D10: Yes | E10: New rows for each new sector (a sector without specific impact years will still add a new row in this table)
B11: =ROW( testDev[[#This Row],[row_id]] ) - ROW(testDev[[#Headers],[row_id]] ) -> 8 | C11: co_impactTypes | D11: Yes | E11: New rows for each new sector, impact type, and variant (a sector without specific impact years will still add least one new row in this table)
B12: =ROW( testDev[[#This Row],[row_id]] ) - ROW(testDev[[#Headers],[row_id]] ) -> 9 | C12: co_scalarInfo | D12: Maybe | E12: New rows if a new sector uses a new type of scalar. Can check if the new `co_impactTypes` has any scalars that aren't in the reference `co_scalarInfo` and, if so, we expect the new `co_scalarInfo` to have new rows (number of new rows = number of new scalars).
B13: =ROW( testDev[[#This Row],[row_id]] ) - ROW(testDev[[#Headers],[row_id]] ) -> 10 | C13: co_regions | D13: No | E13: No changes expected for a new sector
B14: =ROW( testDev[[#This Row],[row_id]] ) - ROW(testDev[[#Headers],[row_id]] ) -> 11 | C14: co_models | D14: Maybe | E14: Sometimes new sectors have new models. We could specific the new model(s) at the time we run the "new sector" test
B15: =ROW( testDev[[#This Row],[row_id]] ) - ROW(testDev[[#Headers],[row_id]] ) -> 12 | C15: co_econMultipliers | D15: No | E15: In theory, yes, but generally, no. We haven't added a new econMultiplier in ages. So let's assume it is no for the purposes of developing the test and revisit this if there is a special case
... B28: =ROW( testDev[[#This Row],[row_id]] ) - ROW(testDev[[#Headers],[row_id]] ) -> 25 | C28: df_results0 | D28: Yes | E28: New rows for each new sector, impact type, variant, region, GCM model (including new models), etc. Will also add rows for any new GCM model for all other combinations

Sheet controlTables
B1: Table of Contents
C2: =OFFSET( INDIRECT( ADDRESS( ROW( co_sectors[[#Headers],[row_id]] ), COLUMN( co_sectors[[#Headers],[row_id]] ), , , ) ), -2, , 1, 1 ) -> Sectors Table | D2: Overview of sectors included in the model
C3: =OFFSET( INDIRECT( ADDRESS( ROW( co_impactYears[[#Headers],[row_id]] ), COLUMN( co_impactYears[[#Headers],[row_id]] ), , , ) ), -2, , 1, 1 ) -> Impact Year Estimates | D3: Overview of impact estimate years associated with each sector
C4: =OFFSET( INDIRECT( ADDRESS( ROW( co_variants[[#Headers],[row_id]] ), COLUMN( co_variants[[#Headers],[row_id]] ), , , ) ), -4, , 1, 1 ) -> Variants Table | D4: Overview of sector-adaptation combinations
C5: =OFFSET( INDIRECT( ADDRESS( ROW( co_impactTypes[[#Headers],[row_id]] ), COLUMN( co_impactTypes[[#Headers],[row_id]] ), , , ) ), -2, , 1, 1 ) -> Impact Types | D5: Overview of sector-impact type combinations
C6: =OFFSET( INDIRECT( ADDRESS( ROW( co_scalarInfo[[#Headers],[row_id]] ), COLUMN( co_scalarInfo[[#Headers],[row_id]] ), , , ) ), -2, , 1, 1 ) -> Scalar Information | D6: Overview of physical scalars, physical adjustments, damage adjustments, economic scalars, and economic multipliers.
C7: =OFFSET( INDIRECT( ADDRESS( ROW( co_econMultipliers[[#Headers],[row_id]] ), COLUMN( co_econMultipliers[[#Headers],[row_id]] ), , , ) ), -2, , 1, 1 ) -> Economic Multipliers | D7: Overview of economic multipliers
C8: =OFFSET( INDIRECT( ADDRESS( ROW( co_constants[[#Headers],[row_id]] ), COLUMN( co_constants[[#Headers],[row_id]] ), , , ) ), -2, , 1, 1 ) -> Constants | D8: Named constants
C9: =OFFSET( INDIRECT( ADDRESS( ROW( co_modelTypes[[#Headers],[row_id]] ), COLUMN( co_modelTypes[[#Headers],[row_id]] ), , , ) ), -2, , 1, 1 ) -> Model Types | D9: Temperature and SLR-binning model types
C10: =OFFSET( INDIRECT( ADDRESS( ROW( co_models[[#Headers],[row_id]] ), COLUMN( co_models[[#Headers],[row_id]] ), , , ) ), -2, , 1, 1 ) -> Binning Models | D10: Temperature and SLR-binning models (GCMs and SLR scenarios)
C11: =OFFSET( INDIRECT( ADDRESS( ROW( co_regions[[#Headers],[row_id]] ), COLUMN( co_regions[[#Headers],[row_id]] ), , , ) ), -2, , 1, 1 ) -> Regions | D11: List of regions
C12: =OFFSET( INDIRECT( ADDRESS( ROW( co_inputScenarioInfo[[#Headers],[row_id]] ), COLUMN( co_inputScenarioInfo[[#Headers],[row_id]] ), , , ) ), -2, , 1, 1 ) -> Input Scenario Information | D12: Information about input scenarios
C13: =OFFSET( INDIRECT( ADDRESS( ROW( co_states[[#Headers],[row_id]] ), COLUMN( co_states[[#Headers],[row_id]] ), , , ) ), -2, , 1, 1 ) -> States | D13: List of states
C14: =OFFSET( INDIRECT( ADDRESS( ROW( co_slrScalars[[#Headers],[row_id]] ), COLUMN( co_slrScalars[[#Headers],[row_id]] ), , , ) ), -3, , 1, 1 ) -> SLR Scalars | D14: Info on SLR scalars past 2090
C16: Color Legend | D16: Hard-coded value/included in model | E16: Calculated value | F16: Column used for record-keeping of data checks
B18: Sectors Table
B20: row_id | C20: sector_id | D20: sector_label | E20: include | F20: modelType | G20: byState | H20: interpolateEstimateYears | I20: variants | J20: impactYears | K20: impactTypes | L20: Number of variants | M20: Number of impact types | N20: Number of impact years | O20: Number of models | P20: Number of levels | Q20: Number of scaled impact rows per region
B21: =ROW( co_sectors[[#This Row],[row_id]] ) - ROW( co_sectors[[#Headers],[row_id]] ) -> 1 | C21: AirQuality | D21: Air Quality | E21: 1 | F21: gcm | G21: 1 | H21: {=IF( AND( SUMPRODUCT( co_impactYears[2010], --( co_sectors[[#This Row],[sector_id]] = co_impactYears[sector_id] ) ) > 1, SUMPRODUCT( co_impactYears[2090], --( co_sectors[[#This Row],[sector_id]] = co_impactYears[sector_id] ) ) > 1 ), 1, 0 )} -> 0 | I21: {=_xlfn.TEXTJOIN( ", ", 1, IF( OFFSET( INDIRECT( ADDRESS( ROW( co_variants[[#Headers],[row_id]] ), COLUMN( co_variants[[#Headers],[sector_id]] ), , , "controlTables" ) ), 1, 0, MAX( co_variants[row_id] ), 1 ) = co_sectors[[#This Row],[sector_id]], co_variants[variant_label], "" ) )} -> 2011 Emissions, 2040 Emissions | J21: =_xlfn.TEXTJOIN( ", ", 1, OFFSET( INDIRECT( ADDRESS( ROW( INDEX( co_impactYears[sector_id], MATCH( co_sectors[[#This Row],[sector_id]], co_impactYears[sector_id], 0 ) ) ), COLUMN( co_impactYears[[#Headers],[sector_id]] ), , , "controlTables" ) ), 0, 1, 1, 4 ) ) -> N/A | K21: {=_xlfn.TEXTJOIN( ", ", 1, IF( OFFSET( INDIRECT( ADDRESS( ROW( co_impactTypes[[#Headers],[row_id]] ), COLUMN( co_impactTypes[[#Headers],[sector_id]] ), , , "controlTables" ) ), 1, 0, MAX( co_impactTypes[row_id] ), 1 ) = co_sectors[[#This Row],[sector_id]], co_impactTypes[impactType_label], "" ) )} -> Ozone, PM2.5 | L21: {=SUMPRODUCT( --( co_sectors[[#This Row],[sector_id]] = co_variants[sector_id] ) )} -> 2 | M21: {=SUMPRODUCT( --( co_sectors[[#This Row],[sector_id]] = co_impactTypes[sector_id] ) )} -> 2 | N21: {=IF( INDEX( co_impactYears[N/A], MATCH( 1, --( co_sectors[[#This Row],[sector_id]] = co_impactYears[sector_id] ), 0 ) ) = "N/A", 1, 2 )} -> 1 | O21: {=INDEX( co_modelTypes[Number of models], MATCH( 1, --( co_sectors[[#This Row],[modelType]] = co_modelTypes[modelType_id] ), 0 ) ) + IF( co_sectors[[#This Row],[modelType]] = "gcm", 1, 0 )} -> 9 | P21: {=INDEX( co_modelTypes[Number of levels], MATCH( 1, --( co_sectors[[#This Row],[modelType]] = co_modelTypes[modelType_id] ), 0 ) )} -> 7 | Q21: =PRODUCT( co_sectors[[#This Row],[Number of variants]:[Number of levels]] ) -> 252
B22: =ROW( co_sectors[[#This Row],[row_id]] ) - ROW( co_sectors[[#Headers],[row_id]] ) -> 2 | C22: AsphaltRoads | D22: Asphalt Roads | E22: 1 | F22: gcm | G22: 1 | H22: {=IF( AND( SUMPRODUCT( co_impactYears[2010], --( co_sectors[[#This Row],[sector_id]] = co_impactYears[sector_id] ) ) > 1, SUMPRODUCT( co_impactYears[2090], --( co_sectors[[#This Row],[sector_id]] = co_impactYears[sector_id] ) ) > 1 ), 1, 0 )} -> 0 | I22: {=_xlfn.TEXTJOIN( ", ", 1, IF( OFFSET( INDIRECT( ADDRESS( ROW( co_variants[[#Headers],[row_id]] ), COLUMN( co_variants[[#Headers],[sector_id]] ), , , "controlTables" ) ), 1, 0, MAX( co_variants[row_id] ), 1 ) = co_sectors[[#This Row],[sector_id]], co_variants[variant_label], "" ) )} -> N/A | J22: =_xlfn.TEXTJOIN( ", ", 1, OFFSET( INDIRECT( ADDRESS( ROW( INDEX( co_impactYears[sector_id], MATCH( co_sectors[[#This Row],[sector_id]], co_impactYears[sector_id], 0 ) ) ), COLUMN( co_impactYears[[#Headers],[sector_id]] ), , , "controlTables" ) ), 0, 1, 1, 4 ) ) -> N/A | K22: {=_xlfn.TEXTJOIN( ", ", 1, IF( OFFSET( INDIRECT( ADDRESS( ROW( co_impactTypes[[#Headers],[row_id]] ), COLUMN( co_impactTypes[[#Headers],[sector_id]] ), , , "controlTables" ) ), 1, 0, MAX( co_impactTypes[row_id] ), 1 ) = co_sectors[[#This Row],[sector_id]], co_impactTypes[impactType_label], "" ) )} -> N/A | L22: {=SUMPRODUCT( --( co_sectors[[#This Row],[sector_id]] = co_variants[sector_id] ) )} -> 1 | M22: {=SUMPRODUCT( --( co_sectors[[#This Row],[sector_id]] = co_impactTypes[sector_id] ) )} -> 1 | N22: {=IF( INDEX( co_impactYears[N/A], MATCH( 1, --( co_sectors[[#This Row],[sector_id]] = co_impactYears[sector_id] ), 0 ) ) = "N/A", 1, 2 )} -> 1 | O22: {=INDEX( co_modelTypes[Number of models], MATCH( 1, --( co_sectors[[#This Row],[modelType]] = co_modelTypes[modelType_id] ), 0 ) ) + IF( co_sectors[[#This Row],[modelType]] = "gcm", 1, 0 )} -> 9 | P22: {=INDEX( co_modelTypes[Number of levels], MATCH( 1, --( co_sectors[[#This Row],[modelType]] = co_modelTypes[modelType_id] ), 0 ) )} -> 7 | Q22: =PRODUCT( co_sectors[[#This Row],[Number of variants]:[Number of levels]] ) -> 63
B23: =ROW( co_sectors[[#This Row],[row_id]] ) - ROW( co_sectors[[#Headers],[row_id]] ) -> 3 | C23: ATSExtremeTemp | D23: ATS Extreme Temperature | E23: 1 | F23: gcm | G23: 1 | H23: {=IF( AND( SUMPRODUCT( co_impactYears[2010], --( co_sectors[[#This Row],[sector_id]] = co_impactYears[sector_id] ) ) > 1, SUMPRODUCT( co_impactYears[2090], --( co_sectors[[#This Row],[sector_id]] = co_impactYears[sector_id] ) ) > 1 ), 1, 0 )} -> 0 | I23: {=_xlfn.TEXTJOIN( ", ", 1, IF( OFFSET( INDIRECT( ADDRESS( ROW( co_variants[[#Headers],[row_id]] ), COLUMN( co_variants[[#Headers],[sector_id]] ), , , "controlTables" ) ), 1, 0, MAX( co_variants[row_id] ), 1 ) = co_sectors[[#This Row],[sector_id]], co_variants[variant_label], "" ) )} -> Mean, Low Confidence Interval, High Confidence Interval | J23: =_xlfn.TEXTJOIN( ", ", 1, OFFSET( INDIRECT( ADDRESS( ROW( INDEX( co_impactYears[sector_id], MATCH( co_sectors[[#This Row],[sector_id]], co_impactYears[sector_id], 0 ) ) ), COLUMN( co_impactYears[[#Headers],[sector_id]] ), , , "controlTables" ) ), 0, 1, 1, 4 ) ) -> N/A | K23: {=_xlfn.TEXTJOIN( ", ", 1, IF( OFFSET( INDIRECT( ADDRESS( ROW( co_impactTypes[[#Headers],[row_id]] ), COLUMN( co_impactTypes[[#Headers],[sector_id]] ), , , "controlTables" ) ), 1, 0, MAX( co_impactTypes[row_id] ), 1 ) = co_sectors[[#This Row],[sector_id]], co_impactTypes[impactType_label], "" ) )} -> N/A | L23: {=SUMPRODUCT( --( co_sectors[[#This Row],[sector_id]] = co_variants[sector_id] ) )} -> 3 | M23: {=SUMPRODUCT( --( co_sectors[[#This Row],[sector_id]] = co_impactTypes[sector_id] ) )} -> 1 | N23: {=IF( INDEX( co_impactYears[N/A], MATCH( 1, --( co_sectors[[#This Row],[sector_id]] = co_impactYears[sector_id] ), 0 ) ) = "N/A", 1, 2 )} -> 1 | O23: {=INDEX( co_modelTypes[Number of models], MATCH( 1, --( co_sectors[[#This Row],[modelType]] = co_modelTypes[modelType_id] ), 0 ) ) + IF( co_sectors[[#This Row],[modelType]] = "gcm", 1, 0 )} -> 9 | P23: {=INDEX( co_modelTypes[Number of levels], MATCH( 1, --( co_sectors[[#This Row],[modelType]] = co_modelTypes[modelType_id] ), 0 ) )} -> 7 | Q23: =PRODUCT( co_sectors[[#This Row],[Number of variants]:[Number of levels]] ) -> 189
B24: =ROW( co_sectors[[#This Row],[row_id]] ) - ROW( co_sectors[[#Headers],[row_id]] ) -> 4 | C24: CILAgriculture | D24: CIL Agriculture | E24: 1 | F24: gcm | G24: 0 | H24: {=IF( AND( SUMPRODUCT( co_impactYears[2010], --( co_sectors[[#This Row],[sector_id]] = co_impactYears[sector_id] ) ) > 1, SUMPRODUCT( co_impactYears[2090], --( co_sectors[[#This Row],[sector_id]] = co_impactYears[sector_id] ) ) > 1 ), 1, 0 )} -> 0 | I24: {=_xlfn.TEXTJOIN( ", ", 1, IF( OFFSET( INDIRECT( ADDRESS( ROW( co_variants[[#Headers],[row_id]] ), COLUMN( co_variants[[#Headers],[sector_id]] ), , , "controlTables" ) ), 1, 0, MAX( co_variants[row_id] ), 1 ) = co_sectors[[#This Row],[sector_id]], co_variants[variant_label], "" ) )} -> With CO2 Fertilization, Without CO2 Fertilization | J24: =_xlfn.TEXTJOIN( ", ", 1, OFFSET( INDIRECT( ADDRESS( ROW( INDEX( co_impactYears[sector_id], MATCH( co_sectors[[#This Row],[sector_id]], co_impactYears[sector_id], 0 ) ) ), COLUMN( co_impactYears[[#Headers],[sector_id]] ), , , "controlTables" ) ), 0, 1, 1, 4 ) ) -> N/A | K24: {=_xlfn.TEXTJOIN( ", ", 1, IF( OFFSET( INDIRECT( ADDRESS( ROW( co_impactTypes[[#Headers],[row_id]] ), COLUMN( co_impactTypes[[#Headers],[sector_id]] ), , , "controlTables" ) ), 1, 0, MAX( co_impactTypes[row_id] ), 1 ) = co_sectors[[#This Row],[sector_id]], co_impactTypes[impactType_label], "" ) )} -> Cotton, Maize, Soybean, Wheat | L24: {=SUMPRODUCT( --( co_sectors[[#This Row],[sector_id]] = co_variants[sector_id] ) )} -> 2 | M24: {=SUMPRODUCT( --( co_sectors[[#This Row],[sector_id]] = co_impactTypes[sector_id] ) )} -> 4 | N24: {=IF( INDEX( co_impactYears[N/A], MATCH( 1, --( co_sectors[[#This Row],[sector_id]] = co_impactYears[sector_id] ), 0 ) ) = "N/A", 1, 2 )} -> 1 | O24: {=INDEX( co_modelTypes[Number of models], MATCH( 1, --( co_sectors[[#This Row],[modelType]] = co_modelTypes[modelType_id] ), 0 ) ) + IF( co_sectors[[#This Row],[modelType]] = "gcm", 1, 0 )} -> 9 | P24: {=INDEX( co_modelTypes[Number of levels], MATCH( 1, --( co_sectors[[#This Row],[modelType]] = co_modelTypes[modelType_id] ), 0 ) )} -> 7 | Q24: =PRODUCT( co_sectors[[#This Row],[Number of variants]:[Number of levels]] ) -> 504
B25: =ROW( co_sectors[[#This Row],[row_id]] ) - ROW( co_sectors[[#Headers],[row_id]] ) -> 5 | C25: CILCrime | D25: CIL Crime | E25: 1 | F25: gcm | G25: 0 | H25: {=IF( AND( SUMPRODUCT( co_impactYears[2010], --( co_sectors[[#This Row],[sector_id]] = co_impactYears[sector_id] ) ) > 1, SUMPRODUCT( co_impactYears[2090], --( co_sectors[[#This Row],[sector_id]] = co_impactYears[sector_id] ) ) > 1 ), 1, 0 )} -> 0 | I25: {=_xlfn.TEXTJOIN( ", ", 1, IF( OFFSET( INDIRECT( ADDRESS( ROW( co_variants[[#Headers],[row_id]] ), COLUMN( co_variants[[#Headers],[sector_id]] ), , , "controlTables" ) ), 1, 0, MAX( co_variants[row_id] ), 1 ) = co_sectors[[#This Row],[sector_id]], co_variants[variant_label], "" ) )} -> N/A | J25: =_xlfn.TEXTJOIN( ", ", 1, OFFSET( INDIRECT( ADDRESS( ROW( INDEX( co_impactYears[sector_id], MATCH( co_sectors[[#This Row],[sector_id]], co_impactYears[sector_id], 0 ) ) ), COLUMN( co_impactYears[[#Headers],[sector_id]] ), , , "controlTables" ) ), 0, 1, 1, 4 ) ) -> N/A | K25: {=_xlfn.TEXTJOIN( ", ", 1, IF( OFFSET( INDIRECT( ADDRESS( ROW( co_impactTypes[[#Headers],[row_id]] ), COLUMN( co_impactTypes[[#Headers],[sector_id]] ), , , "controlTables" ) ), 1, 0, MAX( co_impactTypes[row_id] ), 1 ) = co_sectors[[#This Row],[sector_id]], co_impactTypes[impactType_label], "" ) )} -> Property, Violent | L25: {=SUMPRODUCT( --( co_sectors[[#This Row],[sector_id]] = co_variants[sector_id] ) )} -> 1 | M25: {=SUMPRODUCT( --( co_sectors[[#This Row],[sector_id]] = co_impactTypes[sector_id] ) )} -> 2 | N25: {=IF( INDEX( co_impactYears[N/A], MATCH( 1, --( co_sectors[[#This Row],[sector_id]] = co_impactYears[sector_id] ), 0 ) ) = "N/A", 1, 2 )} -> 1 | O25: {=INDEX( co_modelTypes[Number of models], MATCH( 1, --( co_sectors[[#This Row],[modelType]] = co_modelTypes[modelType_id] ), 0 ) ) + IF( co_sectors[[#This Row],[modelType]] = "gcm", 1, 0 )} -> 9 | P25: {=INDEX( co_modelTypes[Number of levels], MATCH( 1, --( co_sectors[[#This Row],[modelType]] = co_modelTypes[modelType_id] ), 0 ) )} -> 7 | Q25: =PRODUCT( co_sectors[[#This Row],[Number of variants]:[Number of levels]] ) -> 126
B26: =ROW( co_sectors[[#This Row],[row_id]] ) - ROW( co_sectors[[#Headers],[row_id]] ) -> 6 | C26: CILExtremeTemp | D26: CIL Extreme Temperature | E26: 1 | F26: gcm | G26: 0 | H26: {=IF( AND( SUMPRODUCT( co_impactYears[2010], --( co_sectors[[#This Row],[sector_id]] = co_impactYears[sector_id] ) ) > 1, SUMPRODUCT( co_impactYears[2090], --( co_sectors[[#This Row],[sector_id]] = co_impactYears[sector_id] ) ) > 1 ), 1, 0 )} -> 0 | I26: {=_xlfn.TEXTJOIN( ", ", 1, IF( OFFSET( INDIRECT( ADDRESS( ROW( co_variants[[#Headers],[row_id]] ), COLUMN( co_variants[[#Headers],[sector_id]] ), , , "controlTables" ) ), 1, 0, MAX( co_variants[row_id] ), 1 ) = co_sectors[[#This Row],[sector_id]], co_variants[variant_label], "" ) )} -> Median, Low Confidence Interval, High Confidence Interval | J26: =_xlfn.TEXTJOIN( ", ", 1, OFFSET( INDIRECT( ADDRESS( ROW( INDEX( co_impactYears[sector_id], MATCH( co_sectors[[#This Row],[sector_id]], co_impactYears[sector_id], 0 ) ) ), COLUMN( co_impactYears[[#Headers],[sector_id]] ), , , "controlTables" ) ), 0, 1, 1, 4 ) ) -> N/A | K26: {=_xlfn.TEXTJOIN( ", ", 1, IF( OFFSET( INDIRECT( ADDRESS( ROW( co_impactTypes[[#Headers],[row_id]] ), COLUMN( co_impactTypes[[#Headers],[sector_id]] ), , , "controlTables" ) ), 1, 0, MAX( co_impactTypes[row_id] ), 1 ) = co_sectors[[#This Row],[sector_id]], co_impactTypes[impactType_label], "" ) )} -> N/A | L26: {=SUMPRODUCT( --( co_sectors[[#This Row],[sector_id]] = co_variants[sector_id] ) )} -> 3 | M26: {=SUMPRODUCT( --( co_sectors[[#This Row],[sector_id]] = co_impactTypes[sector_id] ) )} -> 1 | N26: {=IF( INDEX( co_impactYears[N/A], MATCH( 1, --( co_sectors[[#This Row],[sector_id]] = co_impactYears[sector_id] ), 0 ) ) = "N/A", 1, 2 )} -> 1 | O26: {=INDEX( co_modelTypes[Number of models], MATCH( 1, --( co_sectors[[#This Row],[modelType]] = co_modelTypes[modelType_id] ), 0 ) ) + IF( co_sectors[[#This Row],[modelType]] = "gcm", 1, 0 )} -> 9 | P26: {=INDEX( co_modelTypes[Number of levels], MATCH( 1, --( co_sectors[[#This Row],[modelType]] = co_modelTypes[modelType_id] ), 0 ) )} -> 7 | Q26: =PRODUCT( co_sectors[[#This Row],[Number of variants]:[Number of levels]] ) -> 189
B27: =ROW( co_sectors[[#This Row],[row_id]] ) - ROW( co_sectors[[#Headers],[row_id]] ) -> 7 | C27: CoastalProperties | D27: Coastal Properties | E27: 1 | F27: slr | G27: 0 | H27: {=IF( AND( SUMPRODUCT( co_impactYears[2010], --( co_sectors[[#This Row],[sector_id]] = co_impactYears[sector_id] ) ) > 1, SUMPRODUCT( co_impactYears[2090], --( co_sectors[[#This Row],[sector_id]] = co_impactYears[sector_id] ) ) > 1 ), 1, 0 )} -> 0 | I27: {=_xlfn.TEXTJOIN( ", ", 1, IF( OFFSET( INDIRECT( ADDRESS( ROW( co_variants[[#Headers],[row_id]] ), COLUMN( co_variants[[#Headers],[sector_id]] ), , , "controlTables" ) ), 1, 0, MAX( co_variants[row_id] ), 1 ) = co_sectors[[#This Row],[sector_id]], co_variants[variant_label], "" ) )} -> No Additional Adaptation, Proactive Adaptation, Reactive Adaptation | J27: =_xlfn.TEXTJOIN( ", ", 1, OFFSET( INDIRECT( ADDRESS( ROW( INDEX( co_impactYears[sector_id], MATCH( co_sectors[[#This Row],[sector_id]], co_impactYears[sector_id], 0 ) ) ), COLUMN( co_impactYears[[#Headers],[sector_id]] ), , , "controlTables" ) ), 0, 1, 1, 4 ) ) -> N/A | K27: {=_xlfn.TEXTJOIN( ", ", 1, IF( OFFSET( INDIRECT( ADDRESS( ROW( co_impactTypes[[#Headers],[row_id]] ), COLUMN( co_impactTypes[[#Headers],[sector_id]] ), , , "controlTables" ) ), 1, 0, MAX( co_impactTypes[row_id] ), 1 ) = co_sectors[[#This Row],[sector_id]], co_impactTypes[impactType_label], "" ) )} -> N/A | L27: {=SUMPRODUCT( --( co_sectors[[#This Row],[sector_id]] = co_variants[sector_id] ) )} -> 3 | M27: {=SUMPRODUCT( --( co_sectors[[#This Row],[sector_id]] = co_impactTypes[sector_id] ) )} -> 1 | N27: {=IF( INDEX( co_impactYears[N/A], MATCH( 1, --( co_sectors[[#This Row],[sector_id]] = co_impactYears[sector_id] ), 0 ) ) = "N/A", 1, 2 )} -> 1 | O27: {=INDEX( co_modelTypes[Number of models], MATCH( 1, --( co_sectors[[#This Row],[modelType]] = co_modelTypes[modelType_id] ), 0 ) ) + IF( co_sectors[[#This Row],[modelType]] = "gcm", 1, 0 )} -> 6 | P27: {=INDEX( co_modelTypes[Number of levels], MATCH( 1, --( co_sectors[[#This Row],[modelType]] = co_modelTypes[modelType_id] ), 0 ) )} -> 6 | Q27: =PRODUCT( co_sectors[[#This Row],[Number of variants]:[Number of levels]] ) -> 108
B28: =ROW( co_sectors[[#This Row],[row_id]] ) - ROW( co_sectors[[#Headers],[row_id]] ) -> 8 | C28: ElecSD | D28: Electricity Demand and Supply | E28: 1 | F28: gcm | G28: 0 | H28: {=IF( AND( SUMPRODUCT( co_impactYears[2010], --( co_sectors[[#This Row],[sector_id]] = co_impactYears[sector_id] ) ) > 1, SUMPRODUCT( co_impactYears[2090], --( co_sectors[[#This Row],[sector_id]] = co_impactYears[sector_id] ) ) > 1 ), 1, 0 )} -> 0 | I28: {=_xlfn.TEXTJOIN( ", ", 1, IF( OFFSET( INDIRECT( ADDRESS( ROW( co_variants[[#Headers],[row_id]] ), COLUMN( co_variants[[#Headers],[sector_id]] ), , , "controlTables" ) ), 1, 0, MAX( co_variants[row_id] ), 1 ) = co_sectors[[#This Row],[sector_id]], co_variants[variant_label], "" ) )} -> N/A | J28: =_xlfn.TEXTJOIN( ", ", 1, OFFSET( INDIRECT( ADDRESS( ROW( INDEX( co_impactYears[sector_id], MATCH( co_sectors[[#This Row],[sector_id]], co_impactYears[sector_id], 0 ) ) ), COLUMN( co_impactYears[[#Headers],[sector_id]] ), , , "controlTables" ) ), 0, 1, 1, 4 ) ) -> N/A | K28: {=_xlfn.TEXTJOIN( ", ", 1, IF( OFFSET( INDIRECT( ADDRESS( ROW( co_impactTypes[[#Headers],[row_id]] ), COLUMN( co_impactTypes[[#Headers],[sector_id]] ), , , "controlTables" ) ), 1, 0, MAX( co_impactTypes[row_id] ), 1 ) = co_sectors[[#This Row],[sector_id]], co_impactTypes[impactType_label], "" ) )} -> N/A | L28: {=SUMPRODUCT( --( co_sectors[[#This Row],[sector_id]] = co_variants[sector_id] ) )} -> 1 | M28: {=SUMPRODUCT( --( co_sectors[[#This Row],[sector_id]] = co_impactTypes[sector_id] ) )} -> 1 | N28: {=IF( INDEX( co_impactYears[N/A], MATCH( 1, --( co_sectors[[#This Row],[sector_id]] = co_impactYears[sector_id] ), 0 ) ) = "N/A", 1, 2 )} -> 1 | O28: {=INDEX( co_modelTypes[Number of models], MATCH( 1, --( co_sectors[[#This Row],[modelType]] = co_modelTypes[modelType_id] ), 0 ) ) + IF( co_sectors[[#This Row],[modelType]] = "gcm", 1, 0 )} -> 9 | P28: {=INDEX( co_modelTypes[Number of levels], MATCH( 1, --( co_sectors[[#This Row],[modelType]] = co_modelTypes[modelType_id] ), 0 ) )} -> 7 | Q28: =PRODUCT( co_sectors[[#This Row],[Number of variants]:[Number of levels]] ) -> 63
B29: =ROW( co_sectors[[#This Row],[row_id]] ) - ROW( co_sectors[[#Headers],[row_id]] ) -> 9 | C29: ElecTD | D29: Electricity Transmission and Distribution | E29: 1 | F29: gcm | G29: 1 | H29: {=IF( AND( SUMPRODUCT( co_impactYears[2010], --( co_sectors[[#This Row],[sector_id]] = co_impactYears[sector_id] ) ) > 1, SUMPRODUCT( co_impactYears[2090], --( co_sectors[[#This Row],[sector_id]] = co_impactYears[sector_id] ) ) > 1 ), 1, 0 )} -> 0 | I29: {=_xlfn.TEXTJOIN( ", ", 1, IF( OFFSET( INDIRECT( ADDRESS( ROW( co_variants[[#Headers],[row_id]] ), COLUMN( co_variants[[#Headers],[sector_id]] ), , , "controlTables" ) ), 1, 0, MAX( co_variants[row_id] ), 1 ) = co_sectors[[#This Row],[sector_id]], co_variants[variant_label], "" ) )} -> No Additional Adaptation, Proactive Adaptation, Reactive Adaptation | J29: =_xlfn.TEXTJOIN( ", ", 1, OFFSET( INDIRECT( ADDRESS( ROW( INDEX( co_impactYears[sector_id], MATCH( co_sectors[[#This Row],[sector_id]], co_impactYears[sector_id], 0 ) ) ), COLUMN( co_impactYears[[#Headers],[sector_id]] ), , , "controlTables" ) ), 0, 1, 1, 4 ) ) -> N/A | K29: {=_xlfn.TEXTJOIN( ", ", 1, IF( OFFSET( INDIRECT( ADDRESS( ROW( co_impactTypes[[#Headers],[row_id]] ), COLUMN( co_impactTypes[[#Headers],[sector_id]] ), , , "controlTables" ) ), 1, 0, MAX( co_impactTypes[row_id] ), 1 ) = co_sectors[[#This Row],[sector_id]], co_impactTypes[impactType_label], "" ) )} -> N/A | L29: {=SUMPRODUCT( --( co_sectors[[#This Row],[sector_id]] = co_variants[sector_id] ) )} -> 3 | M29: {=SUMPRODUCT( --( co_sectors[[#This Row],[sector_id]] = co_impactTypes[sector_id] ) )} -> 1 | N29: {=IF( INDEX( co_impactYears[N/A], MATCH( 1, --( co_sectors[[#This Row],[sector_id]] = co_impactYears[sector_id] ), 0 ) ) = "N/A", 1, 2 )} -> 1 | O29: {=INDEX( co_modelTypes[Number of models], MATCH( 1, --( co_sectors[[#This Row],[modelType]] = co_modelTypes[modelType_id] ), 0 ) ) + IF( co_sectors[[#This Row],[modelType]] = "gcm", 1, 0 )} -> 9 | P29: {=INDEX( co_modelTypes[Number of levels], MATCH( 1, --( co_sectors[[#This Row],[modelType]] = co_modelTypes[modelType_id] ), 0 ) )} -> 7 | Q29: =PRODUCT( co_sectors[[#This Row],[Number of variants]:[Number of levels]] ) -> 189
B30: =ROW( co_sectors[[#This Row],[row_id]] ) - ROW( co_sectors[[#Headers],[row_id]] ) -> 10 | C30: ExtremeTemp | D30: Extreme Temperature | E30: 1 | F30: gcm | G30: 0 | H30: {=IF( AND( SUMPRODUCT( co_impactYears[2010], --( co_sectors[[#This Row],[sector_id]] = co_impactYears[sector_id] ) ) > 1, SUMPRODUCT( co_impactYears[2090], --( co_sectors[[#This Row],[sector_id]] = co_impactYears[sector_id] ) ) > 1 ), 1, 0 )} -> 1 | I30: {=_xlfn.TEXTJOIN( ", ", 1, IF( OFFSET( INDIRECT( ADDRESS( ROW( co_variants[[#Headers],[row_id]] ), COLUMN( co_variants[[#Headers],[sector_id]] ), , , "controlTables" ) ), 1, 0, MAX( co_variants[row_id] ), 1 ) = co_sectors[[#This Row],[sector_id]], co_variants[variant_label], "" ) )} -> Adaptation, No Additional Adaptation | J30: =_xlfn.TEXTJOIN( ", ", 1, OFFSET( INDIRECT( ADDRESS( ROW( INDEX( co_impactYears[sector_id], MATCH( co_sectors[[#This Row],[sector_id]], co_impactYears[sector_id], 0 ) ) ), COLUMN( co_impactYears[[#Headers],[sector_id]] ), , , "controlTables" ) ), 0, 1, 1, 4 ) ) -> 2010, 2090 | K30: {=_xlfn.TEXTJOIN( ", ", 1, IF( OFFSET( INDIRECT( ADDRESS( ROW( co_impactTypes[[#Headers],[row_id]] ), COLUMN( co_impactTypes[[#Headers],[sector_id]] ), , , "controlTables" ) ), 1, 0, MAX( co_impactTypes[row_id] ), 1 ) = co_sectors[[#This Row],[sector_id]], co_impactTypes[impactType_label], "" ) )} -> Cold, Hot | L30: {=SUMPRODUCT( --( co_sectors[[#This Row],[sector_id]] = co_variants[sector_id] ) )} -> 2 | M30: {=SUMPRODUCT( --( co_sectors[[#This Row],[sector_id]] = co_impactTypes[sector_id] ) )} -> 2 | N30: {=IF( INDEX( co_impactYears[N/A], MATCH( 1, --( co_sectors[[#This Row],[sector_id]] = co_impactYears[sector_id] ), 0 ) ) = "N/A", 1, 2 )} -> 2 | O30: {=INDEX( co_modelTypes[Number of models], MATCH( 1, --( co_sectors[[#This Row],[modelType]] = co_modelTypes[modelType_id] ), 0 ) ) + IF( co_sectors[[#This Row],[modelType]] = "gcm", 1, 0 )} -> 9 | P30: {=INDEX( co_modelTypes[Number of levels], MATCH( 1, --( co_sectors[[#This Row],[modelType]] = co_modelTypes[modelType_id] ), 0 ) )} -> 7 | Q30: =PRODUCT( co_sectors[[#This Row],[Number of variants]:[Number of levels]] ) -> 504
B31: =ROW( co_sectors[[#This Row],[row_id]] ) - ROW( co_sectors[[#Headers],[row_id]] ) -> 11 | C31: HTF | D31: High Tide Flooding and Traffic | E31: 1 | F31: slr | G31: 1 | H31: {=IF( AND( SUMPRODUCT( co_impactYears[2010], --( co_sectors[[#This Row],[sector_id]] = co_impactYears[sector_id] ) ) > 1, SUMPRODUCT( co_impactYears[2090], --( co_sectors[[#This Row],[sector_id]] = co_impactYears[sector_id] ) ) > 1 ), 1, 0 )} -> 0 | I31: {=_xlfn.TEXTJOIN( ", ", 1, IF( OFFSET( INDIRECT( ADDRESS( ROW( co_variants[[#Headers],[row_id]] ), COLUMN( co_variants[[#Headers],[sector_id]] ), , , "controlTables" ) ), 1, 0, MAX( co_variants[row_id] ), 1 ) = co_sectors[[#This Row],[sector_id]], co_variants[variant_label], "" ) )} -> Direct Adaptation, No Additional Adaptation, Reasonably Anticipated Adaptation | J31: =_xlfn.TEXTJOIN( ", ", 1, OFFSET( INDIRECT( ADDRESS( ROW( INDEX( co_impactYears[sector_id], MATCH( co_sectors[[#This Row],[sector_id]], co_impactYears[sector_id], 0 ) ) ), COLUMN( co_impactYears[[#Headers],[sector_id]] ), , , "controlTables" ) ), 0, 1, 1, 4 ) ) -> N/A | K31: {=_xlfn.TEXTJOIN( ", ", 1, IF( OFFSET( INDIRECT( ADDRESS( ROW( co_impactTypes[[#Headers],[row_id]] ), COLUMN( co_impactTypes[[#Headers],[sector_id]] ), , , "controlTables" ) ), 1, 0, MAX( co_impactTypes[row_id] ), 1 ) = co_sectors[[#This Row],[sector_id]], co_impactTypes[impactType_label], "" ) )} -> N/A | L31: {=SUMPRODUCT( --( co_sectors[[#This Row],[sector_id]] = co_variants[sector_id] ) )} -> 3 | M31: {=SUMPRODUCT( --( co_sectors[[#This Row],[sector_id]] = co_impactTypes[sector_id] ) )} -> 1 | N31: {=IF( INDEX( co_impactYears[N/A], MATCH( 1, --( co_sectors[[#This Row],[sector_id]] = co_impactYears[sector_id] ), 0 ) ) = "N/A", 1, 2 )} -> 1 | O31: {=INDEX( co_modelTypes[Number of models], MATCH( 1, --( co_sectors[[#This Row],[modelType]] = co_modelTypes[modelType_id] ), 0 ) ) + IF( co_sectors[[#This Row],[modelType]] = "gcm", 1, 0 )} -> 6 | P31: {=INDEX( co_modelTypes[Number of levels], MATCH( 1, --( co_sectors[[#This Row],[modelType]] = co_modelTypes[modelType_id] ), 0 ) )} -> 6 | Q31: =PRODUCT( co_sectors[[#This Row],[Number of variants]:[Number of levels]] ) -> 108
B32: =ROW( co_sectors[[#This Row],[row_id]] ) - ROW( co_sectors[[#Headers],[row_id]] ) -> 12 | C32: InlandFlooding | D32: Inland Flooding | E32: 1 | F32: gcm | G32: 0 | H32: {=IF( AND( SUMPRODUCT( co_impactYears[2010], --( co_sectors[[#This Row],[sector_id]] = co_impactYears[sector_id] ) ) > 1, SUMPRODUCT( co_impactYears[2090], --( co_sectors[[#This Row],[sector_id]] = co_impactYears[sector_id] ) ) > 1 ), 1, 0 )} -> 0 | I32: {=_xlfn.TEXTJOIN( ", ", 1, IF( OFFSET( INDIRECT( ADDRESS( ROW( co_variants[[#Headers],[row_id]] ), COLUMN( co_variants[[#Headers],[sector_id]] ), , , "controlTables" ) ), 1, 0, MAX( co_variants[row_id] ), 1 ) = co_sectors[[#This Row],[sector_id]], co_variants[variant_label], "" ) )} -> N/A | J32: =_xlfn.TEXTJOIN( ", ", 1, OFFSET( INDIRECT( ADDRESS( ROW( INDEX( co_impactYears[sector_id], MATCH( co_sectors[[#This Row],[sector_id]], co_impactYears[sector_id], 0 ) ) ), COLUMN( co_impactYears[[#Headers],[sector_id]] ), , , "controlTables" ) ), 0, 1, 1, 4 ) ) -> N/A | K32: {=_xlfn.TEXTJOIN( ", ", 1, IF( OFFSET( INDIRECT( ADDRESS( ROW( co_impactTypes[[#Headers],[row_id]] ), COLUMN( co_impactTypes[[#Headers],[sector_id]] ), , , "controlTables" ) ), 1, 0, MAX( co_impactTypes[row_id] ), 1 ) = co_sectors[[#This Row],[sector_id]], co_impactTypes[impactType_label], "" ) )} -> N/A | L32: {=SUMPRODUCT( --( co_sectors[[#This Row],[sector_id]] = co_variants[sector_id] ) )} -> 1 | M32: {=SUMPRODUCT( --( co_sectors[[#This Row],[sector_id]] = co_impactTypes[sector_id] ) )} -> 1 | N32: {=IF( INDEX( co_impactYears[N/A], MATCH( 1, --( co_sectors[[#This Row],[sector_id]] = co_impactYears[sector_id] ), 0 ) ) = "N/A", 1, 2 )} -> 1 | O32: {=INDEX( co_modelTypes[Number of models], MATCH( 1, --( co_sectors[[#This Row],[modelType]] = co_modelTypes[modelType_id] ), 0 ) ) + IF( co_sectors[[#This Row],[modelType]] = "gcm", 1, 0 )} -> 9 | P32: {=INDEX( co_modelTypes[Number of levels], MATCH( 1, --( co_sectors[[#This Row],[modelType]] = co_modelTypes[modelType_id] ), 0 ) )} -> 7 | Q32: =PRODUCT( co_sectors[[#This Row],[Number of variants]:[Number of levels]] ) -> 63
... B45: =ROW( co_sectors[[#This Row],[row_id]] ) - ROW( co_sectors[[#Headers],[row_id]] ) -> 25 | C45: WinterRec | D45: Winter Recreation | E45: 1 | F45: gcm | G45: 0 | H45: {=IF( AND( SUMPRODUCT( co_impactYears[2010], --( co_sectors[[#This Row],[sector_id]] = co_impactYears[sector_id] ) ) > 1, SUMPRODUCT( co_impactYears[2090], --( co_sectors[[#This Row],[sector_id]] = co_impactYears[sector_id] ) ) > 1 ), 1, 0 )} -> 1 | I45: {=_xlfn.TEXTJOIN( ", ", 1, IF( OFFSET( INDIRECT( ADDRESS( ROW( co_variants[[#Headers],[row_id]] ), COLUMN( co_variants[[#Headers],[sector_id]] ), , , "controlTables" ) ), 1, 0, MAX( co_variants[row_id] ), 1 ) = co_sectors[[#This Row],[sector_id]], co_variants[variant_label], "" ) )} -> N/A | J45: =_xlfn.TEXTJOIN( ", ", 1, OFFSET( INDIRECT( ADDRESS( ROW( INDEX( co_impactYears[sector_id], MATCH( co_sectors[[#This Row],[sector_id]], co_impactYears[sector_id], 0 ) ) ), COLUMN( co_impactYears[[#Headers],[sector_id]] ), , , "controlTables" ) ), 0, 1, 1, 4 ) ) -> 2010, 2090 | K45: {=_xlfn.TEXTJOIN( ", ", 1, IF( OFFSET( INDIRECT( ADDRESS( ROW( co_impactTypes[[#Headers],[row_id]] ), COLUMN( co_impactTypes[[#Headers],[sector_id]] ), , , "controlTables" ) ), 1, 0, MAX( co_impactTypes[row_id] ), 1 ) = co_sectors[[#This Row],[sector_id]], co_impactTypes[impactType_label], "" ) )} -> Alpine Skiing, Cross-Country Skiing, Snowmobiling | L45: {=SUMPRODUCT( --( co_sectors[[#This Row],[sector_id]] = co_variants[sector_id] ) )} -> 1 | M45: {=SUMPRODUCT( --( co_sectors[[#This Row],[sector_id]] = co_impactTypes[sector_id] ) )} -> 3 | N45: {=IF( INDEX( co_impactYears[N/A], MATCH( 1, --( co_sectors[[#This Row],[sector_id]] = co_impactYears[sector_id] ), 0 ) ) = "N/A", 1, 2 )} -> 2 | O45: {=INDEX( co_modelTypes[Number of models], MATCH( 1, --( co_sectors[[#This Row],[modelType]] = co_modelTypes[modelType_id] ), 0 ) ) + IF( co_sectors[[#This Row],[modelType]] = "gcm", 1, 0 )} -> 9 | P45: {=INDEX( co_modelTypes[Number of levels], MATCH( 1, --( co_sectors[[#This Row],[modelType]] = co_modelTypes[modelType_id] ), 0 ) )} -> 7 | Q45: =PRODUCT( co_sectors[[#This Row],[Number of variants]:[Number of levels]] ) -> 378
B47: Impact Year Estimates
B49: row_id | C49: sector_id | D49: N/A | E49: 2010 | F49: 2090
B50: =ROW( co_impactYears[[#This Row],[row_id]] ) - ROW(co_impactYears[[#Headers],[row_id]] ) -> 1 | C50: AirQuality | D50: {=IF( SUMPRODUCT( --( VALUE( controlTables!E$49 ) = data_scaledImpacts[impactYear] ), --( co_impactYears[[#This Row],[sector_id]] = data_scaledImpacts[sector] ) ) > 0, "", controlTables!D$49 )} -> N/A | E50: {=IF( SUMPRODUCT( --( VALUE( controlTables!E$49 ) = data_scaledImpacts[impactYear] ), --( co_impactYears[[#This Row],[sector_id]] = data_scaledImpacts[sector] ) ) > 0, VALUE( controlTables!E$49 ), "" )} | F50: {=IF( SUMPRODUCT( --( VALUE( controlTables!F$49 ) = data_scaledImpacts[impactYear] ), --( co_impactYears[[#This Row],[sector_id]] = data_scaledImpacts[sector] ) ) > 0, VALUE( controlTables!F$49 ), "" )}
B51: =ROW( co_impactYears[[#This Row],[row_id]] ) - ROW(co_impactYears[[#Headers],[row_id]] ) -> 2 | C51: AsphaltRoads | D51: {=IF( SUMPRODUCT( --( VALUE( controlTables!E$49 ) = data_scaledImpacts[impactYear] ), --( co_impactYears[[#This Row],[sector_id]] = data_scaledImpacts[sector] ) ) > 0, "", controlTables!D$49 )} -> N/A | E51: {=IF( SUMPRODUCT( --( VALUE( controlTables!E$49 ) = data_scaledImpacts[impactYear] ), --( co_impactYears[[#This Row],[sector_id]] = data_scaledImpacts[sector] ) ) > 0, VALUE( controlTables!E$49 ), "" )} | F51: {=IF( SUMPRODUCT( --( VALUE( controlTables!F$49 ) = data_scaledImpacts[impactYear] ), --( co_impactYears[[#This Row],[sector_id]] = data_scaledImpacts[sector] ) ) > 0, VALUE( controlTables!F$49 ), "" )}
B52: =ROW( co_impactYears[[#This Row],[row_id]] ) - ROW(co_impactYears[[#Headers],[row_id]] ) -> 3 | C52: ATSExtremeTemp | D52: {=IF( SUMPRODUCT( --( VALUE( controlTables!E$49 ) = data_scaledImpacts[impactYear] ), --( co_impactYears[[#This Row],[sector_id]] = data_scaledImpacts[sector] ) ) > 0, "", controlTables!D$49 )} -> N/A | E52: {=IF( SUMPRODUCT( --( VALUE( controlTables!E$49 ) = data_scaledImpacts[impactYear] ), --( co_impactYears[[#This Row],[sector_id]] = data_scaledImpacts[sector] ) ) > 0, VALUE( controlTables!E$49 ), "" )} | F52: {=IF( SUMPRODUCT( --( VALUE( controlTables!F$49 ) = data_scaledImpacts[impactYear] ), --( co_impactYears[[#This Row],[sector_id]] = data_scaledImpacts[sector] ) ) > 0, VALUE( controlTables!F$49 ), "" )}
B53: =ROW( co_impactYears[[#This Row],[row_id]] ) - ROW(co_impactYears[[#Headers],[row_id]] ) -> 4 | C53: CILAgriculture | D53: {=IF( SUMPRODUCT( --( VALUE( controlTables!E$49 ) = data_scaledImpacts[impactYear] ), --( co_impactYears[[#This Row],[sector_id]] = data_scaledImpacts[sector] ) ) > 0, "", controlTables!D$49 )} -> N/A | E53: {=IF( SUMPRODUCT( --( VALUE( controlTables!E$49 ) = data_scaledImpacts[impactYear] ), --( co_impactYears[[#This Row],[sector_id]] = data_scaledImpacts[sector] ) ) > 0, VALUE( controlTables!E$49 ), "" )} | F53: {=IF( SUMPRODUCT( --( VALUE( controlTables!F$49 ) = data_scaledImpacts[impactYear] ), --( co_impactYears[[#This Row],[sector_id]] = data_scaledImpacts[sector] ) ) > 0, VALUE( controlTables!F$49 ), "" )}
B54: =ROW( co_impactYears[[#This Row],[row_id]] ) - ROW(co_impactYears[[#Headers],[row_id]] ) -> 5 | C54: CILCrime | D54: {=IF( SUMPRODUCT( --( VALUE( controlTables!E$49 ) = data_scaledImpacts[impactYear] ), --( co_impactYears[[#This Row],[sector_id]] = data_scaledImpacts[sector] ) ) > 0, "", controlTables!D$49 )} -> N/A | E54: {=IF( SUMPRODUCT( --( VALUE( controlTables!E$49 ) = data_scaledImpacts[impactYear] ), --( co_impactYears[[#This Row],[sector_id]] = data_scaledImpacts[sector] ) ) > 0, VALUE( controlTables!E$49 ), "" )} | F54: {=IF( SUMPRODUCT( --( VALUE( controlTables!F$49 ) = data_scaledImpacts[impactYear] ), --( co_impactYears[[#This Row],[sector_id]] = data_scaledImpacts[sector] ) ) > 0, VALUE( controlTables!F$49 ), "" )}
B55: =ROW( co_impactYears[[#This Row],[row_id]] ) - ROW(co_impactYears[[#Headers],[row_id]] ) -> 6 | C55: CILExtremeTemp | D55: {=IF( SUMPRODUCT( --( VALUE( controlTables!E$49 ) = data_scaledImpacts[impactYear] ), --( co_impactYears[[#This Row],[sector_id]] = data_scaledImpacts[sector] ) ) > 0, "", controlTables!D$49 )} -> N/A | E55: {=IF( SUMPRODUCT( --( VALUE( controlTables!E$49 ) = data_scaledImpacts[impactYear] ), --( co_impactYears[[#This Row],[sector_id]] = data_scaledImpacts[sector] ) ) > 0, VALUE( controlTables!E$49 ), "" )} | F55: {=IF( SUMPRODUCT( --( VALUE( controlTables!F$49 ) = data_scaledImpacts[impactYear] ), --( co_impactYears[[#This Row],[sector_id]] = data_scaledImpacts[sector] ) ) > 0, VALUE( controlTables!F$49 ), "" )}
B56: =ROW( co_impactYears[[#This Row],[row_id]] ) - ROW(co_impactYears[[#Headers],[row_id]] ) -> 7 | C56: CoastalProperties | D56: {=IF( SUMPRODUCT( --( VALUE( controlTables!E$49 ) = data_scaledImpacts[impactYear] ), --( co_impactYears[[#This Row],[sector_id]] = data_scaledImpacts[sector] ) ) > 0, "", controlTables!D$49 )} -> N/A | E56: {=IF( SUMPRODUCT( --( VALUE( controlTables!E$49 ) = data_scaledImpacts[impactYear] ), --( co_impactYears[[#This Row],[sector_id]] = data_scaledImpacts[sector] ) ) > 0, VALUE( controlTables!E$49 ), "" )} | F56: {=IF( SUMPRODUCT( --( VALUE( controlTables!F$49 ) = data_scaledImpacts[impactYear] ), --( co_impactYears[[#This Row],[sector_id]] = data_scaledImpacts[sector] ) ) > 0, VALUE( controlTables!F$49 ), "" )}
B57: =ROW( co_impactYears[[#This Row],[row_id]] ) - ROW(co_impactYears[[#Headers],[row_id]] ) -> 8 | C57: ElecSD | D57: {=IF( SUMPRODUCT( --( VALUE( controlTables!E$49 ) = data_scaledImpacts[impactYear] ), --( co_impactYears[[#This Row],[sector_id]] = data_scaledImpacts[sector] ) ) > 0, "", controlTables!D$49 )} -> N/A | E57: {=IF( SUMPRODUCT( --( VALUE( controlTables!E$49 ) = data_scaledImpacts[impactYear] ), --( co_impactYears[[#This Row],[sector_id]] = data_scaledImpacts[sector] ) ) > 0, VALUE( controlTables!E$49 ), "" )} | F57: {=IF( SUMPRODUCT( --( VALUE( controlTables!F$49 ) = data_scaledImpacts[impactYear] ), --( co_impactYears[[#This Row],[sector_id]] = data_scaledImpacts[sector] ) ) > 0, VALUE( controlTables!F$49 ), "" )}
B58: =ROW( co_impactYears[[#This Row],[row_id]] ) - ROW(co_impactYears[[#Headers],[row_id]] ) -> 9 | C58: ElecTD | D58: {=IF( SUMPRODUCT( --( VALUE( controlTables!E$49 ) = data_scaledImpacts[impactYear] ), --( co_impactYears[[#This Row],[sector_id]] = data_scaledImpacts[sector] ) ) > 0, "", controlTables!D$49 )} -> N/A | E58: {=IF( SUMPRODUCT( --( VALUE( controlTables!E$49 ) = data_scaledImpacts[impactYear] ), --( co_impactYears[[#This Row],[sector_id]] = data_scaledImpacts[sector] ) ) > 0, VALUE( controlTables!E$49 ), "" )} | F58: {=IF( SUMPRODUCT( --( VALUE( controlTables!F$49 ) = data_scaledImpacts[impactYear] ), --( co_impactYears[[#This Row],[sector_id]] = data_scaledImpacts[sector] ) ) > 0, VALUE( controlTables!F$49 ), "" )}
B59: =ROW( co_impactYears[[#This Row],[row_id]] ) - ROW(co_impactYears[[#Headers],[row_id]] ) -> 10 | C59: ExtremeTemp | D59: {=IF( SUMPRODUCT( --( VALUE( controlTables!E$49 ) = data_scaledImpacts[impactYear] ), --( co_impactYears[[#This Row],[sector_id]] = data_scaledImpacts[sector] ) ) > 0, "", controlTables!D$49 )} | E59: {=IF( SUMPRODUCT( --( VALUE( controlTables!E$49 ) = data_scaledImpacts[impactYear] ), --( co_impactYears[[#This Row],[sector_id]] = data_scaledImpacts[sector] ) ) > 0, VALUE( controlTables!E$49 ), "" )} -> 2010 | F59: {=IF( SUMPRODUCT( --( VALUE( controlTables!F$49 ) = data_scaledImpacts[impactYear] ), --( co_impactYears[[#This Row],[sector_id]] = data_scaledImpacts[sector] ) ) > 0, VALUE( controlTables!F$49 ), "" )} -> 2090
B60: =ROW( co_impactYears[[#This Row],[row_id]] ) - ROW(co_impactYears[[#Headers],[row_id]] ) -> 11 | C60: HTF | D60: {=IF( SUMPRODUCT( --( VALUE( controlTables!E$49 ) = data_scaledImpacts[impactYear] ), --( co_impactYears[[#This Row],[sector_id]] = data_scaledImpacts[sector] ) ) > 0, "", controlTables!D$49 )} -> N/A | E60: {=IF( SUMPRODUCT( --( VALUE( controlTables!E$49 ) = data_scaledImpacts[impactYear] ), --( co_impactYears[[#This Row],[sector_id]] = data_scaledImpacts[sector] ) ) > 0, VALUE( controlTables!E$49 ), "" )} | F60: {=IF( SUMPRODUCT( --( VALUE( controlTables!F$49 ) = data_scaledImpacts[impactYear] ), --( co_impactYears[[#This Row],[sector_id]] = data_scaledImpacts[sector] ) ) > 0, VALUE( controlTables!F$49 ), "" )}
B61: =ROW( co_impactYears[[#This Row],[row_id]] ) - ROW(co_impactYears[[#Headers],[row_id]] ) -> 12 | C61: InlandFlooding | D61: {=IF( SUMPRODUCT( --( VALUE( controlTables!E$49 ) = data_scaledImpacts[impactYear] ), --( co_impactYears[[#This Row],[sector_id]] = data_scaledImpacts[sector] ) ) > 0, "", controlTables!D$49 )} -> N/A | E61: {=IF( SUMPRODUCT( --( VALUE( controlTables!E$49 ) = data_scaledImpacts[impactYear] ), --( co_impactYears[[#This Row],[sector_id]] = data_scaledImpacts[sector] ) ) > 0, VALUE( controlTables!E$49 ), "" )} | F61: {=IF( SUMPRODUCT( --( VALUE( controlTables!F$49 ) = data_scaledImpacts[impactYear] ), --( co_impactYears[[#This Row],[sector_id]] = data_scaledImpacts[sector] ) ) > 0, VALUE( controlTables!F$49 ), "" )}
... B74: =ROW( co_impactYears[[#This Row],[row_id]] ) - ROW(co_impactYears[[#Headers],[row_id]] ) -> 25 | C74: WinterRec | D74: {=IF( SUMPRODUCT( --( VALUE( controlTables!E$49 ) = data_scaledImpacts[impactYear] ), --( co_impactYears[[#This Row],[sector_id]] = data_scaledImpacts[sector] ) ) > 0, "", controlTables!D$49 )} | E74: {=IF( SUMPRODUCT( --( VALUE( controlTables!E$49 ) = data_scaledImpacts[impactYear] ), --( co_impactYears[[#This Row],[sector_id]] = data_scaledImpacts[sector] ) ) > 0, VALUE( controlTables!E$49 ), "" )} -> 2010 | F74: {=IF( SUMPRODUCT( --( VALUE( controlTables!F$49 ) = data_scaledImpacts[impactYear] ), --( co_impactYears[[#This Row],[sector_id]] = data_scaledImpacts[sector] ) ) > 0, VALUE( controlTables!F$49 ), "" )} -> 2090
B76: Variants Table
B77: If the sector only has one variant, "variant_id_excel" should be "N/A"
B78: When adding a new sector, check that "variant_id_excel" matches the value in the associated scaled impacts table ("scaledImpacts" or "slrImpacts").
B79: "variant_id" should have no spaces
B80: row_id | C80: sector_id | D80: variant_label | E80: variant_id | F80: variant_id_excel | G80: sectorprimary | H80: includeaggregate | I80: damageAdjName | J80: check_data | K80: subImpacts
B81: =ROW( co_variants[[#This Row],[row_id]] ) - ROW( co_variants[[#Headers],[row_id]] ) -> 1 | C81: AirQuality | D81: 2011 Emissions | E81: 2011 | F81: 2011 | G81: 1 | H81: 1 | I81: =INDEX( co_impactTypes[damageAdjName], MATCH( co_variants[[#This Row],[sector_id]], co_impactTypes[sector_id], 0 ) ) & IF( co_variants[[#This Row],[sector_id]] = "Roads", IF( co_variants[[#This Row],[variant_id_excel]] = "Proactive", "_proactive", "_other" ), "" ) -> none | J81: {=--( SUMPRODUCT( --( co_variants[[#This Row],[sector_id]] = data_scaledImpacts[sector] ), --( co_variants[[#This Row],[variant_id_excel]] = data_scaledImpacts[variant] ) ) > 1 )} -> 1 | K81: {=--( SUMPRODUCT( --( co_impactTypes[sector_id] = co_variants[[#This Row],[sector_id]] ) ) > 1 )} -> 1
B82: =ROW( co_variants[[#This Row],[row_id]] ) - ROW( co_variants[[#Headers],[row_id]] ) -> 2 | C82: AirQuality | D82: 2040 Emissions | E82: 2040 | F82: 2040 | G82: 0 | H82: 0 | I82: =INDEX( co_impactTypes[damageAdjName], MATCH( co_variants[[#This Row],[sector_id]], co_impactTypes[sector_id], 0 ) ) & IF( co_variants[[#This Row],[sector_id]] = "Roads", IF( co_variants[[#This Row],[variant_id_excel]] = "Proactive", "_proactive", "_other" ), "" ) -> none | J82: {=--( SUMPRODUCT( --( co_variants[[#This Row],[sector_id]] = data_scaledImpacts[sector] ), --( co_variants[[#This Row],[variant_id_excel]] = data_scaledImpacts[variant] ) ) > 1 )} -> 1 | K82: {=--( SUMPRODUCT( --( co_impactTypes[sector_id] = co_variants[[#This Row],[sector_id]] ) ) > 1 )} -> 1
B83: =ROW( co_variants[[#This Row],[row_id]] ) - ROW( co_variants[[#Headers],[row_id]] ) -> 3 | C83: AsphaltRoads | D83: N/A | E83: NA | F83: N/A | G83: 1 | H83: 0 | I83: =INDEX( co_impactTypes[damageAdjName], MATCH( co_variants[[#This Row],[sector_id]], co_impactTypes[sector_id], 0 ) ) & IF( co_variants[[#This Row],[sector_id]] = "Roads", IF( co_variants[[#This Row],[variant_id_excel]] = "Proactive", "_proactive", "_other" ), "" ) -> none | J83: {=--( SUMPRODUCT( --( co_variants[[#This Row],[sector_id]] = data_scaledImpacts[sector] ), --( co_variants[[#This Row],[variant_id_excel]] = data_scaledImpacts[variant] ) ) > 1 )} -> 1 | K83: {=--( SUMPRODUCT( --( co_impactTypes[sector_id] = co_variants[[#This Row],[sector_id]] ) ) > 1 )} -> 0
B84: =ROW( co_variants[[#This Row],[row_id]] ) - ROW( co_variants[[#Headers],[row_id]] ) -> 4 | C84: ATSExtremeTemp | D84: Mean | E84: mean | F84: mean | G84: 1 | H84: 1 | I84: =INDEX( co_impactTypes[damageAdjName], MATCH( co_variants[[#This Row],[sector_id]], co_impactTypes[sector_id], 0 ) ) & IF( co_variants[[#This Row],[sector_id]] = "Roads", IF( co_variants[[#This Row],[variant_id_excel]] = "Proactive", "_proactive", "_other" ), "" ) -> none | J84: {=--( SUMPRODUCT( --( co_variants[[#This Row],[sector_id]] = data_scaledImpacts[sector] ), --( co_variants[[#This Row],[variant_id_excel]] = data_scaledImpacts[variant] ) ) > 1 )} -> 1 | K84: {=--( SUMPRODUCT( --( co_impactTypes[sector_id] = co_variants[[#This Row],[sector_id]] ) ) > 1 )} -> 0
B85: =ROW( co_variants[[#This Row],[row_id]] ) - ROW( co_variants[[#Headers],[row_id]] ) -> 5 | C85: ATSExtremeTemp | D85: Low Confidence Interval | E85: low_CI | F85: low CI | G85: 0 | H85: 0 | I85: =INDEX( co_impactTypes[damageAdjName], MATCH( co_variants[[#This Row],[sector_id]], co_impactTypes[sector_id], 0 ) ) & IF( co_variants[[#This Row],[sector_id]] = "Roads", IF( co_variants[[#This Row],[variant_id_excel]] = "Proactive", "_proactive", "_other" ), "" ) -> none | J85: {=--( SUMPRODUCT( --( co_variants[[#This Row],[sector_id]] = data_scaledImpacts[sector] ), --( co_variants[[#This Row],[variant_id_excel]] = data_scaledImpacts[variant] ) ) > 1 )} -> 1 | K85: {=--( SUMPRODUCT( --( co_impactTypes[sector_id] = co_variants[[#This Row],[sector_id]] ) ) > 1 )} -> 0
B86: =ROW( co_variants[[#This Row],[row_id]] ) - ROW( co_variants[[#Headers],[row_id]] ) -> 6 | C86: ATSExtremeTemp | D86: High Confidence Interval | E86: high_CI | F86: high CI | G86: 0 | H86: 0 | I86: =INDEX( co_impactTypes[damageAdjName], MATCH( co_variants[[#This Row],[sector_id]], co_impactTypes[sector_id], 0 ) ) & IF( co_variants[[#This Row],[sector_id]] = "Roads", IF( co_variants[[#This Row],[variant_id_excel]] = "Proactive", "_proactive", "_other" ), "" ) -> none | J86: {=--( SUMPRODUCT( --( co_variants[[#This Row],[sector_id]] = data_scaledImpacts[sector] ), --( co_variants[[#This Row],[variant_id_excel]] = data_scaledImpacts[variant] ) ) > 1 )} -> 1 | K86: {=--( SUMPRODUCT( --( co_impactTypes[sector_id] = co_variants[[#This Row],[sector_id]] ) ) > 1 )} -> 0
B87: =ROW( co_variants[[#This Row],[row_id]] ) - ROW( co_variants[[#Headers],[row_id]] ) -> 7 | C87: CILAgriculture | D87: With CO2 Fertilization | E87: withCO2 | F87: With CO2 Fertilization | G87: 1 | H87: 1 | I87: =INDEX( co_impactTypes[damageAdjName], MATCH( co_variants[[#This Row],[sector_id]], co_impactTypes[sector_id], 0 ) ) & IF( co_variants[[#This Row],[sector_id]] = "Roads", IF( co_variants[[#This Row],[variant_id_excel]] = "Proactive", "_proactive", "_other" ), "" ) -> none | J87: {=--( SUMPRODUCT( --( co_variants[[#This Row],[sector_id]] = data_scaledImpacts[sector] ), --( co_variants[[#This Row],[variant_id_excel]] = data_scaledImpacts[variant] ) ) > 1 )} -> 1 | K87: {=--( SUMPRODUCT( --( co_impactTypes[sector_id] = co_variants[[#This Row],[sector_id]] ) ) > 1 )} -> 1
B88: =ROW( co_variants[[#This Row],[row_id]] ) - ROW( co_variants[[#Headers],[row_id]] ) -> 8 | C88: CILAgriculture | D88: Without CO2 Fertilization | E88: withoutCO2 | F88: Without CO2 Fertilization | G88: 0 | H88: 0 | I88: =INDEX( co_impactTypes[damageAdjName], MATCH( co_variants[[#This Row],[sector_id]], co_impactTypes[sector_id], 0 ) ) & IF( co_variants[[#This Row],[sector_id]] = "Roads", IF( co_variants[[#This Row],[variant_id_excel]] = "Proactive", "_proactive", "_other" ), "" ) -> none | J88: {=--( SUMPRODUCT( --( co_variants[[#This Row],[sector_id]] = data_scaledImpacts[sector] ), --( co_variants[[#This Row],[variant_id_excel]] = data_scaledImpacts[variant] ) ) > 1 )} -> 1 | K88: {=--( SUMPRODUCT( --( co_impactTypes[sector_id] = co_variants[[#This Row],[sector_id]] ) ) > 1 )} -> 1
B89: =ROW( co_variants[[#This Row],[row_id]] ) - ROW( co_variants[[#Headers],[row_id]] ) -> 9 | C89: CILCrime | D89: N/A | E89: NA | F89: N/A | G89: 1 | H89: 1 | I89: =INDEX( co_impactTypes[damageAdjName], MATCH( co_variants[[#This Row],[sector_id]], co_impactTypes[sector_id], 0 ) ) & IF( co_variants[[#This Row],[sector_id]] = "Roads", IF( co_variants[[#This Row],[variant_id_excel]] = "Proactive", "_proactive", "_other" ), "" ) -> none | J89: {=--( SUMPRODUCT( --( co_variants[[#This Row],[sector_id]] = data_scaledImpacts[sector] ), --( co_variants[[#This Row],[variant_id_excel]] = data_scaledImpacts[variant] ) ) > 1 )} -> 1 | K89: {=--( SUMPRODUCT( --( co_impactTypes[sector_id] = co_variants[[#This Row],[sector_id]] ) ) > 1 )} -> 1
B90: =ROW( co_variants[[#This Row],[row_id]] ) - ROW( co_variants[[#Headers],[row_id]] ) -> 10 | C90: CILExtremeTemp | D90: Median | E90: median | F90: median | G90: 1 | H90: 0 | I90: =INDEX( co_impactTypes[damageAdjName], MATCH( co_variants[[#This Row],[sector_id]], co_impactTypes[sector_id], 0 ) ) & IF( co_variants[[#This Row],[sector_id]] = "Roads", IF( co_variants[[#This Row],[variant_id_excel]] = "Proactive", "_proactive", "_other" ), "" ) -> none | J90: {=--( SUMPRODUCT( --( co_variants[[#This Row],[sector_id]] = data_scaledImpacts[sector] ), --( co_variants[[#This Row],[variant_id_excel]] = data_scaledImpacts[variant] ) ) > 1 )} -> 1 | K90: {=--( SUMPRODUCT( --( co_impactTypes[sector_id] = co_variants[[#This Row],[sector_id]] ) ) > 1 )} -> 0
B91: =ROW( co_variants[[#This Row],[row_id]] ) - ROW( co_variants[[#Headers],[row_id]] ) -> 11 | C91: CILExtremeTemp | D91: Low Confidence Interval | E91: low_CI | F91: low CI | G91: 0 | H91: 0 | I91: =INDEX( co_impactTypes[damageAdjName], MATCH( co_variants[[#This Row],[sector_id]], co_impactTypes[sector_id], 0 ) ) & IF( co_variants[[#This Row],[sector_id]] = "Roads", IF( co_variants[[#This Row],[variant_id_excel]] = "Proactive", "_proactive", "_other" ), "" ) -> none | J91: {=--( SUMPRODUCT( --( co_variants[[#This Row],[sector_id]] = data_scaledImpacts[sector] ), --( co_variants[[#This Row],[variant_id_excel]] = data_scaledImpacts[variant] ) ) > 1 )} -> 1 | K91: {=--( SUMPRODUCT( --( co_impactTypes[sector_id] = co_variants[[#This Row],[sector_id]] ) ) > 1 )} -> 0
B92: =ROW( co_variants[[#This Row],[row_id]] ) - ROW( co_variants[[#Headers],[row_id]] ) -> 12 | C92: CILExtremeTemp | D92: High Confidence Interval | E92: high_CI | F92: high CI | G92: 0 | H92: 0 | I92: =INDEX( co_impactTypes[damageAdjName], MATCH( co_variants[[#This Row],[sector_id]], co_impactTypes[sector_id], 0 ) ) & IF( co_variants[[#This Row],[sector_id]] = "Roads", IF( co_variants[[#This Row],[variant_id_excel]] = "Proactive", "_proactive", "_other" ), "" ) -> none | J92: {=--( SUMPRODUCT( --( co_variants[[#This Row],[sector_id]] = data_scaledImpacts[sector] ), --( co_variants[[#This Row],[variant_id_excel]] = data_scaledImpacts[variant] ) ) > 1 )} -> 1 | K92: {=--( SUMPRODUCT( --( co_impactTypes[sector_id] = co_variants[[#This Row],[sector_id]] ) ) > 1 )} -> 0
B93: =ROW( co_variants[[#This Row],[row_id]] ) - ROW( co_variants[[#Headers],[row_id]] ) -> 13 | C93: CoastalProperties | D93: No Additional Adaptation | E93: NoAdapt | F93: NoAdapt | G93: 0 | H93: 0 | I93: =INDEX( co_impactTypes[damageAdjName], MATCH( co_variants[[#This Row],[sector_id]], co_impactTypes[sector_id], 0 ) ) & IF( co_variants[[#This Row],[sector_id]] = "Roads", IF( co_variants[[#This Row],[variant_id_excel]] = "Proactive", "_proactive", "_other" ), "" ) -> none | J93: {=--( SUMPRODUCT( --( co_variants[[#This Row],[sector_id]] = data_scaledImpacts[sector] ), --( co_variants[[#This Row],[variant_id_excel]] = data_scaledImpacts[variant] ) ) > 1 )} -> 0 | K93: {=--( SUMPRODUCT( --( co_impactTypes[sector_id] = co_variants[[#This Row],[sector_id]] ) ) > 1 )} -> 0
B94: =ROW( co_variants[[#This Row],[row_id]] ) - ROW( co_variants[[#Headers],[row_id]] ) -> 14 | C94: CoastalProperties | D94: Proactive Adaptation | E94: Proactive | F94: Proactive | G94: 0 | H94: 0 | I94: =INDEX( co_impactTypes[damageAdjName], MATCH( co_variants[[#This Row],[sector_id]], co_impactTypes[sector_id], 0 ) ) & IF( co_variants[[#This Row],[sector_id]] = "Roads", IF( co_variants[[#This Row],[variant_id_excel]] = "Proactive", "_proactive", "_other" ), "" ) -> none | J94: {=--( SUMPRODUCT( --( co_variants[[#This Row],[sector_id]] = data_scaledImpacts[sector] ), --( co_variants[[#This Row],[variant_id_excel]] = data_scaledImpacts[variant] ) ) > 1 )} -> 0 | K94: {=--( SUMPRODUCT( --( co_impactTypes[sector_id] = co_variants[[#This Row],[sector_id]] ) ) > 1 )} -> 0
... B122: =ROW( co_variants[[#This Row],[row_id]] ) - ROW( co_variants[[#Headers],[row_id]] ) -> 42 | C122: WinterRec | D122: N/A | E122: NA | F122: N/A | G122: 1 | H122: 1 | I122: =INDEX( co_impactTypes[damageAdjName], MATCH( co_variants[[#This Row],[sector_id]], co_impactTypes[sector_id], 0 ) ) & IF( co_variants[[#This Row],[sector_id]] = "Roads", IF( co_variants[[#This Row],[variant_id_excel]] = "Proactive", "_proactive", "_other" ), "" ) -> none | J122: {=--( SUMPRODUCT( --( co_variants[[#This Row],[sector_id]] = data_scaledImpacts[sector] ), --( co_variants[[#This Row],[variant_id_excel]] = data_scaledImpacts[variant] ) ) > 1 )} -> 1 | K122: {=--( SUMPRODUCT( --( co_impactTypes[sector_id] = co_variants[[#This Row],[sector_id]] ) ) > 1 )} -> 1
B124: Impact Types
B125: "impactType_id" should have no spaces
B126: row_id | C126: sector_id | D126: impactType_label | E126: impactType_id | F126: impactType_id_excel | G126: impactType_description | H126: physicalmeasure | I126: physScalarName | J126: physAdjName | K126: damageAdjName | L126: econScalarName | M126: econMultiplierName | N126: c0 | O126: c1 | P126: exp0 | Q126: year0 | R126: check_data | S126: check_damageAdj | T126: check_econScalar | U126: check_physScalar
B127: =ROW( co_impactTypes[[#This Row],[row_id]] ) - ROW(co_impactTypes[[#Headers],[row_id]] ) -> 1 | C127: AirQuality | D127: Ozone | E127: O3 | F127: O3 | G127: Ozone | H127: Premature Mortality | I127: reg_pop | J127: none | K127: none | L127: vsl_usd | M127: gdp_percap | N127: 0 | O127: 1 | P127: 0.4 | Q127: =IF(co_impactTypes[[#This Row],[econMultiplierName]]="None", "N/A", 2010) -> 2010 | R127: {=IF( INDEX( co_sectors[modelType], MATCH( 1, --( co_impactTypes[[#This Row],[sector_id]] = co_sectors[sector_id] ), 0 ) ) = "gcm", --( SUMPRODUCT( --( co_impactTypes[[#This Row],[sector_id]] = data_scaledImpacts[sector] ), --( co_impactTypes[[#This Row],[impactType_id_excel]] = data_scaledImpacts[impactType] ) ) > 1 ), --( SUMPRODUCT( --( co_impactTypes[[#This Row],[sector_id]] = slrImpacts[sector] ), --( co_impactTypes[[#This Row],[impactType_id_excel]] = slrImpacts[impactType] ) ) > 1 ) )} -> 1 | S127: {=IF( co_impactTypes[[#This Row],[damageAdjName]] = "none", 1, --( SUMPRODUCT( --IF( ISERROR( FIND( co_impactTypes[[#This Row],[damageAdjName]], scalarDataframe[scalarName] ) ), 0, 1 ), --( "damageAdj" = scalarDataframe[scalarType] ) ) >= 1 ) )} -> 1 | T127: {=IF( co_impactTypes[[#This Row],[econScalarName]] = "none", 1, --( SUMPRODUCT( --IF( ISERROR( FIND( co_impactTypes[[#This Row],[econScalarName]], scalarDataframe[scalarName] ) ), 0, 1 ), --( "econScalar" = scalarDataframe[scalarType] ) ) >= 1 ) )} -> 1 | U127: {=IF( NOT( ISERROR( FIND( co_impactTypes[[#This Row],[physScalarName]], "none, reg_pop" ) ) ), 1, --( SUMPRODUCT( --IF( ISERROR( FIND( co_impactTypes[[#This Row],[physScalarName]], scalarDataframe[scalarName] ) ), 0, 1 ), --( "physScalar" = scalarDataframe[scalarType] ) ) >= 1 ) )} -> 1
B128: =ROW( co_impactTypes[[#This Row],[row_id]] ) - ROW(co_impactTypes[[#Headers],[row_id]] ) -> 2 | C128: AirQuality | D128: PM2.5 | E128: PM | F128: PM | G128: PM2.5 | H128: Premature Mortality | I128: reg_pop | J128: none | K128: none | L128: vsl_usd | M128: gdp_percap | N128: 0 | O128: 1 | P128: 0.4 | Q128: =IF(co_impactTypes[[#This Row],[econMultiplierName]]="None", "N/A", 2010) -> 2010 | R128: {=IF( INDEX( co_sectors[modelType], MATCH( 1, --( co_impactTypes[[#This Row],[sector_id]] = co_sectors[sector_id] ), 0 ) ) = "gcm", --( SUMPRODUCT( --( co_impactTypes[[#This Row],[sector_id]] = data_scaledImpacts[sector] ), --( co_impactTypes[[#This Row],[impactType_id_excel]] = data_scaledImpacts[impactType] ) ) > 1 ), --( SUMPRODUCT( --( co_impactTypes[[#This Row],[sector_id]] = slrImpacts[sector] ), --( co_impactTypes[[#This Row],[impactType_id_excel]] = slrImpacts[impactType] ) ) > 1 ) )} -> 1 | S128: {=IF( co_impactTypes[[#This Row],[damageAdjName]] = "none", 1, --( SUMPRODUCT( --IF( ISERROR( FIND( co_impactTypes[[#This Row],[damageAdjName]], scalarDataframe[scalarName] ) ), 0, 1 ), --( "damageAdj" = scalarDataframe[scalarType] ) ) >= 1 ) )} -> 1 | T128: {=IF( co_impactTypes[[#This Row],[econScalarName]] = "none", 1, --( SUMPRODUCT( --IF( ISERROR( FIND( co_impactTypes[[#This Row],[econScalarName]], scalarDataframe[scalarName] ) ), 0, 1 ), --( "econScalar" = scalarDataframe[scalarType] ) ) >= 1 ) )} -> 1 | U128: {=IF( NOT( ISERROR( FIND( co_impactTypes[[#This Row],[physScalarName]], "none, reg_pop" ) ) ), 1, --( SUMPRODUCT( --IF( ISERROR( FIND( co_impactTypes[[#This Row],[physScalarName]], scalarDataframe[scalarName] ) ), 0, 1 ), --( "physScalar" = scalarDataframe[scalarType] ) ) >= 1 ) )} -> 1
B129: =ROW( co_impactTypes[[#This Row],[row_id]] ) - ROW(co_impactTypes[[#Headers],[row_id]] ) -> 3 | C129: AsphaltRoads | D129: N/A | E129: NA | G129: Damages per lane mile | I129: asphaltRoads_laneMiles | J129: none | K129: none | L129: none | M129: none | N129: 0 | O129: 1 | P129: 1 | Q129: =IF(co_impactTypes[[#This Row],[econMultiplierName]]="None", "N/A", 2010) -> N/A | R129: {=IF( INDEX( co_sectors[modelType], MATCH( 1, --( co_impactTypes[[#This Row],[sector_id]] = co_sectors[sector_id] ), 0 ) ) = "gcm", --( SUMPRODUCT( --( co_impactTypes[[#This Row],[sector_id]] = data_scaledImpacts[sector] ), --( co_impactTypes[[#This Row],[impactType_id_excel]] = data_scaledImpacts[impactType] ) ) > 1 ), --( SUMPRODUCT( --( co_impactTypes[[#This Row],[sector_id]] = slrImpacts[sector] ), --( co_impactTypes[[#This Row],[impactType_id_excel]] = slrImpacts[impactType] ) ) > 1 ) )} -> 1 | S129: {=IF( co_impactTypes[[#This Row],[damageAdjName]] = "none", 1, --( SUMPRODUCT( --IF( ISERROR( FIND( co_impactTypes[[#This Row],[damageAdjName]], scalarDataframe[scalarName] ) ), 0, 1 ), --( "damageAdj" = scalarDataframe[scalarType] ) ) >= 1 ) )} -> 1 | T129: {=IF( co_impactTypes[[#This Row],[econScalarName]] = "none", 1, --( SUMPRODUCT( --IF( ISERROR( FIND( co_impactTypes[[#This Row],[econScalarName]], scalarDataframe[scalarName] ) ), 0, 1 ), --( "econScalar" = scalarDataframe[scalarType] ) ) >= 1 ) )} -> 1 | U129: {=IF( NOT( ISERROR( FIND( co_impactTypes[[#This Row],[physScalarName]], "none, reg_pop" ) ) ), 1, --( SUMPRODUCT( --IF( ISERROR( FIND( co_impactTypes[[#This Row],[physScalarName]], scalarDataframe[scalarName] ) ), 0, 1 ), --( "physScalar" = scalarDataframe[scalarType] ) ) >= 1 ) )} -> 1
B130: =ROW( co_impactTypes[[#This Row],[row_id]] ) - ROW(co_impactTypes[[#Headers],[row_id]] ) -> 4 | C130: ATSExtremeTemp | D130: N/A | E130: NA | G130: Net mortality (heat and cold) | H130: Premature Mortality | I130: reg_pop | J130: none | K130: none | L130: vsl_usd | M130: gdp_percap | N130: 0 | O130: 1 | P130: 0.4 | Q130: =IF(co_impactTypes[[#This Row],[econMultiplierName]]="None", "N/A", 2010) -> 2010 | R130: {=IF( INDEX( co_sectors[modelType], MATCH( 1, --( co_impactTypes[[#This Row],[sector_id]] = co_sectors[sector_id] ), 0 ) ) = "gcm", --( SUMPRODUCT( --( co_impactTypes[[#This Row],[sector_id]] = data_scaledImpacts[sector] ), --( co_impactTypes[[#This Row],[impactType_id_excel]] = data_scaledImpacts[impactType] ) ) > 1 ), --( SUMPRODUCT( --( co_impactTypes[[#This Row],[sector_id]] = slrImpacts[sector] ), --( co_impactTypes[[#This Row],[impactType_id_excel]] = slrImpacts[impactType] ) ) > 1 ) )} -> 1 | S130: {=IF( co_impactTypes[[#This Row],[damageAdjName]] = "none", 1, --( SUMPRODUCT( --IF( ISERROR( FIND( co_impactTypes[[#This Row],[damageAdjName]], scalarDataframe[scalarName] ) ), 0, 1 ), --( "damageAdj" = scalarDataframe[scalarType] ) ) >= 1 ) )} -> 1 | T130: {=IF( co_impactTypes[[#This Row],[econScalarName]] = "none", 1, --( SUMPRODUCT( --IF( ISERROR( FIND( co_impactTypes[[#This Row],[econScalarName]], scalarDataframe[scalarName] ) ), 0, 1 ), --( "econScalar" = scalarDataframe[scalarType] ) ) >= 1 ) )} -> 1 | U130: {=IF( NOT( ISERROR( FIND( co_impactTypes[[#This Row],[physScalarName]], "none, reg_pop" ) ) ), 1, --( SUMPRODUCT( --IF( ISERROR( FIND( co_impactTypes[[#This Row],[physScalarName]], scalarDataframe[scalarName] ) ), 0, 1 ), --( "physScalar" = scalarDataframe[scalarType] ) ) >= 1 ) )} -> 1
B131: =ROW( co_impactTypes[[#This Row],[row_id]] ) - ROW(co_impactTypes[[#Headers],[row_id]] ) -> 5 | C131: CILAgriculture | D131: Cotton | E131: Cotton | F131: Cotton | G131: Lost Production Value | I131: none | J131: none | K131: none | L131: none | M131: none | N131: 0 | O131: 1 | P131: 1 | Q131: =IF(co_impactTypes[[#This Row],[econMultiplierName]]="None", "N/A", 2010) -> N/A | R131: {=IF( INDEX( co_sectors[modelType], MATCH( 1, --( co_impactTypes[[#This Row],[sector_id]] = co_sectors[sector_id] ), 0 ) ) = "gcm", --( SUMPRODUCT( --( co_impactTypes[[#This Row],[sector_id]] = data_scaledImpacts[sector] ), --( co_impactTypes[[#This Row],[impactType_id_excel]] = data_scaledImpacts[impactType] ) ) > 1 ), --( SUMPRODUCT( --( co_impactTypes[[#This Row],[sector_id]] = slrImpacts[sector] ), --( co_impactTypes[[#This Row],[impactType_id_excel]] = slrImpacts[impactType] ) ) > 1 ) )} -> 1 | S131: {=IF( co_impactTypes[[#This Row],[damageAdjName]] = "none", 1, --( SUMPRODUCT( --IF( ISERROR( FIND( co_impactTypes[[#This Row],[damageAdjName]], scalarDataframe[scalarName] ) ), 0, 1 ), --( "damageAdj" = scalarDataframe[scalarType] ) ) >= 1 ) )} -> 1 | T131: {=IF( co_impactTypes[[#This Row],[econScalarName]] = "none", 1, --( SUMPRODUCT( --IF( ISERROR( FIND( co_impactTypes[[#This Row],[econScalarName]], scalarDataframe[scalarName] ) ), 0, 1 ), --( "econScalar" = scalarDataframe[scalarType] ) ) >= 1 ) )} -> 1 | U131: {=IF( NOT( ISERROR( FIND( co_impactTypes[[#This Row],[physScalarName]], "none, reg_pop" ) ) ), 1, --( SUMPRODUCT( --IF( ISERROR( FIND( co_impactTypes[[#This Row],[physScalarName]], scalarDataframe[scalarName] ) ), 0, 1 ), --( "physScalar" = scalarDataframe[scalarType] ) ) >= 1 ) )} -> 1
B132: =ROW( co_impactTypes[[#This Row],[row_id]] ) - ROW(co_impactTypes[[#Headers],[row_id]] ) -> 6 | C132: CILAgriculture | D132: Maize | E132: Maize | F132: Maize | G132: Lost Production Value | I132: none | J132: none | K132: none | L132: none | M132: none | N132: 0 | O132: 1 | P132: 1 | Q132: =IF(co_impactTypes[[#This Row],[econMultiplierName]]="None", "N/A", 2010) -> N/A | R132: {=IF( INDEX( co_sectors[modelType], MATCH( 1, --( co_impactTypes[[#This Row],[sector_id]] = co_sectors[sector_id] ), 0 ) ) = "gcm", --( SUMPRODUCT( --( co_impactTypes[[#This Row],[sector_id]] = data_scaledImpacts[sector] ), --( co_impactTypes[[#This Row],[impactType_id_excel]] = data_scaledImpacts[impactType] ) ) > 1 ), --( SUMPRODUCT( --( co_impactTypes[[#This Row],[sector_id]] = slrImpacts[sector] ), --( co_impactTypes[[#This Row],[impactType_id_excel]] = slrImpacts[impactType] ) ) > 1 ) )} -> 1 | S132: {=IF( co_impactTypes[[#This Row],[damageAdjName]] = "none", 1, --( SUMPRODUCT( --IF( ISERROR( FIND( co_impactTypes[[#This Row],[damageAdjName]], scalarDataframe[scalarName] ) ), 0, 1 ), --( "damageAdj" = scalarDataframe[scalarType] ) ) >= 1 ) )} -> 1 | T132: {=IF( co_impactTypes[[#This Row],[econScalarName]] = "none", 1, --( SUMPRODUCT( --IF( ISERROR( FIND( co_impactTypes[[#This Row],[econScalarName]], scalarDataframe[scalarName] ) ), 0, 1 ), --( "econScalar" = scalarDataframe[scalarType] ) ) >= 1 ) )} -> 1 | U132: {=IF( NOT( ISERROR( FIND( co_impactTypes[[#This Row],[physScalarName]], "none, reg_pop" ) ) ), 1, --( SUMPRODUCT( --IF( ISERROR( FIND( co_impactTypes[[#This Row],[physScalarName]], scalarDataframe[scalarName] ) ), 0, 1 ), --( "physScalar" = scalarDataframe[scalarType] ) ) >= 1 ) )} -> 1
B133: =ROW( co_impactTypes[[#This Row],[row_id]] ) - ROW(co_impactTypes[[#Headers],[row_id]] ) -> 7 | C133: CILAgriculture | D133: Soybean | E133: Soybean | F133: Soybean | G133: Lost Production Value | I133: none | J133: none | K133: none | L133: none | M133: none | N133: 0 | O133: 1 | P133: 1 | Q133: =IF(co_impactTypes[[#This Row],[econMultiplierName]]="None", "N/A", 2010) -> N/A | R133: {=IF( INDEX( co_sectors[modelType], MATCH( 1, --( co_impactTypes[[#This Row],[sector_id]] = co_sectors[sector_id] ), 0 ) ) = "gcm", --( SUMPRODUCT( --( co_impactTypes[[#This Row],[sector_id]] = data_scaledImpacts[sector] ), --( co_impactTypes[[#This Row],[impactType_id_excel]] = data_scaledImpacts[impactType] ) ) > 1 ), --( SUMPRODUCT( --( co_impactTypes[[#This Row],[sector_id]] = slrImpacts[sector] ), --( co_impactTypes[[#This Row],[impactType_id_excel]] = slrImpacts[impactType] ) ) > 1 ) )} -> 1 | S133: {=IF( co_impactTypes[[#This Row],[damageAdjName]] = "none", 1, --( SUMPRODUCT( --IF( ISERROR( FIND( co_impactTypes[[#This Row],[damageAdjName]], scalarDataframe[scalarName] ) ), 0, 1 ), --( "damageAdj" = scalarDataframe[scalarType] ) ) >= 1 ) )} -> 1 | T133: {=IF( co_impactTypes[[#This Row],[econScalarName]] = "none", 1, --( SUMPRODUCT( --IF( ISERROR( FIND( co_impactTypes[[#This Row],[econScalarName]], scalarDataframe[scalarName] ) ), 0, 1 ), --( "econScalar" = scalarDataframe[scalarType] ) ) >= 1 ) )} -> 1 | U133: {=IF( NOT( ISERROR( FIND( co_impactTypes[[#This Row],[physScalarName]], "none, reg_pop" ) ) ), 1, --( SUMPRODUCT( --IF( ISERROR( FIND( co_impactTypes[[#This Row],[physScalarName]], scalarDataframe[scalarName] ) ), 0, 1 ), --( "physScalar" = scalarDataframe[scalarType] ) ) >= 1 ) )} -> 1
B134: =ROW( co_impactTypes[[#This Row],[row_id]] ) - ROW(co_impactTypes[[#Headers],[row_id]] ) -> 8 | C134: CILAgriculture | D134: Wheat | E134: Wheat | F134: Wheat | G134: Lost Production Value | I134: none | J134: none | K134: none | L134: none | M134: none | N134: 0 | O134: 1 | P134: 1 | Q134: =IF(co_impactTypes[[#This Row],[econMultiplierName]]="None", "N/A", 2010) -> N/A | R134: {=IF( INDEX( co_sectors[modelType], MATCH( 1, --( co_impactTypes[[#This Row],[sector_id]] = co_sectors[sector_id] ), 0 ) ) = "gcm", --( SUMPRODUCT( --( co_impactTypes[[#This Row],[sector_id]] = data_scaledImpacts[sector] ), --( co_impactTypes[[#This Row],[impactType_id_excel]] = data_scaledImpacts[impactType] ) ) > 1 ), --( SUMPRODUCT( --( co_impactTypes[[#This Row],[sector_id]] = slrImpacts[sector] ), --( co_impactTypes[[#This Row],[impactType_id_excel]] = slrImpacts[impactType] ) ) > 1 ) )} -> 1 | S134: {=IF( co_impactTypes[[#This Row],[damageAdjName]] = "none", 1, --( SUMPRODUCT( --IF( ISERROR( FIND( co_impactTypes[[#This Row],[damageAdjName]], scalarDataframe[scalarName] ) ), 0, 1 ), --( "damageAdj" = scalarDataframe[scalarType] ) ) >= 1 ) )} -> 1 | T134: {=IF( co_impactTypes[[#This Row],[econScalarName]] = "none", 1, --( SUMPRODUCT( --IF( ISERROR( FIND( co_impactTypes[[#This Row],[econScalarName]], scalarDataframe[scalarName] ) ), 0, 1 ), --( "econScalar" = scalarDataframe[scalarType] ) ) >= 1 ) )} -> 1 | U134: {=IF( NOT( ISERROR( FIND( co_impactTypes[[#This Row],[physScalarName]], "none, reg_pop" ) ) ), 1, --( SUMPRODUCT( --IF( ISERROR( FIND( co_impactTypes[[#This Row],[physScalarName]], scalarDataframe[scalarName] ) ), 0, 1 ), --( "physScalar" = scalarDataframe[scalarType] ) ) >= 1 ) )} -> 1
B135: =ROW( co_impactTypes[[#This Row],[row_id]] ) - ROW(co_impactTypes[[#Headers],[row_id]] ) -> 9 | C135: CILCrime | D135: Property | E135: Property | F135: Property | G135: Cost of crime | H135: Crimes | I135: none | J135: none | K135: none | L135: property_crime_costs_usd | M135: none | N135: 0 | O135: 1 | P135: 1 | Q135: =IF(co_impactTypes[[#This Row],[econMultiplierName]]="None", "N/A", 2010) -> N/A | R135: {=IF( INDEX( co_sectors[modelType], MATCH( 1, --( co_impactTypes[[#This Row],[sector_id]] = co_sectors[sector_id] ), 0 ) ) = "gcm", --( SUMPRODUCT( --( co_impactTypes[[#This Row],[sector_id]] = data_scaledImpacts[sector] ), --( co_impactTypes[[#This Row],[impactType_id_excel]] = data_scaledImpacts[impactType] ) ) > 1 ), --( SUMPRODUCT( --( co_impactTypes[[#This Row],[sector_id]] = slrImpacts[sector] ), --( co_impactTypes[[#This Row],[impactType_id_excel]] = slrImpacts[impactType] ) ) > 1 ) )} -> 1 | S135: {=IF( co_impactTypes[[#This Row],[damageAdjName]] = "none", 1, --( SUMPRODUCT( --IF( ISERROR( FIND( co_impactTypes[[#This Row],[damageAdjName]], scalarDataframe[scalarName] ) ), 0, 1 ), --( "damageAdj" = scalarDataframe[scalarType] ) ) >= 1 ) )} -> 1 | T135: {=IF( co_impactTypes[[#This Row],[econScalarName]] = "none", 1, --( SUMPRODUCT( --IF( ISERROR( FIND( co_impactTypes[[#This Row],[econScalarName]], scalarDataframe[scalarName] ) ), 0, 1 ), --( "econScalar" = scalarDataframe[scalarType] ) ) >= 1 ) )} -> 1 | U135: {=IF( NOT( ISERROR( FIND( co_impactTypes[[#This Row],[physScalarName]], "none, reg_pop" ) ) ), 1, --( SUMPRODUCT( --IF( ISERROR( FIND( co_impactTypes[[#This Row],[physScalarName]], scalarDataframe[scalarName] ) ), 0, 1 ), --( "physScalar" = scalarDataframe[scalarType] ) ) >= 1 ) )} -> 1
B136: =ROW( co_impactTypes[[#This Row],[row_id]] ) - ROW(co_impactTypes[[#Headers],[row_id]] ) -> 10 | C136: CILCrime | D136: Violent | E136: Violent | F136: Violent | G136: Cost of crime | H136: Crimes | I136: none | J136: none | K136: none | L136: violent_crime_costs_usd | M136: none | N136: 0 | O136: 1 | P136: 1 | Q136: =IF(co_impactTypes[[#This Row],[econMultiplierName]]="None", "N/A", 2010) -> N/A | R136: {=IF( INDEX( co_sectors[modelType], MATCH( 1, --( co_impactTypes[[#This Row],[sector_id]] = co_sectors[sector_id] ), 0 ) ) = "gcm", --( SUMPRODUCT( --( co_impactTypes[[#This Row],[sector_id]] = data_scaledImpacts[sector] ), --( co_impactTypes[[#This Row],[impactType_id_excel]] = data_scaledImpacts[impactType] ) ) > 1 ), --( SUMPRODUCT( --( co_impactTypes[[#This Row],[sector_id]] = slrImpacts[sector] ), --( co_impactTypes[[#This Row],[impactType_id_excel]] = slrImpacts[impactType] ) ) > 1 ) )} -> 1 | S136: {=IF( co_impactTypes[[#This Row],[damageAdjName]] = "none", 1, --( SUMPRODUCT( --IF( ISERROR( FIND( co_impactTypes[[#This Row],[damageAdjName]], scalarDataframe[scalarName] ) ), 0, 1 ), --( "damageAdj" = scalarDataframe[scalarType] ) ) >= 1 ) )} -> 1 | T136: {=IF( co_impactTypes[[#This Row],[econScalarName]] = "none", 1, --( SUMPRODUCT( --IF( ISERROR( FIND( co_impactTypes[[#This Row],[econScalarName]], scalarDataframe[scalarName] ) ), 0, 1 ), --( "econScalar" = scalarDataframe[scalarType] ) ) >= 1 ) )} -> 1 | U136: {=IF( NOT( ISERROR( FIND( co_impactTypes[[#This Row],[physScalarName]], "none, reg_pop" ) ) ), 1, --( SUMPRODUCT( --IF( ISERROR( FIND( co_impactTypes[[#This Row],[physScalarName]], scalarDataframe[scalarName] ) ), 0, 1 ), --( "physScalar" = scalarDataframe[scalarType] ) ) >= 1 ) )} -> 1
B137: =ROW( co_impactTypes[[#This Row],[row_id]] ) - ROW(co_impactTypes[[#Headers],[row_id]] ) -> 11 | C137: CILExtremeTemp | D137: N/A | E137: NA | G137: Mortality | H137: Premature Mortality | I137: reg_pop | J137: none | K137: none | L137: vsl_usd | M137: gdp_percap | N137: 0 | O137: 1 | P137: 0.4 | Q137: =IF(co_impactTypes[[#This Row],[econMultiplierName]]="None", "N/A", 2010) -> 2010 | R137: {=IF( INDEX( co_sectors[modelType], MATCH( 1, --( co_impactTypes[[#This Row],[sector_id]] = co_sectors[sector_id] ), 0 ) ) = "gcm", --( SUMPRODUCT( --( co_impactTypes[[#This Row],[sector_id]] = data_scaledImpacts[sector] ), --( co_impactTypes[[#This Row],[impactType_id_excel]] = data_scaledImpacts[impactType] ) ) > 1 ), --( SUMPRODUCT( --( co_impactTypes[[#This Row],[sector_id]] = slrImpacts[sector] ), --( co_impactTypes[[#This Row],[impactType_id_excel]] = slrImpacts[impactType] ) ) > 1 ) )} -> 1 | S137: {=IF( co_impactTypes[[#This Row],[damageAdjName]] = "none", 1, --( SUMPRODUCT( --IF( ISERROR( FIND( co_impactTypes[[#This Row],[damageAdjName]], scalarDataframe[scalarName] ) ), 0, 1 ), --( "damageAdj" = scalarDataframe[scalarType] ) ) >= 1 ) )} -> 1 | T137: {=IF( co_impactTypes[[#This Row],[econScalarName]] = "none", 1, --( SUMPRODUCT( --IF( ISERROR( FIND( co_impactTypes[[#This Row],[econScalarName]], scalarDataframe[scalarName] ) ), 0, 1 ), --( "econScalar" = scalarDataframe[scalarType] ) ) >= 1 ) )} -> 1 | U137: {=IF( NOT( ISERROR( FIND( co_impactTypes[[#This Row],[physScalarName]], "none, reg_pop" ) ) ), 1, --( SUMPRODUCT( --IF( ISERROR( FIND( co_impactTypes[[#This Row],[physScalarName]], scalarDataframe[scalarName] ) ), 0, 1 ), --( "physScalar" = scalarDataframe[scalarType] ) ) >= 1 ) )} -> 1
B138: =ROW( co_impactTypes[[#This Row],[row_id]] ) - ROW(co_impactTypes[[#Headers],[row_id]] ) -> 12 | C138: CoastalProperties | D138: N/A | E138: NA | F138: NA | G138: Coastal Property Damage | I138: none | J138: none | K138: none | L138: none | M138: none | N138: 0 | O138: 1 | P138: 1 | Q138: =IF(co_impactTypes[[#This Row],[econMultiplierName]]="None", "N/A", 2010) -> N/A | R138: {=IF( INDEX( co_sectors[modelType], MATCH( 1, --( co_impactTypes[[#This Row],[sector_id]] = co_sectors[sector_id] ), 0 ) ) = "gcm", --( SUMPRODUCT( --( co_impactTypes[[#This Row],[sector_id]] = data_scaledImpacts[sector] ), --( co_impactTypes[[#This Row],[impactType_id_excel]] = data_scaledImpacts[impactType] ) ) > 1 ), --( SUMPRODUCT( --( co_impactTypes[[#This Row],[sector_id]] = slrImpacts[sector] ), --( co_impactTypes[[#This Row],[impactType_id_excel]] = slrImpacts[impactType] ) ) > 1 ) )} -> 1 | S138: {=IF( co_impactTypes[[#This Row],[damageAdjName]] = "none", 1, --( SUMPRODUCT( --IF( ISERROR( FIND( co_impactTypes[[#This Row],[damageAdjName]], scalarDataframe[scalarName] ) ), 0, 1 ), --( "damageAdj" = scalarDataframe[scalarType] ) ) >= 1 ) )} -> 1 | T138: {=IF( co_impactTypes[[#This Row],[econScalarName]] = "none", 1, --( SUMPRODUCT( --IF( ISERROR( FIND( co_impactTypes[[#This Row],[econScalarName]], scalarDataframe[scalarName] ) ), 0, 1 ), --( "econScalar" = scalarDataframe[scalarType] ) ) >= 1 ) )} -> 1 | U138: {=IF( NOT( ISERROR( FIND( co_impactTypes[[#This Row],[physScalarName]], "none, reg_pop" ) ) ), 1, --( SUMPRODUCT( --IF( ISERROR( FIND( co_impactTypes[[#This Row],[physScalarName]], scalarDataframe[scalarName] ) ), 0, 1 ), --( "physScalar" = scalarDataframe[scalarType] ) ) >= 1 ) )} -> 1
B139: =ROW( co_impactTypes[[#This Row],[row_id]] ) - ROW(co_impactTypes[[#Headers],[row_id]] ) -> 13 | C139: ElecSD | D139: N/A | E139: NA | G139: Change in power sector costs from reference scenario | I139: none | J139: none | K139: elecSD_refCosts | L139: none | M139: none | N139: 0 | O139: 1 | P139: 1 | Q139: =IF(co_impactTypes[[#This Row],[econMultiplierName]]="None", "N/A", 2010) -> N/A | R139: {=IF( INDEX( co_sectors[modelType], MATCH( 1, --( co_impactTypes[[#This Row],[sector_id]] = co_sectors[sector_id] ), 0 ) ) = "gcm", --( SUMPRODUCT( --( co_impactTypes[[#This Row],[sector_id]] = data_scaledImpacts[sector] ), --( co_impactTypes[[#This Row],[impactType_id_excel]] = data_scaledImpacts[impactType] ) ) > 1 ), --( SUMPRODUCT( --( co_impactTypes[[#This Row],[sector_id]] = slrImpacts[sector] ), --( co_impactTypes[[#This Row],[impactType_id_excel]] = slrImpacts[impactType] ) ) > 1 ) )} -> 1 | S139: {=IF( co_impactTypes[[#This Row],[damageAdjName]] = "none", 1, --( SUMPRODUCT( --IF( ISERROR( FIND( co_impactTypes[[#This Row],[damageAdjName]], scalarDataframe[scalarName] ) ), 0, 1 ), --( "damageAdj" = scalarDataframe[scalarType] ) ) >= 1 ) )} -> 1 | T139: {=IF( co_impactTypes[[#This Row],[econScalarName]] = "none", 1, --( SUMPRODUCT( --IF( ISERROR( FIND( co_impactTypes[[#This Row],[econScalarName]], scalarDataframe[scalarName] ) ), 0, 1 ), --( "econScalar" = scalarDataframe[scalarType] ) ) >= 1 ) )} -> 1 | U139: {=IF( NOT( ISERROR( FIND( co_impactTypes[[#This Row],[physScalarName]], "none, reg_pop" ) ) ), 1, --( SUMPRODUCT( --IF( ISERROR( FIND( co_impactTypes[[#This Row],[physScalarName]], scalarDataframe[scalarName] ) ), 0, 1 ), --( "physScalar" = scalarDataframe[scalarType] ) ) >= 1 ) )} -> 1
B140: =ROW( co_impactTypes[[#This Row],[row_id]] ) - ROW(co_impactTypes[[#Headers],[row_id]] ) -> 14 | C140: ElecTD | D140: N/A | E140: NA | G140: Electricity Transmission Impacts | I140: none | J140: none | K140: elecTD_growthFactor | L140: none | M140: none | N140: 0 | O140: 1 | P140: 1 | Q140: =IF(co_impactTypes[[#This Row],[econMultiplierName]]="None", "N/A", 2010) -> N/A | R140: {=IF( INDEX( co_sectors[modelType], MATCH( 1, --( co_impactTypes[[#This Row],[sector_id]] = co_sectors[sector_id] ), 0 ) ) = "gcm", --( SUMPRODUCT( --( co_impactTypes[[#This Row],[sector_id]] = data_scaledImpacts[sector] ), --( co_impactTypes[[#This Row],[impactType_id_excel]] = data_scaledImpacts[impactType] ) ) > 1 ), --( SUMPRODUCT( --( co_impactTypes[[#This Row],[sector_id]] = slrImpacts[sector] ), --( co_impactTypes[[#This Row],[impactType_id_excel]] = slrImpacts[impactType] ) ) > 1 ) )} -> 1 | S140: {=IF( co_impactTypes[[#This Row],[damageAdjName]] = "none", 1, --( SUMPRODUCT( --IF( ISERROR( FIND( co_impactTypes[[#This Row],[damageAdjName]], scalarDataframe[scalarName] ) ), 0, 1 ), --( "damageAdj" = scalarDataframe[scalarType] ) ) >= 1 ) )} -> 1 | T140: {=IF( co_impactTypes[[#This Row],[econScalarName]] = "none", 1, --( SUMPRODUCT( --IF( ISERROR( FIND( co_impactTypes[[#This Row],[econScalarName]], scalarDataframe[scalarName] ) ), 0, 1 ), --( "econScalar" = scalarDataframe[scalarType] ) ) >= 1 ) )} -> 1 | U140: {=IF( NOT( ISERROR( FIND( co_impactTypes[[#This Row],[physScalarName]], "none, reg_pop" ) ) ), 1, --( SUMPRODUCT( --IF( ISERROR( FIND( co_impactTypes[[#This Row],[physScalarName]], scalarDataframe[scalarName] ) ), 0, 1 ), --( "physScalar" = scalarDataframe[scalarType] ) ) >= 1 ) )} -> 1
B141: =ROW( co_impactTypes[[#This Row],[row_id]] ) - ROW(co_impactTypes[[#Headers],[row_id]] ) -> 15 | C141: ExtremeTemp | D141: Cold | E141: cold | F141: cold | G141: Extreme Cold | H141: Premature Mortality | I141: reg_pop | J141: city_popWt | K141: none | L141: vsl_usd | M141: gdp_percap | N141: 0 | O141: 1 | P141: 0.4 | Q141: =IF(co_impactTypes[[#This Row],[econMultiplierName]]="None", "N/A", 2010) -> 2010 | R141: {=IF( INDEX( co_sectors[modelType], MATCH( 1, --( co_impactTypes[[#This Row],[sector_id]] = co_sectors[sector_id] ), 0 ) ) = "gcm", --( SUMPRODUCT( --( co_impactTypes[[#This Row],[sector_id]] = data_scaledImpacts[sector] ), --( co_impactTypes[[#This Row],[impactType_id_excel]] = data_scaledImpacts[impactType] ) ) > 1 ), --( SUMPRODUCT( --( co_impactTypes[[#This Row],[sector_id]] = slrImpacts[sector] ), --( co_impactTypes[[#This Row],[impactType_id_excel]] = slrImpacts[impactType] ) ) > 1 ) )} -> 1 | S141: {=IF( co_impactTypes[[#This Row],[damageAdjName]] = "none", 1, --( SUMPRODUCT( --IF( ISERROR( FIND( co_impactTypes[[#This Row],[damageAdjName]], scalarDataframe[scalarName] ) ), 0, 1 ), --( "damageAdj" = scalarDataframe[scalarType] ) ) >= 1 ) )} -> 1 | T141: {=IF( co_impactTypes[[#This Row],[econScalarName]] = "none", 1, --( SUMPRODUCT( --IF( ISERROR( FIND( co_impactTypes[[#This Row],[econScalarName]], scalarDataframe[scalarName] ) ), 0, 1 ), --( "econScalar" = scalarDataframe[scalarType] ) ) >= 1 ) )} -> 1 | U141: {=IF( NOT( ISERROR( FIND( co_impactTypes[[#This Row],[physScalarName]], "none, reg_pop" ) ) ), 1, --( SUMPRODUCT( --IF( ISERROR( FIND( co_impactTypes[[#This Row],[physScalarName]], scalarDataframe[scalarName] ) ), 0, 1 ), --( "physScalar" = scalarDataframe[scalarType] ) ) >= 1 ) )} -> 1
B142: =ROW( co_impactTypes[[#This Row],[row_id]] ) - ROW(co_impactTypes[[#Headers],[row_id]] ) -> 16 | C142: ExtremeTemp | D142: Hot | E142: hot | F142: hot | G142: Extreme Heat | H142: Premature Mortality | I142: reg_pop | J142: city_popWt | K142: none | L142: vsl_usd | M142: gdp_percap | N142: 0 | O142: 1 | P142: 0.4 | Q142: =IF(co_impactTypes[[#This Row],[econMultiplierName]]="None", "N/A", 2010) -> 2010 | R142: {=IF( INDEX( co_sectors[modelType], MATCH( 1, --( co_impactTypes[[#This Row],[sector_id]] = co_sectors[sector_id] ), 0 ) ) = "gcm", --( SUMPRODUCT( --( co_impactTypes[[#This Row],[sector_id]] = data_scaledImpacts[sector] ), --( co_impactTypes[[#This Row],[impactType_id_excel]] = data_scaledImpacts[impactType] ) ) > 1 ), --( SUMPRODUCT( --( co_impactTypes[[#This Row],[sector_id]] = slrImpacts[sector] ), --( co_impactTypes[[#This Row],[impactType_id_excel]] = slrImpacts[impactType] ) ) > 1 ) )} -> 1 | S142: {=IF( co_impactTypes[[#This Row],[damageAdjName]] = "none", 1, --( SUMPRODUCT( --IF( ISERROR( FIND( co_impactTypes[[#This Row],[damageAdjName]], scalarDataframe[scalarName] ) ), 0, 1 ), --( "damageAdj" = scalarDataframe[scalarType] ) ) >= 1 ) )} -> 1 | T142: {=IF( co_impactTypes[[#This Row],[econScalarName]] = "none", 1, --( SUMPRODUCT( --IF( ISERROR( FIND( co_impactTypes[[#This Row],[econScalarName]], scalarDataframe[scalarName] ) ), 0, 1 ), --( "econScalar" = scalarDataframe[scalarType] ) ) >= 1 ) )} -> 1 | U142: {=IF( NOT( ISERROR( FIND( co_impactTypes[[#This Row],[physScalarName]], "none, reg_pop" ) ) ), 1, --( SUMPRODUCT( --IF( ISERROR( FIND( co_impactTypes[[#This Row],[physScalarName]], scalarDataframe[scalarName] ) ), 0, 1 ), --( "physScalar" = scalarDataframe[scalarType] ) ) >= 1 ) )} -> 1
B143: =ROW( co_impactTypes[[#This Row],[row_id]] ) - ROW(co_impactTypes[[#Headers],[row_id]] ) -> 17 | C143: HTF | D143: N/A | E143: NA | F143: NA | G143: Traffic delays and adaptation costs due to high tide flooding | I143: none | J143: none | K143: none | L143: none | M143: none | N143: 0 | O143: 1 | P143: 1 | Q143: =IF(co_impactTypes[[#This Row],[econMultiplierName]]="None", "N/A", 2010) -> N/A | R143: {=IF( INDEX( co_sectors[modelType], MATCH( 1, --( co_impactTypes[[#This Row],[sector_id]] = co_sectors[sector_id] ), 0 ) ) = "gcm", --( SUMPRODUCT( --( co_impactTypes[[#This Row],[sector_id]] = data_scaledImpacts[sector] ), --( co_impactTypes[[#This Row],[impactType_id_excel]] = data_scaledImpacts[impactType] ) ) > 1 ), --( SUMPRODUCT( --( co_impactTypes[[#This Row],[sector_id]] = slrImpacts[sector] ), --( co_impactTypes[[#This Row],[impactType_id_excel]] = slrImpacts[impactType] ) ) > 1 ) )} -> 1 | S143: {=IF( co_impactTypes[[#This Row],[damageAdjName]] = "none", 1, --( SUMPRODUCT( --IF( ISERROR( FIND( co_impactTypes[[#This Row],[damageAdjName]], scalarDataframe[scalarName] ) ), 0, 1 ), --( "damageAdj" = scalarDataframe[scalarType] ) ) >= 1 ) )} -> 1 | T143: {=IF( co_impactTypes[[#This Row],[econScalarName]] = "none", 1, --( SUMPRODUCT( --IF( ISERROR( FIND( co_impactTypes[[#This Row],[econScalarName]], scalarDataframe[scalarName] ) ), 0, 1 ), --( "econScalar" = scalarDataframe[scalarType] ) ) >= 1 ) )} -> 1 | U143: {=IF( NOT( ISERROR( FIND( co_impactTypes[[#This Row],[physScalarName]], "none, reg_pop" ) ) ), 1, --( SUMPRODUCT( --IF( ISERROR( FIND( co_impactTypes[[#This Row],[physScalarName]], scalarDataframe[scalarName] ) ), 0, 1 ), --( "physScalar" = scalarDataframe[scalarType] ) ) >= 1 ) )} -> 1
B144: =ROW( co_impactTypes[[#This Row],[row_id]] ) - ROW(co_impactTypes[[#Headers],[row_id]] ) -> 18 | C144: InlandFlooding | D144: N/A | E144: NA | G144: Expected annual damage (property damage valuation) | I144: none | J144: none | K144: none | L144: none | M144: none | N144: 0 | O144: 1 | P144: 1 | Q144: =IF(co_impactTypes[[#This Row],[econMultiplierName]]="None", "N/A", 2010) -> N/A | R144: {=IF( INDEX( co_sectors[modelType], MATCH( 1, --( co_impactTypes[[#This Row],[sector_id]] = co_sectors[sector_id] ), 0 ) ) = "gcm", --( SUMPRODUCT( --( co_impactTypes[[#This Row],[sector_id]] = data_scaledImpacts[sector] ), --( co_impactTypes[[#This Row],[impactType_id_excel]] = data_scaledImpacts[impactType] ) ) > 1 ), --( SUMPRODUCT( --( co_impactTypes[[#This Row],[sector_id]] = slrImpacts[sector] ), --( co_impactTypes[[#This Row],[impactType_id_excel]] = slrImpacts[impactType] ) ) > 1 ) )} -> 1 | S144: {=IF( co_impactTypes[[#This Row],[damageAdjName]] = "none", 1, --( SUMPRODUCT( --IF( ISERROR( FIND( co_impactTypes[[#This Row],[damageAdjName]], scalarDataframe[scalarName] ) ), 0, 1 ), --( "damageAdj" = scalarDataframe[scalarType] ) ) >= 1 ) )} -> 1 | T144: {=IF( co_impactTypes[[#This Row],[econScalarName]] = "none", 1, --( SUMPRODUCT( --IF( ISERROR( FIND( co_impactTypes[[#This Row],[econScalarName]], scalarDataframe[scalarName] ) ), 0, 1 ), --( "econScalar" = scalarDataframe[scalarType] ) ) >= 1 ) )} -> 1 | U144: {=IF( NOT( ISERROR( FIND( co_impactTypes[[#This Row],[physScalarName]], "none, reg_pop" ) ) ), 1, --( SUMPRODUCT( --IF( ISERROR( FIND( co_impactTypes[[#This Row],[physScalarName]], scalarDataframe[scalarName] ) ), 0, 1 ), --( "physScalar" = scalarDataframe[scalarType] ) ) >= 1 ) )} -> 1
B145: =ROW( co_impactTypes[[#This Row],[row_id]] ) - ROW(co_impactTypes[[#Headers],[row_id]] ) -> 19 | C145: Labor | D145: N/A | E145: LostWages | G145: Lost Wages for High-Risk Occupations | H145: Hours Lost | I145: highRiskLabor_pop | J145: none | K145: none | L145: highRiskWages_usd | M145: gdp_percap | N145: 0 | O145: 1 | P145: 1 | Q145: =IF(co_impactTypes[[#This Row],[econMultiplierName]]="None", "N/A", 2010) -> 2010 | R145: {=IF( INDEX( co_sectors[modelType], MATCH( 1, --( co_impactTypes[[#This Row],[sector_id]] = co_sectors[sector_id] ), 0 ) ) = "gcm", --( SUMPRODUCT( --( co_impactTypes[[#This Row],[sector_id]] = data_scaledImpacts[sector] ), --( co_impactTypes[[#This Row],[impactType_id_excel]] = data_scaledImpacts[impactType] ) ) > 1 ), --( SUMPRODUCT( --( co_impactTypes[[#This Row],[sector_id]] = slrImpacts[sector] ), --( co_impactTypes[[#This Row],[impactType_id_excel]] = slrImpacts[impactType] ) ) > 1 ) )} -> 1 | S145: {=IF( co_impactTypes[[#This Row],[damageAdjName]] = "none", 1, --( SUMPRODUCT( --IF( ISERROR( FIND( co_impactTypes[[#This Row],[damageAdjName]], scalarDataframe[scalarName] ) ), 0, 1 ), --( "damageAdj" = scalarDataframe[scalarType] ) ) >= 1 ) )} -> 1 | T145: {=IF( co_impactTypes[[#This Row],[econScalarName]] = "none", 1, --( SUMPRODUCT( --IF( ISERROR( FIND( co_impactTypes[[#This Row],[econScalarName]], scalarDataframe[scalarName] ) ), 0, 1 ), --( "econScalar" = scalarDataframe[scalarType] ) ) >= 1 ) )} -> 1 | U145: {=IF( NOT( ISERROR( FIND( co_impactTypes[[#This Row],[physScalarName]], "none, reg_pop" ) ) ), 1, --( SUMPRODUCT( --IF( ISERROR( FIND( co_impactTypes[[#This Row],[physScalarName]], scalarDataframe[scalarName] ) ), 0, 1 ), --( "physScalar" = scalarDataframe[scalarType] ) ) >= 1 ) )} -> 1
B146: =ROW( co_impactTypes[[#This Row],[row_id]] ) - ROW(co_impactTypes[[#Headers],[row_id]] ) -> 20 | C146: MarineFisheries | D146: N/A | E146: NA | G146: Decrease in revenue | I146: none | J146: none | K146: none | L146: none | M146: none | N146: 0 | O146: 1000000 | P146: 1 | Q146: =IF(co_impactTypes[[#This Row],[econMultiplierName]]="None", "N/A", 2010) -> N/A | R146: {=IF( INDEX( co_sectors[modelType], MATCH( 1, --( co_impactTypes[[#This Row],[sector_id]] = co_sectors[sector_id] ), 0 ) ) = "gcm", --( SUMPRODUCT( --( co_impactTypes[[#This Row],[sector_id]] = data_scaledImpacts[sector] ), --( co_impactTypes[[#This Row],[impactType_id_excel]] = data_scaledImpacts[impactType] ) ) > 1 ), --( SUMPRODUCT( --( co_impactTypes[[#This Row],[sector_id]] = slrImpacts[sector] ), --( co_impactTypes[[#This Row],[impactType_id_excel]] = slrImpacts[impactType] ) ) > 1 ) )} -> 1 | S146: {=IF( co_impactTypes[[#This Row],[damageAdjName]] = "none", 1, --( SUMPRODUCT( --IF( ISERROR( FIND( co_impactTypes[[#This Row],[damageAdjName]], scalarDataframe[scalarName] ) ), 0, 1 ), --( "damageAdj" = scalarDataframe[scalarType] ) ) >= 1 ) )} -> 1 | T146: {=IF( co_impactTypes[[#This Row],[econScalarName]] = "none", 1, --( SUMPRODUCT( --IF( ISERROR( FIND( co_impactTypes[[#This Row],[econScalarName]], scalarDataframe[scalarName] ) ), 0, 1 ), --( "econScalar" = scalarDataframe[scalarType] ) ) >= 1 ) )} -> 1 | U146: {=IF( NOT( ISERROR( FIND( co_impactTypes[[#This Row],[physScalarName]], "none, reg_pop" ) ) ), 1, --( SUMPRODUCT( --IF( ISERROR( FIND( co_impactTypes[[#This Row],[physScalarName]], scalarDataframe[scalarName] ) ), 0, 1 ), --( "physScalar" = scalarDataframe[scalarType] ) ) >= 1 ) )} -> 1
B147: =ROW( co_impactTypes[[#This Row],[row_id]] ) - ROW(co_impactTypes[[#Headers],[row_id]] ) -> 21 | C147: MentalHealth | D147: N/A | E147: NA | G147: Mortality from suicide | H147: Premature Mortality | I147: reg_pop | J147: MH_popSliceAdj | K147: MH_popDemoAdj | L147: vsl_usd | M147: gdp_percap | N147: 0 | O147: 1 | P147: 0.4 | Q147: =IF(co_impactTypes[[#This Row],[econMultiplierName]]="None", "N/A", 2010) -> 2010 | R147: {=IF( INDEX( co_sectors[modelType], MATCH( 1, --( co_impactTypes[[#This Row],[sector_id]] = co_sectors[sector_id] ), 0 ) ) = "gcm", --( SUMPRODUCT( --( co_impactTypes[[#This Row],[sector_id]] = data_scaledImpacts[sector] ), --( co_impactTypes[[#This Row],[impactType_id_excel]] = data_scaledImpacts[impactType] ) ) > 1 ), --( SUMPRODUCT( --( co_impactTypes[[#This Row],[sector_id]] = slrImpacts[sector] ), --( co_impactTypes[[#This Row],[impactType_id_excel]] = slrImpacts[impactType] ) ) > 1 ) )} -> 1 | S147: {=IF( co_impactTypes[[#This Row],[damageAdjName]] = "none", 1, --( SUMPRODUCT( --IF( ISERROR( FIND( co_impactTypes[[#This Row],[damageAdjName]], scalarDataframe[scalarName] ) ), 0, 1 ), --( "damageAdj" = scalarDataframe[scalarType] ) ) >= 1 ) )} -> 1 | T147: {=IF( co_impactTypes[[#This Row],[econScalarName]] = "none", 1, --( SUMPRODUCT( --IF( ISERROR( FIND( co_impactTypes[[#This Row],[econScalarName]], scalarDataframe[scalarName] ) ), 0, 1 ), --( "econScalar" = scalarDataframe[scalarType] ) ) >= 1 ) )} -> 1 | U147: {=IF( NOT( ISERROR( FIND( co_impactTypes[[#This Row],[physScalarName]], "none, reg_pop" ) ) ), 1, --( SUMPRODUCT( --IF( ISERROR( FIND( co_impactTypes[[#This Row],[physScalarName]], scalarDataframe[scalarName] ) ), 0, 1 ), --( "physScalar" = scalarDataframe[scalarType] ) ) >= 1 ) )} -> 1
B148: =ROW( co_impactTypes[[#This Row],[row_id]] ) - ROW(co_impactTypes[[#Headers],[row_id]] ) -> 22 | C148: Rail | D148: N/A | E148: NA | G148: Rail Impacts | I148: rail_miles | J148: none | K148: rail_growth_factor | L148: none | M148: none | N148: 0 | O148: 1 | P148: 1 | Q148: =IF(co_impactTypes[[#This Row],[econMultiplierName]]="None", "N/A", 2010) -> N/A | R148: {=IF( INDEX( co_sectors[modelType], MATCH( 1, --( co_impactTypes[[#This Row],[sector_id]] = co_sectors[sector_id] ), 0 ) ) = "gcm", --( SUMPRODUCT( --( co_impactTypes[[#This Row],[sector_id]] = data_scaledImpacts[sector] ), --( co_impactTypes[[#This Row],[impactType_id_excel]] = data_scaledImpacts[impactType] ) ) > 1 ), --( SUMPRODUCT( --( co_impactTypes[[#This Row],[sector_id]] = slrImpacts[sector] ), --( co_impactTypes[[#This Row],[impactType_id_excel]] = slrImpacts[impactType] ) ) > 1 ) )} -> 1 | S148: {=IF( co_impactTypes[[#This Row],[damageAdjName]] = "none", 1, --( SUMPRODUCT( --IF( ISERROR( FIND( co_impactTypes[[#This Row],[damageAdjName]], scalarDataframe[scalarName] ) ), 0, 1 ), --( "damageAdj" = scalarDataframe[scalarType] ) ) >= 1 ) )} -> 1 | T148: {=IF( co_impactTypes[[#This Row],[econScalarName]] = "none", 1, --( SUMPRODUCT( --IF( ISERROR( FIND( co_impactTypes[[#This Row],[econScalarName]], scalarDataframe[scalarName] ) ), 0, 1 ), --( "econScalar" = scalarDataframe[scalarType] ) ) >= 1 ) )} -> 1 | U148: {=IF( NOT( ISERROR( FIND( co_impactTypes[[#This Row],[physScalarName]], "none, reg_pop" ) ) ), 1, --( SUMPRODUCT( --IF( ISERROR( FIND( co_impactTypes[[#This Row],[physScalarName]], scalarDataframe[scalarName] ) ), 0, 1 ), --( "physScalar" = scalarDataframe[scalarType] ) ) >= 1 ) )} -> 1
B149: =ROW( co_impactTypes[[#This Row],[row_id]] ) - ROW(co_impactTypes[[#Headers],[row_id]] ) -> 23 | C149: Roads | D149: N/A | E149: NA | G149: Road Impacts | I149: road_miles | J149: none | K149: road_miles_and_pop | L149: none | M149: none | N149: 0 | O149: 1 | P149: 1 | Q149: =IF(co_impactTypes[[#This Row],[econMultiplierName]]="None", "N/A", 2010) -> N/A | R149: {=IF( INDEX( co_sectors[modelType], MATCH( 1, --( co_impactTypes[[#This Row],[sector_id]] = co_sectors[sector_id] ), 0 ) ) = "gcm", --( SUMPRODUCT( --( co_impactTypes[[#This Row],[sector_id]] = data_scaledImpacts[sector] ), --( co_impactTypes[[#This Row],[impactType_id_excel]] = data_scaledImpacts[impactType] ) ) > 1 ), --( SUMPRODUCT( --( co_impactTypes[[#This Row],[sector_id]] = slrImpacts[sector] ), --( co_impactTypes[[#This Row],[impactType_id_excel]] = slrImpacts[impactType] ) ) > 1 ) )} -> 1 | S149: {=IF( co_impactTypes[[#This Row],[damageAdjName]] = "none", 1, --( SUMPRODUCT( --IF( ISERROR( FIND( co_impactTypes[[#This Row],[damageAdjName]], scalarDataframe[scalarName] ) ), 0, 1 ), --( "damageAdj" = scalarDataframe[scalarType] ) ) >= 1 ) )} -> 1 | T149: {=IF( co_impactTypes[[#This Row],[econScalarName]] = "none", 1, --( SUMPRODUCT( --IF( ISERROR( FIND( co_impactTypes[[#This Row],[econScalarName]], scalarDataframe[scalarName] ) ), 0, 1 ), --( "econScalar" = scalarDataframe[scalarType] ) ) >= 1 ) )} -> 1 | U149: {=IF( NOT( ISERROR( FIND( co_impactTypes[[#This Row],[physScalarName]], "none, reg_pop" ) ) ), 1, --( SUMPRODUCT( --IF( ISERROR( FIND( co_impactTypes[[#This Row],[physScalarName]], scalarDataframe[scalarName] ) ), 0, 1 ), --( "physScalar" = scalarDataframe[scalarType] ) ) >= 1 ) )} -> 1
B150: =ROW( co_impactTypes[[#This Row],[row_id]] ) - ROW(co_impactTypes[[#Headers],[row_id]] ) -> 24 | C150: SouthwestDust | D150: Acute Myocardial Infarction | E150: ACMI | F150: ACMI | G150: Hospitalization (Acute Myocardial Infarction) | I150: reg_pop | J150: swDust_popWt | K150: none | L150: hospCosts_cardio | M150: none | N150: 0 | O150: 1 | P150: 1 | Q150: =IF(co_impactTypes[[#This Row],[econMultiplierName]]="None", "N/A", 2010) -> N/A | R150: {=IF( INDEX( co_sectors[modelType], MATCH( 1, --( co_impactTypes[[#This Row],[sector_id]] = co_sectors[sector_id] ), 0 ) ) = "gcm", --( SUMPRODUCT( --( co_impactTypes[[#This Row],[sector_id]] = data_scaledImpacts[sector] ), --( co_impactTypes[[#This Row],[impactType_id_excel]] = data_scaledImpacts[impactType] ) ) > 1 ), --( SUMPRODUCT( --( co_impactTypes[[#This Row],[sector_id]] = slrImpacts[sector] ), --( co_impactTypes[[#This Row],[impactType_id_excel]] = slrImpacts[impactType] ) ) > 1 ) )} -> 1 | S150: {=IF( co_impactTypes[[#This Row],[damageAdjName]] = "none", 1, --( SUMPRODUCT( --IF( ISERROR( FIND( co_impactTypes[[#This Row],[damageAdjName]], scalarDataframe[scalarName] ) ), 0, 1 ), --( "damageAdj" = scalarDataframe[scalarType] ) ) >= 1 ) )} -> 1 | T150: {=IF( co_impactTypes[[#This Row],[econScalarName]] = "none", 1, --( SUMPRODUCT( --IF( ISERROR( FIND( co_impactTypes[[#This Row],[econScalarName]], scalarDataframe[scalarName] ) ), 0, 1 ), --( "econScalar" = scalarDataframe[scalarType] ) ) >= 1 ) )} -> 1 | U150: {=IF( NOT( ISERROR( FIND( co_impactTypes[[#This Row],[physScalarName]], "none, reg_pop" ) ) ), 1, --( SUMPRODUCT( --IF( ISERROR( FIND( co_impactTypes[[#This Row],[physScalarName]], scalarDataframe[scalarName] ) ), 0, 1 ), --( "physScalar" = scalarDataframe[scalarType] ) ) >= 1 ) )} -> 1
B151: =ROW( co_impactTypes[[#This Row],[row_id]] ) - ROW(co_impactTypes[[#Headers],[row_id]] ) -> 25 | C151: SouthwestDust | D151: All Cardiovascular | E151: AllCardiovasc | F151: AllCardiovasc | G151: Hospitalization (Cardiovascular) | I151: reg_pop | J151: swDust_popWt | K151: none | L151: hospCosts_cardio | M151: none | N151: 0 | O151: 1 | P151: 1 | Q151: =IF(co_impactTypes[[#This Row],[econMultiplierName]]="None", "N/A", 2010) -> N/A | R151: {=IF( INDEX( co_sectors[modelType], MATCH( 1, --( co_impactTypes[[#This Row],[sector_id]] = co_sectors[sector_id] ), 0 ) ) = "gcm", --( SUMPRODUCT( --( co_impactTypes[[#This Row],[sector_id]] = data_scaledImpacts[sector] ), --( co_impactTypes[[#This Row],[impactType_id_excel]] = data_scaledImpacts[impactType] ) ) > 1 ), --( SUMPRODUCT( --( co_impactTypes[[#This Row],[sector_id]] = slrImpacts[sector] ), --( co_impactTypes[[#This Row],[impactType_id_excel]] = slrImpacts[impactType] ) ) > 1 ) )} -> 1 | S151: {=IF( co_impactTypes[[#This Row],[damageAdjName]] = "none", 1, --( SUMPRODUCT( --IF( ISERROR( FIND( co_impactTypes[[#This Row],[damageAdjName]], scalarDataframe[scalarName] ) ), 0, 1 ), --( "damageAdj" = scalarDataframe[scalarType] ) ) >= 1 ) )} -> 1 | T151: {=IF( co_impactTypes[[#This Row],[econScalarName]] = "none", 1, --( SUMPRODUCT( --IF( ISERROR( FIND( co_impactTypes[[#This Row],[econScalarName]], scalarDataframe[scalarName] ) ), 0, 1 ), --( "econScalar" = scalarDataframe[scalarType] ) ) >= 1 ) )} -> 1 | U151: {=IF( NOT( ISERROR( FIND( co_impactTypes[[#This Row],[physScalarName]], "none, reg_pop" ) ) ), 1, --( SUMPRODUCT( --IF( ISERROR( FIND( co_impactTypes[[#This Row],[physScalarName]], scalarDataframe[scalarName] ) ), 0, 1 ), --( "physScalar" = scalarDataframe[scalarType] ) ) >= 1 ) )} -> 1
B152: =ROW( co_impactTypes[[#This Row],[row_id]] ) - ROW(co_impactTypes[[#Headers],[row_id]] ) -> 26 | C152: SouthwestDust | D152: All Mortality | E152: AllMort | F152: AllMort | G152: All Mortality | H152: Premature Mortality | I152: reg_pop | J152: swDust_popWt | K152: none | L152: vsl_usd | M152: gdp_percap | N152: 0 | O152: 1 | P152: 0.4 | Q152: =IF(co_impactTypes[[#This Row],[econMultiplierName]]="None", "N/A", 2010) -> 2010 | R152: {=IF( INDEX( co_sectors[modelType], MATCH( 1, --( co_impactTypes[[#This Row],[sector_id]] = co_sectors[sector_id] ), 0 ) ) = "gcm", --( SUMPRODUCT( --( co_impactTypes[[#This Row],[sector_id]] = data_scaledImpacts[sector] ), --( co_impactTypes[[#This Row],[impactType_id_excel]] = data_scaledImpacts[impactType] ) ) > 1 ), --( SUMPRODUCT( --( co_impactTypes[[#This Row],[sector_id]] = slrImpacts[sector] ), --( co_impactTypes[[#This Row],[impactType_id_excel]] = slrImpacts[impactType] ) ) > 1 ) )} -> 1 | S152: {=IF( co_impactTypes[[#This Row],[damageAdjName]] = "none", 1, --( SUMPRODUCT( --IF( ISERROR( FIND( co_impactTypes[[#This Row],[damageAdjName]], scalarDataframe[scalarName] ) ), 0, 1 ), --( "damageAdj" = scalarDataframe[scalarType] ) ) >= 1 ) )} -> 1 | T152: {=IF( co_impactTypes[[#This Row],[econScalarName]] = "none", 1, --( SUMPRODUCT( --IF( ISERROR( FIND( co_impactTypes[[#This Row],[econScalarName]], scalarDataframe[scalarName] ) ), 0, 1 ), --( "econScalar" = scalarDataframe[scalarType] ) ) >= 1 ) )} -> 1 | U152: {=IF( NOT( ISERROR( FIND( co_impactTypes[[#This Row],[physScalarName]], "none, reg_pop" ) ) ), 1, --( SUMPRODUCT( --IF( ISERROR( FIND( co_impactTypes[[#This Row],[physScalarName]], scalarDataframe[scalarName] ) ), 0, 1 ), --( "physScalar" = scalarDataframe[scalarType] ) ) >= 1 ) )} -> 1
B153: =ROW( co_impactTypes[[#This Row],[row_id]] ) - ROW(co_impactTypes[[#Headers],[row_id]] ) -> 27 | C153: SouthwestDust | D153: All Respiratory | E153: AllResp | F153: AllResp | G153: Hospitalization (Respiratory) | I153: reg_pop | J153: swDust_popWt | K153: none | L153: hospCosts_resp | M153: none | N153: 0 | O153: 1 | P153: 1 | Q153: =IF(co_impactTypes[[#This Row],[econMultiplierName]]="None", "N/A", 2010) -> N/A | R153: {=IF( INDEX( co_sectors[modelType], MATCH( 1, --( co_impactTypes[[#This Row],[sector_id]] = co_sectors[sector_id] ), 0 ) ) = "gcm", --( SUMPRODUCT( --( co_impactTypes[[#This Row],[sector_id]] = data_scaledImpacts[sector] ), --( co_impactTypes[[#This Row],[impactType_id_excel]] = data_scaledImpacts[impactType] ) ) > 1 ), --( SUMPRODUCT( --( co_impactTypes[[#This Row],[sector_id]] = slrImpacts[sector] ), --( co_impactTypes[[#This Row],[impactType_id_excel]] = slrImpacts[impactType] ) ) > 1 ) )} -> 1 | S153: {=IF( co_impactTypes[[#This Row],[damageAdjName]] = "none", 1, --( SUMPRODUCT( --IF( ISERROR( FIND( co_impactTypes[[#This Row],[damageAdjName]], scalarDataframe[scalarName] ) ), 0, 1 ), --( "damageAdj" = scalarDataframe[scalarType] ) ) >= 1 ) )} -> 1 | T153: {=IF( co_impactTypes[[#This Row],[econScalarName]] = "none", 1, --( SUMPRODUCT( --IF( ISERROR( FIND( co_impactTypes[[#This Row],[econScalarName]], scalarDataframe[scalarName] ) ), 0, 1 ), --( "econScalar" = scalarDataframe[scalarType] ) ) >= 1 ) )} -> 1 | U153: {=IF( NOT( ISERROR( FIND( co_impactTypes[[#This Row],[physScalarName]], "none, reg_pop" ) ) ), 1, --( SUMPRODUCT( --IF( ISERROR( FIND( co_impactTypes[[#This Row],[physScalarName]], scalarDataframe[scalarName] ) ), 0, 1 ), --( "physScalar" = scalarDataframe[scalarType] ) ) >= 1 ) )} -> 1
B154: =ROW( co_impactTypes[[#This Row],[row_id]] ) - ROW(co_impactTypes[[#Headers],[row_id]] ) -> 28 | C154: SouthwestDust | D154: Asthma ER | E154: AsthmaER | F154: AsthmaER | G154: Asthma ED Visits | I154: reg_pop | J154: swDust_popWt | K154: none | L154: hospCosts_asthma | M154: none | N154: 0 | O154: 1 | P154: 1 | Q154: =IF(co_impactTypes[[#This Row],[econMultiplierName]]="None", "N/A", 2010) -> N/A | R154: {=IF( INDEX( co_sectors[modelType], MATCH( 1, --( co_impactTypes[[#This Row],[sector_id]] = co_sectors[sector_id] ), 0 ) ) = "gcm", --( SUMPRODUCT( --( co_impactTypes[[#This Row],[sector_id]] = data_scaledImpacts[sector] ), --( co_impactTypes[[#This Row],[impactType_id_excel]] = data_scaledImpacts[impactType] ) ) > 1 ), --( SUMPRODUCT( --( co_impactTypes[[#This Row],[sector_id]] = slrImpacts[sector] ), --( co_impactTypes[[#This Row],[impactType_id_excel]] = slrImpacts[impactType] ) ) > 1 ) )} -> 1 | S154: {=IF( co_impactTypes[[#This Row],[damageAdjName]] = "none", 1, --( SUMPRODUCT( --IF( ISERROR( FIND( co_impactTypes[[#This Row],[damageAdjName]], scalarDataframe[scalarName] ) ), 0, 1 ), --( "damageAdj" = scalarDataframe[scalarType] ) ) >= 1 ) )} -> 1 | T154: {=IF( co_impactTypes[[#This Row],[econScalarName]] = "none", 1, --( SUMPRODUCT( --IF( ISERROR( FIND( co_impactTypes[[#This Row],[econScalarName]], scalarDataframe[scalarName] ) ), 0, 1 ), --( "econScalar" = scalarDataframe[scalarType] ) ) >= 1 ) )} -> 1 | U154: {=IF( NOT( ISERROR( FIND( co_impactTypes[[#This Row],[physScalarName]], "none, reg_pop" ) ) ), 1, --( SUMPRODUCT( --IF( ISERROR( FIND( co_impactTypes[[#This Row],[physScalarName]], scalarDataframe[scalarName] ) ), 0, 1 ), --( "physScalar" = scalarDataframe[scalarType] ) ) >= 1 ) )} -> 1
B155: =ROW( co_impactTypes[[#This Row],[row_id]] ) - ROW(co_impactTypes[[#Headers],[row_id]] ) -> 29 | C155: UrbanDrainage | D155: N/A | E155: NA | G155: Proactive costs of improving urban drainage infrastructure | I155: none | J155: none | K155: none | L155: none | M155: none | N155: 0 | O155: =10^6 -> 1000000 | P155: 1 | Q155: =IF(co_impactTypes[[#This Row],[econMultiplierName]]="None", "N/A", 2010) -> N/A | R155: {=IF( INDEX( co_sectors[modelType], MATCH( 1, --( co_impactTypes[[#This Row],[sector_id]] = co_sectors[sector_id] ), 0 ) ) = "gcm", --( SUMPRODUCT( --( co_impactTypes[[#This Row],[sector_id]] = data_scaledImpacts[sector] ), --( co_impactTypes[[#This Row],[impactType_id_excel]] = data_scaledImpacts[impactType] ) ) > 1 ), --( SUMPRODUCT( --( co_impactTypes[[#This Row],[sector_id]] = slrImpacts[sector] ), --( co_impactTypes[[#This Row],[impactType_id_excel]] = slrImpacts[impactType] ) ) > 1 ) )} -> 1 | S155: {=IF( co_impactTypes[[#This Row],[damageAdjName]] = "none", 1, --( SUMPRODUCT( --IF( ISERROR( FIND( co_impactTypes[[#This Row],[damageAdjName]], scalarDataframe[scalarName] ) ), 0, 1 ), --( "damageAdj" = scalarDataframe[scalarType] ) ) >= 1 ) )} -> 1 | T155: {=IF( co_impactTypes[[#This Row],[econScalarName]] = "none", 1, --( SUMPRODUCT( --IF( ISERROR( FIND( co_impactTypes[[#This Row],[econScalarName]], scalarDataframe[scalarName] ) ), 0, 1 ), --( "econScalar" = scalarDataframe[scalarType] ) ) >= 1 ) )} -> 1 | U155: {=IF( NOT( ISERROR( FIND( co_impactTypes[[#This Row],[physScalarName]], "none, reg_pop" ) ) ), 1, --( SUMPRODUCT( --IF( ISERROR( FIND( co_impactTypes[[#This Row],[physScalarName]], scalarDataframe[scalarName] ) ), 0, 1 ), --( "physScalar" = scalarDataframe[scalarType] ) ) >= 1 ) )} -> 1
B156: =ROW( co_impactTypes[[#This Row],[row_id]] ) - ROW(co_impactTypes[[#Headers],[row_id]] ) -> 30 | C156: ValleyFever | D156: Lost Wages | E156: LostWages | F156: Lost Wages | G156: Lost Wages | I156: reg_pop | J156: vfever_prob_wages | K156: none | L156: daily_wages | M156: gdp_percap | N156: 0 | O156: 1 | P156: 1 | Q156: =IF(co_impactTypes[[#This Row],[econMultiplierName]]="None", "N/A", 2010) -> 2010 | R156: {=IF( INDEX( co_sectors[modelType], MATCH( 1, --( co_impactTypes[[#This Row],[sector_id]] = co_sectors[sector_id] ), 0 ) ) = "gcm", --( SUMPRODUCT( --( co_impactTypes[[#This Row],[sector_id]] = data_scaledImpacts[sector] ), --( co_impactTypes[[#This Row],[impactType_id_excel]] = data_scaledImpacts[impactType] ) ) > 1 ), --( SUMPRODUCT( --( co_impactTypes[[#This Row],[sector_id]] = slrImpacts[sector] ), --( co_impactTypes[[#This Row],[impactType_id_excel]] = slrImpacts[impactType] ) ) > 1 ) )} -> 1 | S156: {=IF( co_impactTypes[[#This Row],[damageAdjName]] = "none", 1, --( SUMPRODUCT( --IF( ISERROR( FIND( co_impactTypes[[#This Row],[damageAdjName]], scalarDataframe[scalarName] ) ), 0, 1 ), --( "damageAdj" = scalarDataframe[scalarType] ) ) >= 1 ) )} -> 1 | T156: {=IF( co_impactTypes[[#This Row],[econScalarName]] = "none", 1, --( SUMPRODUCT( --IF( ISERROR( FIND( co_impactTypes[[#This Row],[econScalarName]], scalarDataframe[scalarName] ) ), 0, 1 ), --( "econScalar" = scalarDataframe[scalarType] ) ) >= 1 ) )} -> 1 | U156: {=IF( NOT( ISERROR( FIND( co_impactTypes[[#This Row],[physScalarName]], "none, reg_pop" ) ) ), 1, --( SUMPRODUCT( --IF( ISERROR( FIND( co_impactTypes[[#This Row],[physScalarName]], scalarDataframe[scalarName] ) ), 0, 1 ), --( "physScalar" = scalarDataframe[scalarType] ) ) >= 1 ) )} -> 1
B157: =ROW( co_impactTypes[[#This Row],[row_id]] ) - ROW(co_impactTypes[[#Headers],[row_id]] ) -> 31 | C157: ValleyFever | D157: Morbidity | E157: Morbidity | F157: Morbidity | G157: Morbidity | I157: reg_pop | J157: vfever_morbidity_prob | K157: none | L157: vfever_illness_costs | M157: none | N157: 0 | O157: 1 | P157: 1 | Q157: =IF(co_impactTypes[[#This Row],[econMultiplierName]]="None", "N/A", 2010) -> N/A | R157: {=IF( INDEX( co_sectors[modelType], MATCH( 1, --( co_impactTypes[[#This Row],[sector_id]] = co_sectors[sector_id] ), 0 ) ) = "gcm", --( SUMPRODUCT( --( co_impactTypes[[#This Row],[sector_id]] = data_scaledImpacts[sector] ), --( co_impactTypes[[#This Row],[impactType_id_excel]] = data_scaledImpacts[impactType] ) ) > 1 ), --( SUMPRODUCT( --( co_impactTypes[[#This Row],[sector_id]] = slrImpacts[sector] ), --( co_impactTypes[[#This Row],[impactType_id_excel]] = slrImpacts[impactType] ) ) > 1 ) )} -> 1 | S157: {=IF( co_impactTypes[[#This Row],[damageAdjName]] = "none", 1, --( SUMPRODUCT( --IF( ISERROR( FIND( co_impactTypes[[#This Row],[damageAdjName]], scalarDataframe[scalarName] ) ), 0, 1 ), --( "damageAdj" = scalarDataframe[scalarType] ) ) >= 1 ) )} -> 1 | T157: {=IF( co_impactTypes[[#This Row],[econScalarName]] = "none", 1, --( SUMPRODUCT( --IF( ISERROR( FIND( co_impactTypes[[#This Row],[econScalarName]], scalarDataframe[scalarName] ) ), 0, 1 ), --( "econScalar" = scalarDataframe[scalarType] ) ) >= 1 ) )} -> 1 | U157: {=IF( NOT( ISERROR( FIND( co_impactTypes[[#This Row],[physScalarName]], "none, reg_pop" ) ) ), 1, --( SUMPRODUCT( --IF( ISERROR( FIND( co_impactTypes[[#This Row],[physScalarName]], scalarDataframe[scalarName] ) ), 0, 1 ), --( "physScalar" = scalarDataframe[scalarType] ) ) >= 1 ) )} -> 1
B158: =ROW( co_impactTypes[[#This Row],[row_id]] ) - ROW(co_impactTypes[[#Headers],[row_id]] ) -> 32 | C158: ValleyFever | D158: Mortality | E158: Mortality | F158: Mortality | G158: Mortality | H158: Premature Mortality | I158: reg_pop | J158: vfever_prob_mortality | K158: none | L158: vsl_usd | M158: gdp_percap | N158: 0 | O158: 1 | P158: 0.4 | Q158: =IF(co_impactTypes[[#This Row],[econMultiplierName]]="None", "N/A", 2010) -> 2010 | R158: {=IF( INDEX( co_sectors[modelType], MATCH( 1, --( co_impactTypes[[#This Row],[sector_id]] = co_sectors[sector_id] ), 0 ) ) = "gcm", --( SUMPRODUCT( --( co_impactTypes[[#This Row],[sector_id]] = data_scaledImpacts[sector] ), --( co_impactTypes[[#This Row],[impactType_id_excel]] = data_scaledImpacts[impactType] ) ) > 1 ), --( SUMPRODUCT( --( co_impactTypes[[#This Row],[sector_id]] = slrImpacts[sector] ), --( co_impactTypes[[#This Row],[impactType_id_excel]] = slrImpacts[impactType] ) ) > 1 ) )} -> 1 | S158: {=IF( co_impactTypes[[#This Row],[damageAdjName]] = "none", 1, --( SUMPRODUCT( --IF( ISERROR( FIND( co_impactTypes[[#This Row],[damageAdjName]], scalarDataframe[scalarName] ) ), 0, 1 ), --( "damageAdj" = scalarDataframe[scalarType] ) ) >= 1 ) )} -> 1 | T158: {=IF( co_impactTypes[[#This Row],[econScalarName]] = "none", 1, --( SUMPRODUCT( --IF( ISERROR( FIND( co_impactTypes[[#This Row],[econScalarName]], scalarDataframe[scalarName] ) ), 0, 1 ), --( "econScalar" = scalarDataframe[scalarType] ) ) >= 1 ) )} -> 1 | U158: {=IF( NOT( ISERROR( FIND( co_impactTypes[[#This Row],[physScalarName]], "none, reg_pop" ) ) ), 1, --( SUMPRODUCT( --IF( ISERROR( FIND( co_impactTypes[[#This Row],[physScalarName]], scalarDataframe[scalarName] ) ), 0, 1 ), --( "physScalar" = scalarDataframe[scalarType] ) ) >= 1 ) )} -> 1
...

Sheet defaultScenario
B2: Default socioeconomic scenario
B3: row_id | C3: year | D3: gdp_usd | E3: pop_Midwest | F3: pop_Northeast | G3: pop_Northern.Plains | H3: pop_Northwest | I3: pop_Southeast | J3: pop_Southern.Plains | K3: pop_Southwest
B4: =ROW( co_defaultScenario[[#This Row],[row_id]] ) - ROW( co_defaultScenario[[#Headers],[row_id]] ) -> 1 | C4: 2010 | D4: 1.6693672e+13 | E4: 60760771 | F4: 64443443 | G4: 4866153 | H4: 12123196 | I4: 76532629 | J4: 31750030 | K4: 56198784
B5: =ROW( co_defaultScenario[[#This Row],[row_id]] ) - ROW( co_defaultScenario[[#Headers],[row_id]] ) -> 2 | C5: 2015 | D5: 1.8459286e+13 | E5: 62531700 | F5: 66262356 | G5: 5143618.4 | H5: 12500441 | I5: 79584504 | J5: 33914631 | K5: 59678477
B6: =ROW( co_defaultScenario[[#This Row],[row_id]] ) - ROW( co_defaultScenario[[#Headers],[row_id]] ) -> 3 | C6: 2020 | D6: 2.0956428e+13 | E6: 64097103 | F6: 67903699 | G6: 5394605.1 | H6: 12816323 | I6: 82228514 | J6: 35921126 | K6: 62947312
B7: =ROW( co_defaultScenario[[#This Row],[row_id]] ) - ROW( co_defaultScenario[[#Headers],[row_id]] ) -> 4 | C7: 2025 | D7: 2.350259e+13 | E7: 65655846 | F7: 69515267 | G7: 5640953.5 | H7: 13124230 | I7: 84797999 | J7: 37898560 | K7: 66137464
B8: =ROW( co_defaultScenario[[#This Row],[row_id]] ) - ROW( co_defaultScenario[[#Headers],[row_id]] ) -> 5 | C8: 2030 | D8: 2.6191153e+13 | E8: 66987745 | F8: 70975809 | G8: 5863187.6 | H8: 13399008 | I8: 87135477 | J8: 39793579 | K8: 69224308
B9: =ROW( co_defaultScenario[[#This Row],[row_id]] ) - ROW( co_defaultScenario[[#Headers],[row_id]] ) -> 6 | C9: 2035 | D9: 2.891476e+13 | E9: 67985079 | F9: 72264293 | G9: 6050736.6 | H9: 13622298 | I9: 89177634 | J9: 41541842 | K9: 72174762
B10: =ROW( co_defaultScenario[[#This Row],[row_id]] ) - ROW( co_defaultScenario[[#Headers],[row_id]] ) -> 7 | C10: 2040 | D10: 3.2112407e+13 | E10: 68741241 | F10: 73411923 | G10: 6214809.4 | H10: 13805065 | I10: 90996054 | J10: 43133591 | K10: 74957385
B11: =ROW( co_defaultScenario[[#This Row],[row_id]] ) - ROW( co_defaultScenario[[#Headers],[row_id]] ) -> 8 | C11: 2045 | D11: 3.5194683e+13 | E11: 69343598 | F11: 74455788 | G11: 6361549.6 | H11: 13960224 | I11: 92638619 | J11: 44583572 | K11: 77572679
B12: =ROW( co_defaultScenario[[#This Row],[row_id]] ) - ROW( co_defaultScenario[[#Headers],[row_id]] ) -> 9 | C12: 2050 | D12: 3.8477619e+13 | E12: 69918188 | F12: 75470921 | G12: 6502332.4 | H12: 14107875 | I12: 94235017 | J12: 45957244 | K12: 80065339
B13: =ROW( co_defaultScenario[[#This Row],[row_id]] ) - ROW( co_defaultScenario[[#Headers],[row_id]] ) -> 10 | C13: 2055 | D13: 4.1964197e+13 | E13: 70505868 | F13: 76489049 | G13: 6641433.2 | H13: 14254356 | I13: 95838507 | J13: 47283831 | K13: 82455432
B14: =ROW( co_defaultScenario[[#This Row],[row_id]] ) - ROW( co_defaultScenario[[#Headers],[row_id]] ) -> 11 | C14: 2060 | D14: 4.5654537e+13 | E14: 71141395 | F14: 77560889 | G14: 6782559.3 | H14: 14408702 | I14: 97500055 | J14: 48594359 | K14: 84809714
B15: =ROW( co_defaultScenario[[#This Row],[row_id]] ) - ROW( co_defaultScenario[[#Headers],[row_id]] ) -> 12 | C15: 2065 | D15: 4.9547387e+13 | E15: 71800214 | F15: 78677245 | G15: 6922707 | H15: 14564856 | I15: 99183481 | J15: 49871975 | K15: 87118968
... B20: =ROW( co_defaultScenario[[#This Row],[row_id]] ) - ROW( co_defaultScenario[[#Headers],[row_id]] ) -> 17 | C20: 2090 | D20: 7.1877254e+13 | E20: 74601088 | F20: 83501161 | G20: 7482239.2 | H20: 15210659 | I20: 1.0628984e+08 | J20: 54868179 | K20: 96242314
B22: row_id | C22: year | D22: temp_C_global
B23: =ROW( co_defaultTemps[[#This Row],[row_id]] ) - ROW( co_defaultTemps[[#Headers],[row_id]] ) -> 1 | C23: 2000 | D23: 0.12696486
B24: =ROW( co_defaultTemps[[#This Row],[row_id]] ) - ROW( co_defaultTemps[[#Headers],[row_id]] ) -> 2 | C24: 2001 | D24: 0.15755131
B25: =ROW( co_defaultTemps[[#This Row],[row_id]] ) - ROW( co_defaultTemps[[#Headers],[row_id]] ) -> 3 | C25: 2002 | D25: 0.18583101
B26: =ROW( co_defaultTemps[[#This Row],[row_id]] ) - ROW( co_defaultTemps[[#Headers],[row_id]] ) -> 4 | C26: 2003 | D26: 0.21016112
B27: =ROW( co_defaultTemps[[#This Row],[row_id]] ) - ROW( co_defaultTemps[[#Headers],[row_id]] ) -> 5 | C27: 2004 | D27: 0.23065512
B28: =ROW( co_defaultTemps[[#This Row],[row_id]] ) - ROW( co_defaultTemps[[#Headers],[row_id]] ) -> 6 | C28: 2005 | D28: 0.24442523
B29: =ROW( co_defaultTemps[[#This Row],[row_id]] ) - ROW( co_defaultTemps[[#Headers],[row_id]] ) -> 7 | C29: 2006 | D29: 0.24741047
B30: =ROW( co_defaultTemps[[#This Row],[row_id]] ) - ROW( co_defaultTemps[[#Headers],[row_id]] ) -> 8 | C30: 2007 | D30: 0.24616652
B31: =ROW( co_defaultTemps[[#This Row],[row_id]] ) - ROW( co_defaultTemps[[#Headers],[row_id]] ) -> 9 | C31: 2008 | D31: 0.2482241
B32: =ROW( co_defaultTemps[[#This Row],[row_id]] ) - ROW( co_defaultTemps[[#Headers],[row_id]] ) -> 10 | C32: 2009 | D32: 0.26162653
B33: =ROW( co_defaultTemps[[#This Row],[row_id]] ) - ROW( co_defaultTemps[[#Headers],[row_id]] ) -> 11 | C33: 2010 | D33: 0.26559363
B34: =ROW( co_defaultTemps[[#This Row],[row_id]] ) - ROW( co_defaultTemps[[#Headers],[row_id]] ) -> 12 | C34: 2011 | D34: 0.27091856
... B113: =ROW( co_defaultTemps[[#This Row],[row_id]] ) - ROW( co_defaultTemps[[#Headers],[row_id]] ) -> 91 | C113: 2090 | D113: 2.3901693

Sheet slrReadMe
B2: Sectors Info
B3: row_id | C3: sector_id | D3: adapt_id | E3: adapt_label | F3: Description
B4: =ROW( Readme_sectors[[#This Row],[row_id]] ) - ROW( Readme_sectors[[#Headers],[row_id]] ) -> 1 | C4: CoastalProperties | D4: NoAdapt | E4: No Adaptation | F4: NCPM costs with GDP/capita property adjustment, dated 09 2018. 11-year moving average, with using financial smoothing technique. Costs are $2015 dollars / year. Costs include abandonment, storm surge damage, nourishment, armor, and elevate .
B5: =ROW( Readme_sectors[[#This Row],[row_id]] ) - ROW( Readme_sectors[[#Headers],[row_id]] ) -> 2 | C5: HTF | D5: NoAdapt | E5: No Adaptation | F5: High Tide Flooding and Traffic with GDP and population growth, dated 04 2020. 11-year moving average for temp binning. Costs are $2015 dollars / year.
B8: Adaptations Info
B9: row_id | C9: sector_id | D9: adapt_id | E9: adapt_label
B10: =ROW( Readme_adaptations[[#This Row],[row_id]] ) - ROW( Readme_adaptations[[#Headers],[row_id]] ) -> 1 | C10: CoastalProperties | D10: NoAdapt | E10: No Adaptation
B11: =ROW( Readme_adaptations[[#This Row],[row_id]] ) - ROW( Readme_adaptations[[#Headers],[row_id]] ) -> 2 | C11: CoastalProperties | D11: Reactive | E11: Reactive Adaptation
B12: =ROW( Readme_adaptations[[#This Row],[row_id]] ) - ROW( Readme_adaptations[[#Headers],[row_id]] ) -> 3 | C12: CoastalProperties | D12: Proactive | E12: Proactive Adaptation
B13: =ROW( Readme_adaptations[[#This Row],[row_id]] ) - ROW( Readme_adaptations[[#Headers],[row_id]] ) -> 4 | C13: HTF | D13: NoAdapt | E13: No Adaptation
B14: =ROW( Readme_adaptations[[#This Row],[row_id]] ) - ROW( Readme_adaptations[[#Headers],[row_id]] ) -> 5 | C14: HTF | D14: Reactive | E14: Reasonably Anticipated Adaptation
B15: =ROW( Readme_adaptations[[#This Row],[row_id]] ) - ROW( Readme_adaptations[[#Headers],[row_id]] ) -> 6 | C15: HTF | D15: Proactive | E15: Direct Adaptation

Sheet scalarData
A1: row_id | B1: scalarType | C1: scalarLabel | D1: scalarName | E1: region | F1: year | G1: value
A2: =ROW( scalarDataframe[[#This Row],[row_id]] ) - ROW( scalarDataframe[[#Headers],[row_id]] ) -> 1 | B2: =INDEX( co_scalarInfo[scalarType], MATCH( scalarDataframe[[#This Row],[scalarName]], co_scalarInfo[scalarName], 0 ) ) -> damageAdj | C2: =INDEX( co_scalarInfo[scalarLabel], MATCH( scalarDataframe[[#This Row],[scalarName]], co_scalarInfo[scalarName], 0 ) ) -> Population-Driven Demand Growth Factor for Grid Reliability | D2: elecTD_growthFactor | E2: Midwest | F2: 2010 | G2: 1.0999218
A3: =ROW( scalarDataframe[[#This Row],[row_id]] ) - ROW( scalarDataframe[[#Headers],[row_id]] ) -> 2 | B3: =INDEX( co_scalarInfo[scalarType], MATCH( scalarDataframe[[#This Row],[scalarName]], co_scalarInfo[scalarName], 0 ) ) -> damageAdj | C3: =INDEX( co_scalarInfo[scalarLabel], MATCH( scalarDataframe[[#This Row],[scalarName]], co_scalarInfo[scalarName], 0 ) ) -> Population-Driven Demand Growth Factor for Grid Reliability | D3: elecTD_growthFactor | E3: Midwest | F3: 2015 | G3: 1.1555698
A4: =ROW( scalarDataframe[[#This Row],[row_id]] ) - ROW( scalarDataframe[[#Headers],[row_id]] ) -> 3 | B4: =INDEX( co_scalarInfo[scalarType], MATCH( scalarDataframe[[#This Row],[scalarName]], co_scalarInfo[scalarName], 0 ) ) -> damageAdj | C4: =INDEX( co_scalarInfo[scalarLabel], MATCH( scalarDataframe[[#This Row],[scalarName]], co_scalarInfo[scalarName], 0 ) ) -> Population-Driven Demand Growth Factor for Grid Reliability | D4: elecTD_growthFactor | E4: Midwest | F4: 2020 | G4: 1.1555698
A5: =ROW( scalarDataframe[[#This Row],[row_id]] ) - ROW( scalarDataframe[[#Headers],[row_id]] ) -> 4 | B5: =INDEX( co_scalarInfo[scalarType], MATCH( scalarDataframe[[#This Row],[scalarName]], co_scalarInfo[scalarName], 0 ) ) -> damageAdj | C5: =INDEX( co_scalarInfo[scalarLabel], MATCH( scalarDataframe[[#This Row],[scalarName]], co_scalarInfo[scalarName], 0 ) ) -> Population-Driven Demand Growth Factor for Grid Reliability | D5: elecTD_growthFactor | E5: Midwest | F5: 2025 | G5: 1.1555698
A6: =ROW( scalarDataframe[[#This Row],[row_id]] ) - ROW( scalarDataframe[[#Headers],[row_id]] ) -> 5 | B6: =INDEX( co_scalarInfo[scalarType], MATCH( scalarDataframe[[#This Row],[scalarName]], co_scalarInfo[scalarName], 0 ) ) -> damageAdj | C6: =INDEX( co_scalarInfo[scalarLabel], MATCH( scalarDataframe[[#This Row],[scalarName]], co_scalarInfo[scalarName], 0 ) ) -> Population-Driven Demand Growth Factor for Grid Reliability | D6: elecTD_growthFactor | E6: Midwest | F6: 2030 | G6: 1.1555698
A7: =ROW( scalarDataframe[[#This Row],[row_id]] ) - ROW( scalarDataframe[[#Headers],[row_id]] ) -> 6 | B7: =INDEX( co_scalarInfo[scalarType], MATCH( scalarDataframe[[#This Row],[scalarName]], co_scalarInfo[scalarName], 0 ) ) -> damageAdj | C7: =INDEX( co_scalarInfo[scalarLabel], MATCH( scalarDataframe[[#This Row],[scalarName]], co_scalarInfo[scalarName], 0 ) ) -> Population-Driven Demand Growth Factor for Grid Reliability | D7: elecTD_growthFactor | E7: Midwest | F7: 2035 | G7: 1.1555698
A8: =ROW( scalarDataframe[[#This Row],[row_id]] ) - ROW( scalarDataframe[[#Headers],[row_id]] ) -> 7 | B8: =INDEX( co_scalarInfo[scalarType], MATCH( scalarDataframe[[#This Row],[scalarName]], co_scalarInfo[scalarName], 0 ) ) -> damageAdj | C8: =INDEX( co_scalarInfo[scalarLabel], MATCH( scalarDataframe[[#This Row],[scalarName]], co_scalarInfo[scalarName], 0 ) ) -> Population-Driven Demand Growth Factor for Grid Reliability | D8: elecTD_growthFactor | E8: Midwest | F8: 2040 | G8: 1.1555698
A9: =ROW( scalarDataframe[[#This Row],[row_id]] ) - ROW( scalarDataframe[[#Headers],[row_id]] ) -> 8 | B9: =INDEX( co_scalarInfo[scalarType], MATCH( scalarDataframe[[#This Row],[scalarName]], co_scalarInfo[scalarName], 0 ) ) -> damageAdj | C9: =INDEX( co_scalarInfo[scalarLabel], MATCH( scalarDataframe[[#This Row],[scalarName]], co_scalarInfo[scalarName], 0 ) ) -> Population-Driven Demand Growth Factor for Grid Reliability | D9: elecTD_growthFactor | E9: Midwest | F9: 2045 | G9: 1.1555698
A10: =ROW( scalarDataframe[[#This Row],[row_id]] ) - ROW( scalarDataframe[[#Headers],[row_id]] ) -> 9 | B10: =INDEX( co_scalarInfo[scalarType], MATCH( scalarDataframe[[#This Row],[scalarName]], co_scalarInfo[scalarName], 0 ) ) -> damageAdj | C10: =INDEX( co_scalarInfo[scalarLabel], MATCH( scalarDataframe[[#This Row],[scalarName]], co_scalarInfo[scalarName], 0 ) ) -> Population-Driven Demand Growth Factor for Grid Reliability | D10: elecTD_growthFactor | E10: Midwest | F10: 2050 | G10: 1.1555698
A11: =ROW( scalarDataframe[[#This Row],[row_id]] ) - ROW( scalarDataframe[[#Headers],[row_id]] ) -> 10 | B11: =INDEX( co_scalarInfo[scalarType], MATCH( scalarDataframe[[#This Row],[scalarName]], co_scalarInfo[scalarName], 0 ) ) -> damageAdj | C11: =INDEX( co_scalarInfo[scalarLabel], MATCH( scalarDataframe[[#This Row],[scalarName]], co_scalarInfo[scalarName], 0 ) ) -> Population-Driven Demand Growth Factor for Grid Reliability | D11: elecTD_growthFactor | E11: Midwest | F11: 2055 | G11: 1.1555698
A12: =ROW( scalarDataframe[[#This Row],[row_id]] ) - ROW( scalarDataframe[[#Headers],[row_id]] ) -> 11 | B12: =INDEX( co_scalarInfo[scalarType], MATCH( scalarDataframe[[#This Row],[scalarName]], co_scalarInfo[scalarName], 0 ) ) -> damageAdj | C12: =INDEX( co_scalarInfo[scalarLabel], MATCH( scalarDataframe[[#This Row],[scalarName]], co_scalarInfo[scalarName], 0 ) ) -> Population-Driven Demand Growth Factor for Grid Reliability | D12: elecTD_growthFactor | E12: Midwest | F12: 2060 | G12: 1.1847576
A13: =ROW( scalarDataframe[[#This Row],[row_id]] ) - ROW( scalarDataframe[[#Headers],[row_id]] ) -> 12 | B13: =INDEX( co_scalarInfo[scalarType], MATCH( scalarDataframe[[#This Row],[scalarName]], co_scalarInfo[scalarName], 0 ) ) -> damageAdj | C13: =INDEX( co_scalarInfo[scalarLabel], MATCH( scalarDataframe[[#This Row],[scalarName]], co_scalarInfo[scalarName], 0 ) ) -> Population-Driven Demand Growth Factor for Grid Reliability | D13: elecTD_growthFactor | E13: Midwest | F13: 2065 | G13: 1.2252784
... A1490: =ROW( scalarDataframe[[#This Row],[row_id]] ) - ROW( scalarDataframe[[#Headers],[row_id]] ) -> 1489 | B1490: =INDEX( co_scalarInfo[scalarType], MATCH( scalarDataframe[[#This Row],[scalarName]], co_scalarInfo[scalarName], 0 ) ) -> damageAdj | C1490: =INDEX( co_scalarInfo[scalarLabel], MATCH( scalarDataframe[[#This Row],[scalarName]], co_scalarInfo[scalarName], 0 ) ) -> Road Miles and Population Adjustment Factor (Proactive Adaptation) | D1490: road_miles_and_pop_proactive | E1490: Southwest | F1490: 2300 | G1490: 1.7326333

Sheet scaledImpacts
A1: row_id | B1: output_lookupID | C1: sector | D1: model | E1: modelUnitValue | F1: impactYear | G1: variant | H1: impactType | I1: outputRowID | J1: Midwest | K1: Northeast | L1: Northern Plains | M1: Northwest | N1: Southeast | O1: Southern Plains | P1: Southwest
A2: =ROW( data_scaledImpacts[[#This Row],[row_id]] ) - ROW( data_scaledImpacts[[#Headers],[row_id]] ) -> 1 | B2: =_xlfn.TEXTJOIN( "", , data_scaledImpacts[[#This Row],[sector]:[impactType]] ) -> ExtremeTempCanESM212010No Adaptationhot | C2: ExtremeTemp | D2: CanESM2 | E2: 1 | F2: 2010 | G2: No Adaptation | H2: hot | I2: CanESM2 2010 adj | J2: 6.6863862e-06 | K2: 4.5337311e-06 | N2: 4.4187355e-06 | O2: 5.9738952e-06 | P2: 6.6240061e-06
A3: =ROW( data_scaledImpacts[[#This Row],[row_id]] ) - ROW( data_scaledImpacts[[#Headers],[row_id]] ) -> 2 | B3: =_xlfn.TEXTJOIN( "", , data_scaledImpacts[[#This Row],[sector]:[impactType]] ) -> ExtremeTempCCSM412010No Adaptationhot | C3: ExtremeTemp | D3: CCSM4 | E3: 1 | F3: 2010 | G3: No Adaptation | H3: hot | I3: CCSM4 2010 adj | J3: 4.4811932e-06 | K3: 2.5564427e-06 | N3: 2.6400996e-06 | O3: 2.1802674e-06 | P3: 3.6478823e-06
A4: =ROW( data_scaledImpacts[[#This Row],[row_id]] ) - ROW( data_scaledImpacts[[#Headers],[row_id]] ) -> 3 | B4: =_xlfn.TEXTJOIN( "", , data_scaledImpacts[[#This Row],[sector]:[impactType]] ) -> ExtremeTempGISS-E2-R12010No Adaptationhot | C4: ExtremeTemp | D4: GISS-E2-R | E4: 1 | F4: 2010 | G4: No Adaptation | H4: hot | I4: GISS_E2_R 2010 adj | J4: 1.1240075e-05 | K4: 8.0194224e-06 | N4: 5.7131385e-06 | O4: 3.4074498e-06 | P4: 3.1291716e-06
A5: =ROW( data_scaledImpacts[[#This Row],[row_id]] ) - ROW( data_scaledImpacts[[#Headers],[row_id]] ) -> 4 | B5: =_xlfn.TEXTJOIN( "", , data_scaledImpacts[[#This Row],[sector]:[impactType]] ) -> ExtremeTempHadGEM2-ES12010No Adaptationhot | C5: ExtremeTemp | D5: HadGEM2-ES | E5: 1 | F5: 2010 | G5: No Adaptation | H5: hot | I5: HadGEM2_ES 2010 adj | J5: 6.7275342e-06 | K5: 5.3203714e-06 | N5: 1.0840419e-05 | O5: 7.1329502e-06 | P5: 2.9643399e-06
A6: =ROW( data_scaledImpacts[[#This Row],[row_id]] ) - ROW( data_scaledImpacts[[#Headers],[row_id]] ) -> 5 | B6: =_xlfn.TEXTJOIN( "", , data_scaledImpacts[[#This Row],[sector]:[impactType]] ) -> ExtremeTempMIROC512010No Adaptationhot | C6: ExtremeTemp | D6: MIROC5 | E6: 1 | F6: 2010 | G6: No Adaptation | H6: hot | I6: MIROC5 2010 adj | J6: 6.3343431e-06 | K6: 1.6425537e-06 | N6: 4.4454858e-06 | O6: 7.7733144e-06 | P6: 3.0991484e-07
A7: =ROW( data_scaledImpacts[[#This Row],[row_id]] ) - ROW( data_scaledImpacts[[#Headers],[row_id]] ) -> 6 | B7: =_xlfn.TEXTJOIN( "", , data_scaledImpacts[[#This Row],[sector]:[impactType]] ) -> ExtremeTempGFDL-CM312010No Adaptationhot | C7: ExtremeTemp | D7: GFDL-CM3 | E7: 1 | F7: 2010 | G7: No Adaptation | H7: hot | I7: GFDL_CM3 2010 adj | J7: 8.7943474e-06 | K7: 7.4745256e-06 | N7: 5.3323782e-06 | O7: 6.9639203e-06 | P7: 3.8899221e-06
A8: =ROW( data_scaledImpacts[[#This Row],[row_id]] ) - ROW( data_scaledImpacts[[#Headers],[row_id]] ) -> 7 | B8: =_xlfn.TEXTJOIN( "", , data_scaledImpacts[[#This Row],[sector]:[impactType]] ) -> ExtremeTempGCM Average12010No Adaptationhot | C8: ExtremeTemp | D8: GCM Average | E8: 1 | F8: 2010 | G8: No Adaptation | H8: hot | I8: 2010 adj | J8: 7.3773131e-06 | K8: 4.9245078e-06 | N8: 5.5650428e-06 | O8: 5.5719662e-06 | P8: 3.4275395e-06
A9: =ROW( data_scaledImpacts[[#This Row],[row_id]] ) - ROW( data_scaledImpacts[[#Headers],[row_id]] ) -> 8 | B9: =_xlfn.TEXTJOIN( "", , data_scaledImpacts[[#This Row],[sector]:[impactType]] ) -> ExtremeTempCanESM222010No Adaptationhot | C9: ExtremeTemp | D9: CanESM2 | E9: 2 | F9: 2010 | G9: No Adaptation | H9: hot | I9: CanESM2 2010 adj | J9: 1.6864246e-05 | K9: 1.5211248e-05 | N9: 2.0144767e-05 | O9: 2.0681969e-05 | P9: 1.154479e-05
A10: =ROW( data_scaledImpacts[[#This Row],[row_id]] ) - ROW( data_scaledImpacts[[#Headers],[row_id]] ) -> 9 | B10: =_xlfn.TEXTJOIN( "", , data_scaledImpacts[[#This Row],[sector]:[impactType]] ) -> ExtremeTempCCSM422010No Adaptationhot | C10: ExtremeTemp | D10: CCSM4 | E10: 2 | F10: 2010 | G10: No Adaptation | H10: hot | I10: CCSM4 2010 adj | J10: 1.4879969e-05 | K10: 1.13411e-05 | N10: 1.0928816e-05 | O10: 1.1130886e-05 | P10: 5.7085645e-06
A11: =ROW( data_scaledImpacts[[#This Row],[row_id]] ) - ROW( data_scaledImpacts[[#Headers],[row_id]] ) -> 10 | B11: =_xlfn.TEXTJOIN( "", , data_scaledImpacts[[#This Row],[sector]:[impactType]] ) -> ExtremeTempGISS-E2-R22010No Adaptationhot | C11: ExtremeTemp | D11: GISS-E2-R | E11: 2 | F11: 2010 | G11: No Adaptation | H11: hot | I11: GISS_E2_R 2010 adj | J11: 2.0181285e-05 | K11: 1.5942113e-05 | N11: 2.1455318e-05 | O11: 1.3408475e-05 | P11: 7.7724442e-06
A12: =ROW( data_scaledImpacts[[#This Row],[row_id]] ) - ROW( data_scaledImpacts[[#Headers],[row_id]] ) -> 11 | B12: =_xlfn.TEXTJOIN( "", , data_scaledImpacts[[#This Row],[sector]:[impactType]] ) -> ExtremeTempHadGEM2-ES22010No Adaptationhot | C12: ExtremeTemp | D12: HadGEM2-ES | E12: 2 | F12: 2010 | G12: No Adaptation | H12: hot | I12: HadGEM2_ES 2010 adj | J12: 2.378447e-05 | K12: 1.8730311e-05 | N12: 2.3028736e-05 | O12: 1.3893139e-05 | P12: 5.4306394e-06
A13: =ROW( data_scaledImpacts[[#This Row],[row_id]] ) - ROW( data_scaledImpacts[[#Headers],[row_id]] ) -> 12 | B13: =_xlfn.TEXTJOIN( "", , data_scaledImpacts[[#This Row],[sector]:[impactType]] ) -> ExtremeTempMIROC522010No Adaptationhot | C13: ExtremeTemp | D13: MIROC5 | E13: 2 | F13: 2010 | G13: No Adaptation | H13: hot | I13: MIROC5 2010 adj | J13: 1.1154454e-05 | K13: 5.2777716e-06 | N13: 1.0164522e-05 | O13: 1.5652837e-05 | P13: 2.3031555e-06
... A24: =ROW( data_scaledImpacts[[#This Row],[row_id]] ) - ROW( data_scaledImpacts[[#Headers],[row_id]] ) -> 23 | B24: =_xlfn.TEXTJOIN( "", , data_scaledImpacts[[#This Row],[sector]:[impactType]] ) -> ExtremeTempCCSM442010No Adaptationhot | C24: ExtremeTemp | D24: CCSM4 | E24: 4 | F24: 2010 | G24: No Adaptation | H24: hot | I24: CCSM4 2010 adj | J24: 3.5853505e-05 | K24: 4.5020958e-05 | N24: 4.4437884e-05 | O24: 3.9889218e-05 | P24: 1.7350302e-05
A25: =ROW( data_scaledImpacts[[#This Row],[row_id]] ) - ROW( data_scaledImpacts[[#Headers],[row_id]] ) -> 24 | B25: =_xlfn.TEXTJOIN( "", , data_scaledImpacts[[#This Row],[sector]:[impactType]] ) -> ExtremeTempGISS-E2-R42010No Adaptationhot | C25: ExtremeTemp | D25: GISS-E2-R | E25: 4 | F25: 2010 | G25: No Adaptation | H25: hot | I25: GISS_E2_R 2010 adj
A26: =ROW( data_scaledImpacts[[#This Row],[row_id]] ) - ROW( data_scaledImpacts[[#Headers],[row_id]] ) -> 25 | B26: =_xlfn.TEXTJOIN( "", , data_scaledImpacts[[#This Row],[sector]:[impactType]] ) -> ExtremeTempHadGEM2-ES42010No Adaptationhot | C26: ExtremeTemp | D26: HadGEM2-ES | E26: 4 | F26: 2010 | G26: No Adaptation | H26: hot | I26: HadGEM2_ES 2010 adj | J26: 4.9746232e-05 | K26: 5.0055408e-05 | N26: 6.3306652e-05 | O26: 4.6616453e-05 | P26: 1.933804e-05
A27: =ROW( data_scaledImpacts[[#This Row],[row_id]] ) - ROW( data_scaledImpacts[[#Headers],[row_id]] ) -> 26 | B27: =_xlfn.TEXTJOIN( "", , data_scaledImpacts[[#This Row],[sector]:[impactType]] ) -> ExtremeTempMIROC542010No Adaptationhot | C27: ExtremeTemp | D27: MIROC5 | E27: 4 | F27: 2010 | G27: No Adaptation | H27: hot | I27: MIROC5 2010 adj | J27: 3.5612087e-05 | K27: 3.6364875e-05 | N27: 3.8812732e-05 | O27: 4.7648283e-05 | P27: 1.102826e-05
A28: =ROW( data_scaledImpacts[[#This Row],[row_id]] ) - ROW( data_scaledImpacts[[#Headers],[row_id]] ) -> 27 | B28: =_xlfn.TEXTJOIN( "", , data_scaledImpacts[[#This Row],[sector]:[impactType]] ) -> ExtremeTempGFDL-CM342010No Adaptationhot | C28: ExtremeTemp | D28: GFDL-CM3 | E28: 4 | F28: 2010 | G28: No Adaptation | H28: hot | I28: GFDL_CM3 2010 adj | J28: 5.2258612e-05 | K28: 7.4290465e-05 | N28: 6.0390981e-05 | O28: 6.2731432e-05 | P28: 3.2954712e-05
A29: =ROW( data_scaledImpacts[[#This Row],[row_id]] ) - ROW( data_scaledImpacts[[#Headers],[row_id]] ) -> 28 | B29: =_xlfn.TEXTJOIN( "", , data_scaledImpacts[[#This Row],[sector]:[impactType]] ) -> ExtremeTempGCM Average42010No Adaptationhot | C29: ExtremeTemp | D29: GCM Average | E29: 4 | F29: 2010 | G29: No Adaptation | H29: hot | I29: 2010 adj | J29: 4.2612172e-05 | K29: 5.2473608e-05 | N29: 5.2236992e-05 | O29: 5.0236057e-05 | P29: 2.3248505e-05
A30: =ROW( data_scaledImpacts[[#This Row],[row_id]] ) - ROW( data_scaledImpacts[[#Headers],[row_id]] ) -> 29 | B30: =_xlfn.TEXTJOIN( "", , data_scaledImpacts[[#This Row],[sector]:[impactType]] ) -> ExtremeTempCanESM252010No Adaptationhot | C30: ExtremeTemp | D30: CanESM2 | E30: 5 | F30: 2010 | G30: No Adaptation | H30: hot | I30: CanESM2 2010 adj | J30: 5.9726447e-05 | K30: 8.1855878e-05 | N30: 7.916318e-05 | O30: 6.1223225e-05 | P30: 5.181572e-05
A31: =ROW( data_scaledImpacts[[#This Row],[row_id]] ) - ROW( data_scaledImpacts[[#Headers],[row_id]] ) -> 30 | B31: =_xlfn.TEXTJOIN( "", , data_scaledImpacts[[#This Row],[sector]:[impactType]] ) -> ExtremeTempCCSM452010No Adaptationhot | C31: ExtremeTemp | D31: CCSM4 | E31: 5 | F31: 2010 | G31: No Adaptation | H31: hot | I31: CCSM4 2010 adj | J31: 4.8050187e-05 | K31: 5.9354726e-05 | N31: 6.5698939e-05 | O31: 5.6010571e-05 | P31: 2.3048769e-05
A32: =ROW( data_scaledImpacts[[#This Row],[row_id]] ) - ROW( data_scaledImpacts[[#Headers],[row_id]] ) -> 31 | B32: =_xlfn.TEXTJOIN( "", , data_scaledImpacts[[#This Row],[sector]:[impactType]] ) -> ExtremeTempGISS-E2-R52010No Adaptationhot | C32: ExtremeTemp | D32: GISS-E2-R | E32: 5 | F32: 2010 | G32: No Adaptation | H32: hot | I32: GISS_E2_R 2010 adj
A33: =ROW( data_scaledImpacts[[#This Row],[row_id]] ) - ROW( data_scaledImpacts[[#Headers],[row_id]] ) -> 32 | B33: =_xlfn.TEXTJOIN( "", , data_scaledImpacts[[#This Row],[sector]:[impactType]] ) -> ExtremeTempHadGEM2-ES52010No Adaptationhot | C33: ExtremeTemp | D33: HadGEM2-ES | E33: 5 | F33: 2010 | G33: No Adaptation | H33: hot | I33: HadGEM2_ES 2010 adj | J33: 7.3210447e-05 | K33: 7.2348563e-05 | N33: 7.9503666e-05 | O33: 5.857073e-05 | P33: 2.6591512e-05
A34: =ROW( data_scaledImpacts[[#This Row],[row_id]] ) - ROW( data_scaledImpacts[[#Headers],[row_id]] ) -> 33 | B34: =_xlfn.TEXTJOIN( "", , data_scaledImpacts[[#This Row],[sector]:[impactType]] ) -> ExtremeTempMIROC552010No Adaptationhot | C34: ExtremeTemp | D34: MIROC5 | E34: 5 | F34: 2010 | G34: No Adaptation | H34: hot | I34: MIROC5 2010 adj | J34: 5.0823224e-05 | K34: 4.9554905e-05 | N34: 5.8887827e-05 | O34: 6.9860312e-05 | P34: 1.8703378e-05
A35: =ROW( data_scaledImpacts[[#This Row],[row_id]] ) - ROW( data_scaledImpacts[[#Headers],[row_id]] ) -> 34 | B35: =_xlfn.TEXTJOIN( "", , data_scaledImpacts[[#This Row],[sector]:[impactType]] ) -> ExtremeTempGFDL-CM352010No Adaptationhot | C35: ExtremeTemp | D35: GFDL-CM3 | E35: 5 | F35: 2010 | G35: No Adaptation | H35: hot | I35: GFDL_CM3 2010 adj | J35: 7.7859094e-05 | K35: 9.0931368e-05 | N35: 7.652873e-05 | O35: 7.4104223e-05 | P35: 4.1287833e-05
A36: =ROW( data_scaledImpacts[[#This Row],[row_id]] ) - ROW( data_scaledImpacts[[#Headers],[row_id]] ) -> 35 | B36: =_xlfn.TEXTJOIN( "", , data_scaledImpacts[[#This Row],[sector]:[impactType]] ) -> ExtremeTempGCM Average52010No Adaptationhot | C36: ExtremeTemp | D36: GCM Average | E36: 5 | F36: 2010 | G36: No Adaptation | H36: hot | I36: 2010 adj | J36: 6.193388e-05 | K36: 7.0809088e-05 | N36: 7.1956468e-05 | O36: 6.3953812e-05 | P36: 3.2289442e-05
A37: =ROW( data_scaledImpacts[[#This Row],[row_id]] ) - ROW( data_scaledImpacts[[#Headers],[row_id]] ) -> 36 | B37: =_xlfn.TEXTJOIN( "", , data_scaledImpacts[[#This Row],[sector]:[impactType]] ) -> ExtremeTempCanESM262010No Adaptationhot | C37: ExtremeTemp | D37: CanESM2 | E37: 6 | F37: 2010 | G37: No Adaptation | H37: hot | I37: CanESM2 2010 adj | J37: 8.6971305e-05 | K37: 0.00011107136 | N37: 9.8117941e-05 | O37: 7.5461046e-05 | P37: 6.5898642e-05
A38: =ROW( data_scaledImpacts[[#This Row],[row_id]] ) - ROW( data_scaledImpacts[[#Headers],[row_id]] ) -> 37 | B38: =_xlfn.TEXTJOIN( "", , data_scaledImpacts[[#This Row],[sector]:[impactType]] ) -> ExtremeTempCCSM462010No Adaptationhot | C38: ExtremeTemp | D38: CCSM4 | E38: 6 | F38: 2010 | G38: No Adaptation | H38: hot | I38: CCSM4 2010 adj
A39: =ROW( data_scaledImpacts[[#This Row],[row_id]] ) - ROW( data_scaledImpacts[[#Headers],[row_id]] ) -> 38 | B39: =_xlfn.TEXTJOIN( "", , data_scaledImpacts[[#This Row],[sector]:[impactType]] ) -> ExtremeTempGISS-E2-R62010No Adaptationhot | C39: ExtremeTemp | D39: GISS-E2-R | E39: 6 | F39: 2010 | G39: No Adaptation | H39: hot | I39: GISS_E2_R 2010 adj
A40: =ROW( data_scaledImpacts[[#This Row],[row_id]] ) - ROW( data_scaledImpacts[[#Headers],[row_id]] ) -> 39 | B40: =_xlfn.TEXTJOIN( "", , data_scaledImpacts[[#This Row],[sector]:[impactType]] ) -> ExtremeTempHadGEM2-ES62010No Adaptationhot | C40: ExtremeTemp | D40: HadGEM2-ES | E40: 6 | F40: 2010 | G40: No Adaptation | H40: hot | I40: HadGEM2_ES 2010 adj | J40: 9.7671819e-05 | K40: 9.7158053e-05 | N40: 9.6826837e-05 | O40: 7.0945795e-05 | P40: 3.8365308e-05
A41: =ROW( data_scaledImpacts[[#This Row],[row_id]] ) - ROW( data_scaledImpacts[[#Headers],[row_id]] ) -> 40 | B41: =_xlfn.TEXTJOIN( "", , data_scaledImpacts[[#This Row],[sector]:[impactType]] ) -> ExtremeTempMIROC562010No Adaptationhot | C41: ExtremeTemp | D41: MIROC5 | E41: 6 | F41: 2010 | G41: No Adaptation | H41: hot | I41: MIROC5 2010 adj
A42: =ROW( data_scaledImpacts[[#This Row],[row_id]] ) - ROW( data_scaledImpacts[[#Headers],[row_id]] ) -> 41 | B42: =_xlfn.TEXTJOIN( "", , data_scaledImpacts[[#This Row],[sector]:[impactType]] ) -> ExtremeTempGFDL-CM362010No Adaptationhot | C42: ExtremeTemp | D42: GFDL-CM3 | E42: 6 | F42: 2010 | G42: No Adaptation | H42: hot | I42: GFDL_CM3 2010 adj | J42: 0.00010198006 | K42: 0.00011024698 | N42: 9.7391258e-05 | O42: 8.1767597e-05 | P42: 5.93328e-05
A43: =ROW( data_scaledImpacts[[#This Row],[row_id]] ) - ROW( data_scaledImpacts[[#Headers],[row_id]] ) -> 42 | B43: =_xlfn.TEXTJOIN( "", , data_scaledImpacts[[#This Row],[sector]:[impactType]] ) -> ExtremeTempGCM Average62010No Adaptationhot | C43: ExtremeTemp | D43: GCM Average | E43: 6 | F43: 2010 | G43: No Adaptation | H43: hot | I43: 2010 adj | J43: 9.5541061e-05 | K43: 0.0001061588 | N43: 9.7445345e-05 | O43: 7.6058146e-05 | P43: 5.453225e-05
A44: =ROW( data_scaledImpacts[[#This Row],[row_id]] ) - ROW( data_scaledImpacts[[#Headers],[row_id]] ) -> 43 | B44: =_xlfn.TEXTJOIN( "", , data_scaledImpacts[[#This Row],[sector]:[impactType]] ) -> ExtremeTempCanESM272010No Adaptationhot | C44: ExtremeTemp | D44: CanESM2 | E44: 7 | F44: 2010 | G44: No Adaptation | H44: hot | I44: CanESM2 2010 adj
A45: =ROW( data_scaledImpacts[[#This Row],[row_id]] ) - ROW( data_scaledImpacts[[#Headers],[row_id]] ) -> 44 | B45: =_xlfn.TEXTJOIN( "", , data_scaledImpacts[[#This Row],[sector]:[impactType]] ) -> ExtremeTempCCSM472010No Adaptationhot | C45: ExtremeTemp | D45: CCSM4 | E45: 7 | F45: 2010 | G45: No Adaptation | H45: hot | I45: CCSM4 2010 adj
A46: =ROW( data_scaledImpacts[[#This Row],[row_id]] ) - ROW( data_scaledImpacts[[#Headers],[row_id]] ) -> 45 | B46: =_xlfn.TEXTJOIN( "", , data_scaledImpacts[[#This Row],[sector]:[impactType]] ) -> ExtremeTempGISS-E2-R72010No Adaptationhot | C46: ExtremeTemp | D46: GISS-E2-R | E46: 7 | F46: 2010 | G46: No Adaptation | H46: hot | I46: GISS_E2_R 2010 adj
A47: =ROW( data_scaledImpacts[[#This Row],[row_id]] ) - ROW( data_scaledImpacts[[#Headers],[row_id]] ) -> 46 | B47: =_xlfn.TEXTJOIN( "", , data_scaledImpacts[[#This Row],[sector]:[impactType]] ) -> ExtremeTempHadGEM2-ES72010No Adaptationhot | C47: ExtremeTemp | D47: HadGEM2-ES | E47: 7 | F47: 2010 | G47: No Adaptation | H47: hot | I47: HadGEM2_ES 2010 adj
A48: =ROW( data_scaledImpacts[[#This Row],[row_id]] ) - ROW( data_scaledImpacts[[#Headers],[row_id]] ) -> 47 | B48: =_xlfn.TEXTJOIN( "", , data_scaledImpacts[[#This Row],[sector]:[impactType]] ) -> ExtremeTempMIROC572010No Adaptationhot | C48: ExtremeTemp | D48: MIROC5 | E48: 7 | F48: 2010 | G48: No Adaptation | H48: hot | I48: MIROC5 2010 adj
A49: =ROW( data_scaledImpacts[[#This Row],[row_id]] ) - ROW( data_scaledImpacts[[#Headers],[row_id]] ) -> 48 | B49: =_xlfn.TEXTJOIN( "", , data_scaledImpacts[[#This Row],[sector]:[impactType]] ) -> ExtremeTempGFDL-CM372010No Adaptationhot | C49: ExtremeTemp | D49: GFDL-CM3 | E49: 7 | F49: 2010 | G49: No Adaptation | H49: hot | I49: GFDL_CM3 2010 adj
A50: =ROW( data_scaledImpacts[[#This Row],[row_id]] ) - ROW( data_scaledImpacts[[#Headers],[row_id]] ) -> 49 | B50: =_xlfn.TEXTJOIN( "", , data_scaledImpacts[[#This Row],[sector]:[impactType]] ) -> ExtremeTempGCM Average72010No Adaptationhot | C50: ExtremeTemp | D50: GCM Average | E50: 7 | F50: 2010 | G50: No Adaptation | H50: hot | I50: 2010 adj
A51: =ROW( data_scaledImpacts[[#This Row],[row_id]] ) - ROW( data_scaledImpacts[[#Headers],[row_id]] ) -> 50 | B51: =_xlfn.TEXTJOIN( "", , data_scaledImpacts[[#This Row],[sector]:[impactType]] ) -> ExtremeTempCanESM212010No Adaptationcold | C51: ExtremeTemp | D51: CanESM2 | E51: 1 | F51: 2010 | G51: No Adaptation | H51: cold | I51: CanESM2 2010 adj | J51: -1.7756247e-07 | K51: -6.2103685e-07 | M51: -4.8583046e-07 | N51: -9.4368123e-08 | O51: -1.3201786e-07 | P51: -4.09459e-08
A52: =ROW( data_scaledImpacts[[#This Row],[row_id]] ) - ROW( data_scaledImpacts[[#Headers],[row_id]] ) -> 51 | B52: =_xlfn.TEXTJOIN( "", , data_scaledImpacts[[#This Row],[sector]:[impactType]] ) -> ExtremeTempCCSM412010No Adaptationcold | C52: ExtremeTemp | D52: CCSM4 | E52: 1 | F52: 2010 | G52: No Adaptation | H52: cold | I52: CCSM4 2010 adj | J52: -4.4545629e-07 | K52: -2.9648174e-07 | M52: 2.681281e-07 | N52: -1.5448953e-07 | O52: -2.4046735e-07 | P52: -3.2344903e-08
A53: =ROW( data_scaledImpacts[[#This Row],[row_id]] ) - ROW( data_scaledImpacts[[#Headers],[row_id]] ) -> 52 | B53: =_xlfn.TEXTJOIN( "", , data_scaledImpacts[[#This Row],[sector]:[impactType]] ) -> ExtremeTempGISS-E2-R12010No Adaptationcold | C53: ExtremeTemp | D53: GISS-E2-R | E53: 1 | F53: 2010 | G53: No Adaptation | H53: cold | I53: GISS_E2_R 2010 adj | J53: -7.9778894e-07 | K53: -8.9487901e-07 | M53: -5.0961764e-07 | N53: -2.5495212e-07 | O53: -3.129059e-07 | P53: -7.8885109e-08
A54: =ROW( data_scaledImpacts[[#This Row],[row_id]] ) - ROW( data_scaledImpacts[[#Headers],[row_id]] ) -> 53 | B54: =_xlfn.TEXTJOIN( "", , data_scaledImpacts[[#This Row],[sector]:[impactType]] ) -> ExtremeTempHadGEM2-ES12010No Adaptationcold | C54: ExtremeTemp | D54: HadGEM2-ES | E54: 1 | F54: 2010 | G54: No Adaptation | H54: cold | I54: HadGEM2_ES 2010 adj | J54: -4.3902085e-07 | K54: -8.2995294e-07 | M54: 1.6092092e-07 | N54: -1.1909652e-07 | O54: 1.3177784e-07 | P54: 3.6465768e-08
A55: =ROW( data_scaledImpacts[[#This Row],[row_id]] ) - ROW( data_scaledImpacts[[#Headers],[row_id]] ) -> 54 | B55: =_xlfn.TEXTJOIN( "", , data_scaledImpacts[[#This Row],[sector]:[impactType]] ) -> ExtremeTempMIROC512010No Adaptationcold | C55: ExtremeTemp | D55: MIROC5 | E55: 1 | F55: 2010 | G55: No Adaptation | H55: cold | I55: MIROC5 2010 adj | J55: -9.9999276e-08 | K55: -3.3969645e-07 | M55: 4.0894793e-08 | N55: -1.1125935e-07 | O55: -2.2539718e-07 | P55: -5.4030385e-08
A56: =ROW( data_scaledImpacts[[#This Row],[row_id]] ) - ROW( data_scaledImpacts[[#Headers],[row_id]] ) -> 55 | B56: =_xlfn.TEXTJOIN( "", , data_scaledImpacts[[#This Row],[sector]:[impactType]] ) -> ExtremeTempGFDL-CM312010No Adaptationcold | C56: ExtremeTemp | D56: GFDL-CM3 | E56: 1 | F56: 2010 | G56: No Adaptation | H56: cold | I56: GFDL_CM3 2010 adj | J56: -5.060083e-07 | K56: -7.4228627e-07 | M56: 4.9021448e-08 | N56: -1.6577213e-07 | O56: -4.5070181e-08 | P56: -1.3762165e-08
A57: =ROW( data_scaledImpacts[[#This Row],[row_id]] ) - ROW( data_scaledImpacts[[#Headers],[row_id]] ) -> 56 | B57: =_xlfn.TEXTJOIN( "", , data_scaledImpacts[[#This Row],[sector]:[impactType]] ) -> ExtremeTempGCM Average12010No Adaptationcold | C57: ExtremeTemp | D57: GCM Average | E57: 1 | F57: 2010 | G57: No Adaptation | H57: cold | I57: 2010 adj | J57: -4.1097269e-07 | K57: -6.2072221e-07 | M57: -7.9413806e-08 | N57: -1.4998963e-07 | O57: -1.3734677e-07 | P57: -3.0583782e-08
A58: =ROW( data_scaledImpacts[[#This Row],[row_id]] ) - ROW( data_scaledImpacts[[#Headers],[row_id]] ) -> 57 | B58: =_xlfn.TEXTJOIN( "", , data_scaledImpacts[[#This Row],[sector]:[impactType]] ) -> ExtremeTempCanESM222010No Adaptationcold | C58: ExtremeTemp | D58: CanESM2 | E58: 2 | F58: 2010 | G58: No Adaptation | H58: cold | I58: CanESM2 2010 adj | J58: -6.4219114e-07 | K58: -8.0461667e-07 | M58: -5.7795604e-07 | N58: -1.3871985e-07 | O58: -1.609813e-07 | P58: -1.1507875e-07
A59: =ROW( data_scaledImpacts[[#This Row],[row_id]] ) - ROW( data_scaledImpacts[[#Headers],[row_id]] ) -> 58 | B59: =_xlfn.TEXTJOIN( "", , data_scaledImpacts[[#This Row],[sector]:[impactType]] ) -> ExtremeTempCCSM422010No Adaptationcold | C59: ExtremeTemp | D59: CCSM4 | E59: 2 | F59: 2010 | G59: No Adaptation | H59: cold | I59: CCSM4 2010 adj | J59: -5.2643347e-07 | K59: -8.2431593e-07 | M59: -1.5011728e-07 | N59: -1.9982925e-07 | O59: -2.7616272e-07 | P59: -1.2009517e-07
A60: =ROW( data_scaledImpacts[[#This Row],[row_id]] ) - ROW( data_scaledImpacts[[#Headers],[row_id]] ) -> 59 | B60: =_xlfn.TEXTJOIN( "", , data_scaledImpacts[[#This Row],[sector]:[impactType]] ) -> ExtremeTempGISS-E2-R22010No Adaptationcold | C60: ExtremeTemp | D60: GISS-E2-R | E60: 2 | F60: 2010 | G60: No Adaptation | H60: cold | I60: GISS_E2_R 2010 adj | J60: -8.1487941e-07 | K60: -1.0044205e-06 | M60: 5.2395221e-07 | N60: -2.8468612e-07 | O60: -3.3347546e-07 | P60: -4.0223061e-08
A61: =ROW( data_scaledImpacts[[#This Row],[row_id]] ) - ROW( data_scaledImpacts[[#Headers],[row_id]] ) -> 60 | B61: =_xlfn.TEXTJOIN( "", , data_scaledImpacts[[#This Row],[sector]:[impactType]] ) -> ExtremeTempHadGEM2-ES22010No Adaptationcold | C61: ExtremeTemp | D61: HadGEM2-ES | E61: 2 | F61: 2010 | G61: No Adaptation | H61: cold | I61: HadGEM2_ES 2010 adj | J61: -6.2075592e-07 | K61: -8.1857204e-07 | M61: -2.9707085e-07 | N61: -1.8106741e-07 | O61: -1.7432371e-07 | P61: -9.3153583e-08
A62: =ROW( data_scaledImpacts[[#This Row],[row_id]] ) - ROW( data_scaledImpacts[[#Headers],[row_id]] ) -> 61 | B62: =_xlfn.TEXTJOIN( "", , data_scaledImpacts[[#This Row],[sector]:[impactType]] ) -> ExtremeTempMIROC522010No Adaptationcold | C62: ExtremeTemp | D62: MIROC5 | E62: 2 | F62: 2010 | G62: No Adaptation | H62: cold | I62: MIROC5 2010 adj | J62: -5.2185152e-07 | K62: -9.6145929e-07 | M62: 9.4839556e-08 | N62: -1.8727978e-07 | O62: -1.5338293e-07 | P62: -7.4843384e-08
... A73: =ROW( data_scaledImpacts[[#This Row],[row_id]] ) - ROW( data_scaledImpacts[[#Headers],[row_id]] ) -> 72 | B73: =_xlfn.TEXTJOIN( "", , data_scaledImpacts[[#This Row],[sector]:[impactType]] ) -> ExtremeTempCCSM442010No Adaptationcold | C73: ExtremeTemp | D73: CCSM4 | E73: 4 | F73: 2010 | G73: No Adaptation | H73: cold | I73: CCSM4 2010 adj | J73: -9.1988478e-07 | K73: -1.052555e-06 | M73: -6.7752365e-07 | N73: -3.1004739e-07 | O73: -4.1761312e-07 | P73: -1.6759098e-07
A74: =ROW( data_scaledImpacts[[#This Row],[row_id]] ) - ROW( data_scaledImpacts[[#Headers],[row_id]] ) -> 73 | B74: =_xlfn.TEXTJOIN( "", , data_scaledImpacts[[#This Row],[sector]:[impactType]] ) -> ExtremeTempGISS-E2-R42010No Adaptationcold | C74: ExtremeTemp | D74: GISS-E2-R | E74: 4 | F74: 2010 | G74: No Adaptation | H74: cold | I74: GISS_E2_R 2010 adj
A75: =ROW( data_scaledImpacts[[#This Row],[row_id]] ) - ROW( data_scaledImpacts[[#Headers],[row_id]] ) -> 74 | B75: =_xlfn.TEXTJOIN( "", , data_scaledImpacts[[#This Row],[sector]:[impactType]] ) -> ExtremeTempHadGEM2-ES42010No Adaptationcold | C75: ExtremeTemp | D75: HadGEM2-ES | E75: 4 | F75: 2010 | G75: No Adaptation | H75: cold | I75: HadGEM2_ES 2010 adj | J75: -7.9984182e-07 | K75: -9.4846408e-07 | M75: -6.796785e-07 | N75: -2.6041037e-07 | O75: -3.0126752e-07 | P75: -1.3545239e-07
A76: =ROW( data_scaledImpacts[[#This Row],[row_id]] ) - ROW( data_scaledImpacts[[#Headers],[row_id]] ) -> 75 | B76: =_xlfn.TEXTJOIN( "", , data_scaledImpacts[[#This Row],[sector]:[impactType]] ) -> ExtremeTempMIROC542010No Adaptationcold | C76: ExtremeTemp | D76: MIROC5 | E76: 4 | F76: 2010 | G76: No Adaptation | H76: cold | I76: MIROC5 2010 adj | J76: -8.6457697e-07 | K76: -1.0733972e-06 | M76: -5.6953422e-07 | N76: -2.9837374e-07 | O76: -3.3690471e-07 | P76: -1.5372248e-07
A77: =ROW( data_scaledImpacts[[#This Row],[row_id]] ) - ROW( data_scaledImpacts[[#Headers],[row_id]] ) -> 76 | B77: =_xlfn.TEXTJOIN( "", , data_scaledImpacts[[#This Row],[sector]:[impactType]] ) -> ExtremeTempGFDL-CM342010No Adaptationcold | C77: ExtremeTemp | D77: GFDL-CM3 | E77: 4 | F77: 2010 | G77: No Adaptation | H77: cold | I77: GFDL_CM3 2010 adj | J77: -7.9933225e-07 | K77: -1.0551245e-06 | M77: -5.3752275e-07 | N77: -2.7217988e-07 | O77: -2.3672763e-07 | P77: -1.4058905e-07
A78: =ROW( data_scaledImpacts[[#This Row],[row_id]] ) - ROW( data_scaledImpacts[[#Headers],[row_id]] ) -> 77 | B78: =_xlfn.TEXTJOIN( "", , data_scaledImpacts[[#This Row],[sector]:[impactType]] ) -> ExtremeTempGCM Average42010No Adaptationcold | C78: ExtremeTemp | D78: GCM Average | E78: 4 | F78: 2010 | G78: No Adaptation | H78: cold | I78: 2010 adj | J78: -8.0571897e-07 | K78: -9.942531e-07 | M78: -6.4372767e-07 | N78: -2.7036764e-07 | O78: -3.1726276e-07 | P78: -1.4948955e-07
A79: =ROW( data_scaledImpacts[[#This Row],[row_id]] ) - ROW( data_scaledImpacts[[#Headers],[row_id]] ) -> 78 | B79: =_xlfn.TEXTJOIN( "", , data_scaledImpacts[[#This Row],[sector]:[impactType]] ) -> ExtremeTempCanESM252010No Adaptationcold | C79: ExtremeTemp | D79: CanESM2 | E79: 5 | F79: 2010 | G79: No Adaptation | H79: cold | I79: CanESM2 2010 adj | J79: -9.4264313e-07 | K79: -1.0655388e-06 | M79: -8.7176571e-07 | N79: -3.2006912e-07 | O79: -4.2134775e-07 | P79: -1.7018472e-07
A80: =ROW( data_scaledImpacts[[#This Row],[row_id]] ) - ROW( data_scaledImpacts[[#Headers],[row_id]] ) -> 79 | B80: =_xlfn.TEXTJOIN( "", , data_scaledImpacts[[#This Row],[sector]:[impactType]] ) -> ExtremeTempCCSM452010No Adaptationcold | C80: ExtremeTemp | D80: CCSM4 | E80: 5 | F80: 2010 | G80: No Adaptation | H80: cold | I80: CCSM4 2010 adj | J80: -9.3302898e-07 | K80: -1.0670841e-06 | M80: -7.6602874e-07 | N80: -2.8886579e-07 | O80: -3.7634235e-07 | P80: -1.2937417e-07
A81: =ROW( data_scaledImpacts[[#This Row],[row_id]] ) - ROW( data_scaledImpacts[[#Headers],[row_id]] ) -> 80 | B81: =_xlfn.TEXTJOIN( "", , data_scaledImpacts[[#This Row],[sector]:[impactType]] ) -> ExtremeTempGISS-E2-R52010No Adaptationcold | C81: ExtremeTemp | D81: GISS-E2-R | E81: 5 | F81: 2010 | G81: No Adaptation | H81: cold | I81: GISS_E2_R 2010 adj
A82: =ROW( data_scaledImpacts[[#This Row],[row_id]] ) - ROW( data_scaledImpacts[[#Headers],[row_id]] ) -> 81 | B82: =_xlfn.TEXTJOIN( "", , data_scaledImpacts[[#This Row],[sector]:[impactType]] ) -> ExtremeTempHadGEM2-ES52010No Adaptationcold | C82: ExtremeTemp | D82: HadGEM2-ES | E82: 5 | F82: 2010 | G82: No Adaptation | H82: cold | I82: HadGEM2_ES 2010 adj | J82: -9.4130895e-07 | K82: -1.0655502e-06 | M82: -7.1325903e-07 | N82: -3.1870043e-07 | O82: -3.9844475e-07 | P82: -1.2178151e-07
A83: =ROW( data_scaledImpacts[[#This Row],[row_id]] ) - ROW( data_scaledImpacts[[#Headers],[row_id]] ) -> 82 | B83: =_xlfn.TEXTJOIN( "", , data_scaledImpacts[[#This Row],[sector]:[impactType]] ) -> ExtremeTempMIROC552010No Adaptationcold | C83: ExtremeTemp | D83: MIROC5 | E83: 5 | F83: 2010 | G83: No Adaptation | H83: cold | I83: MIROC5 2010 adj | J83: -9.2155628e-07 | K83: -1.070252e-06 | M83: -4.6037201e-07 | N83: -3.5096587e-07 | O83: -3.9991431e-07 | P83: -1.1890858e-07
A84: =ROW( data_scaledImpacts[[#This Row],[row_id]] ) - ROW( data_scaledImpacts[[#Headers],[row_id]] ) -> 83 | B84: =_xlfn.TEXTJOIN( "", , data_scaledImpacts[[#This Row],[sector]:[impactType]] ) -> ExtremeTempGFDL-CM352010No Adaptationcold | C84: ExtremeTemp | D84: GFDL-CM3 | E84: 5 | F84: 2010 | G84: No Adaptation | H84: cold | I84: GFDL_CM3 2010 adj | J84: -9.3924615e-07 | K84: -1.0765423e-06 | M84: -4.4157563e-07 | N84: -3.0723087e-07 | O84: -3.2827382e-07 | P84: -1.4353657e-07
A85: =ROW( data_scaledImpacts[[#This Row],[row_id]] ) - ROW( data_scaledImpacts[[#Headers],[row_id]] ) -> 84 | B85: =_xlfn.TEXTJOIN( "", , data_scaledImpacts[[#This Row],[sector]:[impactType]] ) -> ExtremeTempGCM Average52010No Adaptationcold | C85: ExtremeTemp | D85: GCM Average | E85: 5 | F85: 2010 | G85: No Adaptation | H85: cold | I85: 2010 adj | J85: -9.3555669e-07 | K85: -1.0689935e-06 | M85: -6.5060022e-07 | N85: -3.1716642e-07 | O85: -3.8486459e-07 | P85: -1.3675711e-07
A86: =ROW( data_scaledImpacts[[#This Row],[row_id]] ) - ROW( data_scaledImpacts[[#Headers],[row_id]] ) -> 85 | B86: =_xlfn.TEXTJOIN( "", , data_scaledImpacts[[#This Row],[sector]:[impactType]] ) -> ExtremeTempCanESM262010No Adaptationcold | C86: ExtremeTemp | D86: CanESM2 | E86: 6 | F86: 2010 | G86: No Adaptation | H86: cold | I86: CanESM2 2010 adj | J86: -9.1758946e-07 | K86: -1.0702406e-06 | M86: -8.6755594e-07 | N86: -2.8620399e-07 | O86: -3.5080561e-07 | P86: -1.6499724e-07
A87: =ROW( data_scaledImpacts[[#This Row],[row_id]] ) - ROW( data_scaledImpacts[[#Headers],[row_id]] ) -> 86 | B87: =_xlfn.TEXTJOIN( "", , data_scaledImpacts[[#This Row],[sector]:[impactType]] ) -> ExtremeTempCCSM462010No Adaptationcold | C87: ExtremeTemp | D87: CCSM4 | E87: 6 | F87: 2010 | G87: No Adaptation | H87: cold | I87: CCSM4 2010 adj
A88: =ROW( data_scaledImpacts[[#This Row],[row_id]] ) - ROW( data_scaledImpacts[[#Headers],[row_id]] ) -> 87 | B88: =_xlfn.TEXTJOIN( "", , data_scaledImpacts[[#This Row],[sector]:[impactType]] ) -> ExtremeTempGISS-E2-R62010No Adaptationcold | C88: ExtremeTemp | D88: GISS-E2-R | E88: 6 | F88: 2010 | G88: No Adaptation | H88: cold | I88: GISS_E2_R 2010 adj
A89: =ROW( data_scaledImpacts[[#This Row],[row_id]] ) - ROW( data_scaledImpacts[[#Headers],[row_id]] ) -> 88 | B89: =_xlfn.TEXTJOIN( "", , data_scaledImpacts[[#This Row],[sector]:[impactType]] ) -> ExtremeTempHadGEM2-ES62010No Adaptationcold | C89: ExtremeTemp | D89: HadGEM2-ES | E89: 6 | F89: 2010 | G89: No Adaptation | H89: cold | I89: HadGEM2_ES 2010 adj | J89: -9.5114854e-07 | K89: -1.0733972e-06 | M89: -6.5481161e-07 | N89: -3.2843112e-07 | O89: -4.2698134e-07 | P89: -1.6759098e-07
A90: =ROW( data_scaledImpacts[[#This Row],[row_id]] ) - ROW( data_scaledImpacts[[#Headers],[row_id]] ) -> 89 | B90: =_xlfn.TEXTJOIN( "", , data_scaledImpacts[[#This Row],[sector]:[impactType]] ) -> ExtremeTempMIROC562010No Adaptationcold | C90: ExtremeTemp | D90: MIROC5 | E90: 6 | F90: 2010 | G90: No Adaptation | H90: cold | I90: MIROC5 2010 adj
A91: =ROW( data_scaledImpacts[[#This Row],[row_id]] ) - ROW( data_scaledImpacts[[#Headers],[row_id]] ) -> 90 | B91: =_xlfn.TEXTJOIN( "", , data_scaledImpacts[[#This Row],[sector]:[impactType]] ) -> ExtremeTempGFDL-CM362010No Adaptationcold | C91: ExtremeTemp | D91: GFDL-CM3 | E91: 6 | F91: 2010 | G91: No Adaptation | H91: cold | I91: GFDL_CM3 2010 adj | J91: -9.4313535e-07 | K91: -1.0765423e-06 | M91: -5.1461195e-07 | N91: -3.4035294e-07 | O91: -3.2453918e-07 | P91: -1.3737508e-07
A92: =ROW( data_scaledImpacts[[#This Row],[row_id]] ) - ROW( data_scaledImpacts[[#Headers],[row_id]] ) -> 91 | B92: =_xlfn.TEXTJOIN( "", , data_scaledImpacts[[#This Row],[sector]:[impactType]] ) -> ExtremeTempGCM Average62010No Adaptationcold | C92: ExtremeTemp | D92: GCM Average | E92: 6 | F92: 2010 | G92: No Adaptation | H92: cold | I92: 2010 adj | J92: -9.3729112e-07 | K92: -1.0733934e-06 | M92: -6.7899317e-07 | N92: -3.1832935e-07 | O92: -3.6744204e-07 | P92: -1.5665444e-07
A93: =ROW( data_scaledImpacts[[#This Row],[row_id]] ) - ROW( data_scaledImpacts[[#Headers],[row_id]] ) -> 92 | B93: =_xlfn.TEXTJOIN( "", , data_scaledImpacts[[#This Row],[sector]:[impactType]] ) -> ExtremeTempCanESM272010No Adaptationcold | C93: ExtremeTemp | D93: CanESM2 | E93: 7 | F93: 2010 | G93: No Adaptation | H93: cold | I93: CanESM2 2010 adj
A94: =ROW( data_scaledImpacts[[#This Row],[row_id]] ) - ROW( data_scaledImpacts[[#Headers],[row_id]] ) -> 93 | B94: =_xlfn.TEXTJOIN( "", , data_scaledImpacts[[#This Row],[sector]:[impactType]] ) -> ExtremeTempCCSM472010No Adaptationcold | C94: ExtremeTemp | D94: CCSM4 | E94: 7 | F94: 2010 | G94: No Adaptation | H94: cold | I94: CCSM4 2010 adj
A95: =ROW( data_scaledImpacts[[#This Row],[row_id]] ) - ROW( data_scaledImpacts[[#Headers],[row_id]] ) -> 94 | B95: =_xlfn.TEXTJOIN( "", , data_scaledImpacts[[#This Row],[sector]:[impactType]] ) -> ExtremeTempGISS-E2-R72010No Adaptationcold | C95: ExtremeTemp | D95: GISS-E2-R | E95: 7 | F95: 2010 | G95: No Adaptation | H95: cold | I95: GISS_E2_R 2010 adj
A96: =ROW( data_scaledImpacts[[#This Row],[row_id]] ) - ROW( data_scaledImpacts[[#Headers],[row_id]] ) -> 95 | B96: =_xlfn.TEXTJOIN( "", , data_scaledImpacts[[#This Row],[sector]:[impactType]] ) -> ExtremeTempHadGEM2-ES72010No Adaptationcold | C96: ExtremeTemp | D96: HadGEM2-ES | E96: 7 | F96: 2010 | G96: No Adaptation | H96: cold | I96: HadGEM2_ES 2010 adj
A97: =ROW( data_scaledImpacts[[#This Row],[row_id]] ) - ROW( data_scaledImpacts[[#Headers],[row_id]] ) -> 96 | B97: =_xlfn.TEXTJOIN( "", , data_scaledImpacts[[#This Row],[sector]:[impactType]] ) -> ExtremeTempMIROC572010No Adaptationcold | C97: ExtremeTemp | D97: MIROC5 | E97: 7 | F97: 2010 | G97: No Adaptation | H97: cold | I97: MIROC5 2010 adj
A98: =ROW( data_scaledImpacts[[#This Row],[row_id]] ) - ROW( data_scaledImpacts[[#Headers],[row_id]] ) -> 97 | B98: =_xlfn.TEXTJOIN( "", , data_scaledImpacts[[#This Row],[sector]:[impactType]] ) -> ExtremeTempGFDL-CM372010No Adaptationcold | C98: ExtremeTemp | D98: GFDL-CM3 | E98: 7 | F98: 2010 | G98: No Adaptation | H98: cold | I98: GFDL_CM3 2010 adj
A99: =ROW( data_scaledImpacts[[#This Row],[row_id]] ) - ROW( data_scaledImpacts[[#Headers],[row_id]] ) -> 98 | B99: =_xlfn.TEXTJOIN( "", , data_scaledImpacts[[#This Row],[sector]:[impactType]] ) -> ExtremeTempGCM Average72010No Adaptationcold | C99: ExtremeTemp | D99: GCM Average | E99: 7 | F99: 2010 | G99: No Adaptation | H99: cold | I99: 2010 adj
A100: =ROW( data_scaledImpacts[[#This Row],[row_id]] ) - ROW( data_scaledImpacts[[#Headers],[row_id]] ) -> 99 | B100: =_xlfn.TEXTJOIN( "", , data_scaledImpacts[[#This Row],[sector]:[impactType]] ) -> ExtremeTempCanESM212090No Adaptationhot | C100: ExtremeTemp | D100: CanESM2 | E100: 1 | F100: 2090 | G100: No Adaptation | H100: hot | I100: CanESM2 2090 adj | J100: 6.8533123e-06 | K100: 4.1550553e-06 | N100: 4.1798494e-06 | O100: 6.0258583e-06 | P100: 6.8798187e-06
A101: =ROW( data_scaledImpacts[[#This Row],[row_id]] ) - ROW( data_scaledImpacts[[#Headers],[row_id]] ) -> 100 | B101: =_xlfn.TEXTJOIN( "", , data_scaledImpacts[[#This Row],[sector]:[impactType]] ) -> ExtremeTempCCSM412090No Adaptationhot | C101: ExtremeTemp | D101: CCSM4 | E101: 1 | F101: 2090 | G101: No Adaptation | H101: hot | I101: CCSM4 2090 adj | J101: 4.5936703e-06 | K101: 2.6160339e-06 | N101: 2.3769626e-06 | O101: 2.0724046e-06 | P101: 4.0012721e-06
A102: =ROW( data_scaledImpacts[[#This Row],[row_id]] ) - ROW( data_scaledImpacts[[#Headers],[row_id]] ) -> 101 | B102: =_xlfn.TEXTJOIN( "", , data_scaledImpacts[[#This Row],[sector]:[impactType]] ) -> ExtremeTempGISS-E2-R12090No Adaptationhot | C102: ExtremeTemp | D102: GISS-E2-R | E102: 1 | F102: 2090 | G102: No Adaptation | H102: hot | I102: GISS_E2_R 2090 adj | J102: 1.1783932e-05 | K102: 7.6652958e-06 | N102: 5.1414538e-06 | O102: 3.4767353e-06 | P102: 3.2181797e-06
A103: =ROW( data_scaledImpacts[[#This Row],[row_id]] ) - ROW( data_scaledImpacts[[#Headers],[row_id]] ) -> 102 | B103: =_xlfn.TEXTJOIN( "", , data_scaledImpacts[[#This Row],[sector]:[impactType]] ) -> ExtremeTempHadGEM2-ES12090No Adaptationhot | C103: ExtremeTemp | D103: HadGEM2-ES | E103: 1 | F103: 2090 | G103: No Adaptation | H103: hot | I103: HadGEM2_ES 2090 adj | J103: 6.9999681e-06 | K103: 5.0809359e-06 | N103: 1.0076922e-05 | O103: 7.3210974e-06 | P103: 3.163124e-06
A104: =ROW( data_scaledImpacts[[#This Row],[row_id]] ) - ROW( data_scaledImpacts[[#Headers],[row_id]] ) -> 103 | B104: =_xlfn.TEXTJOIN( "", , data_scaledImpacts[[#This Row],[sector]:[impactType]] ) -> ExtremeTempMIROC512090No Adaptationhot | C104: ExtremeTemp | D104: MIROC5 | E104: 1 | F104: 2090 | G104: No Adaptation | H104: hot | I104: MIROC5 2090 adj | J104: 6.6731423e-06 | K104: 1.640499e-06 | N104: 4.3660606e-06 | O104: 7.8935864e-06 | P104: 3.4076293e-07
A105: =ROW( data_scaledImpacts[[#This Row],[row_id]] ) - ROW( data_scaledImpacts[[#Headers],[row_id]] ) -> 104 | B105: =_xlfn.TEXTJOIN( "", , data_scaledImpacts[[#This Row],[sector]:[impactType]] ) -> ExtremeTempGFDL-CM312090No Adaptationhot | C105: ExtremeTemp | D105: GFDL-CM3 | E105: 1 | F105: 2090 | G105: No Adaptation | H105: hot | I105: GFDL_CM3 2090 adj | J105: 9.583975e-06 | K105: 7.3784832e-06 | N105: 4.976211e-06 | O105: 6.7523856e-06 | P105: 3.9648216e-06
A106: =ROW( data_scaledImpacts[[#This Row],[row_id]] ) - ROW( data_scaledImpacts[[#Headers],[row_id]] ) -> 105 | B106: =_xlfn.TEXTJOIN( "", , data_scaledImpacts[[#This Row],[sector]:[impactType]] ) -> ExtremeTempGCM Average12090No Adaptationhot | C106: ExtremeTemp | D106: GCM Average | E106: 1 | F106: 2090 | G106: No Adaptation | H106: hot | I106: 2090 adj | J106: 7.748e-06 | K106: 4.7560505e-06 | N106: 5.1862432e-06 | O106: 5.5903446e-06 | P106: 3.5946632e-06
A107: =ROW( data_scaledImpacts[[#This Row],[row_id]] ) - ROW( data_scaledImpacts[[#Headers],[row_id]] ) -> 106 | B107: =_xlfn.TEXTJOIN( "", , data_scaledImpacts[[#This Row],[sector]:[impactType]] ) -> ExtremeTempCanESM222090No Adaptationhot | C107: ExtremeTemp | D107: CanESM2 | E107: 2 | F107: 2090 | G107: No Adaptation | H107: hot | I107: CanESM2 2090 adj | J107: 1.7192959e-05 | K107: 1.395882e-05 | N107: 1.9389195e-05 | O107: 2.1232866e-05 | P107: 1.1837585e-05
A108: =ROW( data_scaledImpacts[[#This Row],[row_id]] ) - ROW( data_scaledImpacts[[#Headers],[row_id]] ) -> 107 | B108: =_xlfn.TEXTJOIN( "", , data_scaledImpacts[[#This Row],[sector]:[impactType]] ) -> ExtremeTempCCSM422090No Adaptationhot | C108: ExtremeTemp | D108: CCSM4 | E108: 2 | F108: 2090 | G108: No Adaptation | H108: hot | I108: CCSM4 2090 adj | J108: 1.5380012e-05 | K108: 1.0955941e-05 | N108: 1.0286162e-05 | O108: 1.1030984e-05 | P108: 6.1460218e-06
A109: =ROW( data_scaledImpacts[[#This Row],[row_id]] ) - ROW( data_scaledImpacts[[#Headers],[row_id]] ) -> 108 | B109: =_xlfn.TEXTJOIN( "", , data_scaledImpacts[[#This Row],[sector]:[impactType]] ) -> ExtremeTempGISS-E2-R22090No Adaptationhot | C109: ExtremeTemp | D109: GISS-E2-R | E109: 2 | F109: 2090 | G109: No Adaptation | H109: hot | I109: GISS_E2_R 2090 adj | J109: 2.1208644e-05 | K109: 1.49111e-05 | N109: 2.151659e-05 | O109: 1.3722061e-05 | P109: 7.8647517e-06
A110: =ROW( data_scaledImpacts[[#This Row],[row_id]] ) - ROW( data_scaledImpacts[[#Headers],[row_id]] ) -> 109 | B110: =_xlfn.TEXTJOIN( "", , data_scaledImpacts[[#This Row],[sector]:[impactType]] ) -> ExtremeTempHadGEM2-ES22090No Adaptationhot | C110: ExtremeTemp | D110: HadGEM2-ES | E110: 2 | F110: 2090 | G110: No Adaptation | H110: hot | I110: HadGEM2_ES 2090 adj | J110: 2.4583138e-05 | K110: 1.7579999e-05 | N110: 2.07964e-05 | O110: 1.4127558e-05 | P110: 5.5664295e-06
A111: =ROW( data_scaledImpacts[[#This Row],[row_id]] ) - ROW( data_scaledImpacts[[#Headers],[row_id]] ) -> 110 | B111: =_xlfn.TEXTJOIN( "", , data_scaledImpacts[[#This Row],[sector]:[impactType]] ) -> ExtremeTempMIROC522090No Adaptationhot | C111: ExtremeTemp | D111: MIROC5 | E111: 2 | F111: 2090 | G111: No Adaptation | H111: hot | I111: MIROC5 2090 adj | J111: 1.2103374e-05 | K111: 5.2614639e-06 | N111: 1.036917e-05 | O111: 1.5924797e-05 | P111: 2.3211191e-06
... A122: =ROW( data_scaledImpacts[[#This Row],[row_id]] ) - ROW( data_scaledImpacts[[#Headers],[row_id]] ) -> 121 | B122: =_xlfn.TEXTJOIN( "", , data_scaledImpacts[[#This Row],[sector]:[impactType]] ) -> ExtremeTempCCSM442090No Adaptationhot | C122: ExtremeTemp | D122: CCSM4 | E122: 4 | F122: 2090 | G122: No Adaptation | H122: hot | I122: CCSM4 2090 adj | J122: 3.7010523e-05 | K122: 4.5037268e-05 | N122: 4.4045814e-05 | O122: 4.0680533e-05 | P122: 1.8049406e-05
A123: =ROW( data_scaledImpacts[[#This Row],[row_id]] ) - ROW( data_scaledImpacts[[#Headers],[row_id]] ) -> 122 | B123: =_xlfn.TEXTJOIN( "", , data_scaledImpacts[[#This Row],[sector]:[impactType]] ) -> ExtremeTempGISS-E2-R42090No Adaptationhot | C123: ExtremeTemp | D123: GISS-E2-R | E123: 4 | F123: 2090 | G123: No Adaptation | H123: hot | I123: GISS_E2_R 2090 adj
A124: =ROW( data_scaledImpacts[[#This Row],[row_id]] ) - ROW( data_scaledImpacts[[#Headers],[row_id]] ) -> 123 | B124: =_xlfn.TEXTJOIN( "", , data_scaledImpacts[[#This Row],[sector]:[impactType]] ) -> ExtremeTempHadGEM2-ES42090No Adaptationhot | C124: ExtremeTemp | D124: HadGEM2-ES | E124: 4 | F124: 2090 | G124: No Adaptation | H124: hot | I124: HadGEM2_ES 2090 adj | J124: 5.1111729e-05 | K124: 4.8175808e-05 | N124: 5.9502392e-05 | O124: 4.7424078e-05 | P124: 1.9606035e-05
A125: =ROW( data_scaledImpacts[[#This Row],[row_id]] ) - ROW( data_scaledImpacts[[#Headers],[row_id]] ) -> 124 | B125: =_xlfn.TEXTJOIN( "", , data_scaledImpacts[[#This Row],[sector]:[impactType]] ) -> ExtremeTempMIROC542090No Adaptationhot | C125: ExtremeTemp | D125: MIROC5 | E125: 4 | F125: 2090 | G125: No Adaptation | H125: hot | I125: MIROC5 2090 adj | J125: 3.7062638e-05 | K125: 3.6358097e-05 | N125: 3.9123962e-05 | O125: 4.8838934e-05 | P125: 1.0953138e-05
A126: =ROW( data_scaledImpacts[[#This Row],[row_id]] ) - ROW( data_scaledImpacts[[#Headers],[row_id]] ) -> 125 | B126: =_xlfn.TEXTJOIN( "", , data_scaledImpacts[[#This Row],[sector]:[impactType]] ) -> ExtremeTempGFDL-CM342090No Adaptationhot | C126: ExtremeTemp | D126: GFDL-CM3 | E126: 4 | F126: 2090 | G126: No Adaptation | H126: hot | I126: GFDL_CM3 2090 adj | J126: 5.3808781e-05 | K126: 7.3612673e-05 | N126: 6.1555284e-05 | O126: 6.427158e-05 | P126: 3.3311956e-05
A127: =ROW( data_scaledImpacts[[#This Row],[row_id]] ) - ROW( data_scaledImpacts[[#Headers],[row_id]] ) -> 126 | B127: =_xlfn.TEXTJOIN( "", , data_scaledImpacts[[#This Row],[sector]:[impactType]] ) -> ExtremeTempGCM Average42090No Adaptationhot | C127: ExtremeTemp | D127: GCM Average | E127: 4 | F127: 2090 | G127: No Adaptation | H127: hot | I127: 2090 adj | J127: 4.3847834e-05 | K127: 5.1613114e-05 | N127: 5.1720882e-05 | O127: 5.1387907e-05 | P127: 2.375371e-05
A128: =ROW( data_scaledImpacts[[#This Row],[row_id]] ) - ROW( data_scaledImpacts[[#Headers],[row_id]] ) -> 127 | B128: =_xlfn.TEXTJOIN( "", , data_scaledImpacts[[#This Row],[sector]:[impactType]] ) -> ExtremeTempCanESM252090No Adaptationhot | C128: ExtremeTemp | D128: CanESM2 | E128: 5 | F128: 2090 | G128: No Adaptation | H128: hot | I128: CanESM2 2090 adj | J128: 6.0410761e-05 | K128: 7.9318955e-05 | N128: 8.0853282e-05 | O128: 6.2702063e-05 | P128: 5.4338951e-05
A129: =ROW( data_scaledImpacts[[#This Row],[row_id]] ) - ROW( data_scaledImpacts[[#Headers],[row_id]] ) -> 128 | B129: =_xlfn.TEXTJOIN( "", , data_scaledImpacts[[#This Row],[sector]:[impactType]] ) -> ExtremeTempCCSM452090No Adaptationhot | C129: ExtremeTemp | D129: CCSM4 | E129: 5 | F129: 2090 | G129: No Adaptation | H129: hot | I129: CCSM4 2090 adj | J129: 4.9031896e-05 | K129: 5.9209511e-05 | N129: 6.6653609e-05 | O129: 5.7113247e-05 | P129: 2.3748167e-05
A130: =ROW( data_scaledImpacts[[#This Row],[row_id]] ) - ROW( data_scaledImpacts[[#Headers],[row_id]] ) -> 129 | B130: =_xlfn.TEXTJOIN( "", , data_scaledImpacts[[#This Row],[sector]:[impactType]] ) -> ExtremeTempGISS-E2-R52090No Adaptationhot | C130: ExtremeTemp | D130: GISS-E2-R | E130: 5 | F130: 2090 | G130: No Adaptation | H130: hot | I130: GISS_E2_R 2090 adj
...

Sheet slr_cm
A1: row_id | B1: year | C1: 0_cm | D1: 30_cm | E1: 50_cm | F1: 100_cm | G1: 150_cm | H1: 200_cm | I1: 250_cm
A2: =ROW( slr_cm[[#This Row],[row_id]] ) - ROW( slr_cm[[#Headers],[row_id]] ) -> 1 | B2: 2000 | C2: 0 | D2: 0 | E2: 0 | F2: 0 | G2: 0 | H2: 0 | I2: 0
A3: =ROW( slr_cm[[#This Row],[row_id]] ) - ROW( slr_cm[[#Headers],[row_id]] ) -> 2 | B3: 2001 | C3: 0 | D3: 0.3 | E3: 0.4 | F3: 0.4 | G3: 0.5 | H3: 0.5 | I3: 0.5
A4: =ROW( slr_cm[[#This Row],[row_id]] ) - ROW( slr_cm[[#Headers],[row_id]] ) -> 3 | B4: 2002 | C4: 0 | D4: 0.6 | E4: 0.8 | F4: 0.8 | G4: 1 | H4: 1 | I4: 1
A5: =ROW( slr_cm[[#This Row],[row_id]] ) - ROW( slr_cm[[#Headers],[row_id]] ) -> 4 | B5: 2003 | C5: 0 | D5: 0.9 | E5: 1.2 | F5: 1.2 | G5: 1.5 | H5: 1.5 | I5: 1.5
A6: =ROW( slr_cm[[#This Row],[row_id]] ) - ROW( slr_cm[[#Headers],[row_id]] ) -> 5 | B6: 2004 | C6: 0 | D6: 1.2 | E6: 1.6 | F6: 1.6 | G6: 2 | H6: 2 | I6: 2
A7: =ROW( slr_cm[[#This Row],[row_id]] ) - ROW( slr_cm[[#Headers],[row_id]] ) -> 6 | B7: 2005 | C7: 0 | D7: 1.5 | E7: 2 | F7: 2 | G7: 2.5 | H7: 2.5 | I7: 2.5
A8: =ROW( slr_cm[[#This Row],[row_id]] ) - ROW( slr_cm[[#Headers],[row_id]] ) -> 7 | B8: 2006 | C8: 0 | D8: 1.8 | E8: 2.4 | F8: 2.4 | G8: 3 | H8: 3 | I8: 3
A9: =ROW( slr_cm[[#This Row],[row_id]] ) - ROW( slr_cm[[#Headers],[row_id]] ) -> 8 | B9: 2007 | C9: 0 | D9: 2.1 | E9: 2.8 | F9: 2.8 | G9: 3.5 | H9: 3.5 | I9: 3.5
A10: =ROW( slr_cm[[#This Row],[row_id]] ) - ROW( slr_cm[[#Headers],[row_id]] ) -> 9 | B10: 2008 | C10: 0 | D10: 2.4 | E10: 3.2 | F10: 3.2 | G10: 4 | H10: 4 | I10: 4
A11: =ROW( slr_cm[[#This Row],[row_id]] ) - ROW( slr_cm[[#Headers],[row_id]] ) -> 10 | B11: 2009 | C11: 0 | D11: 2.7 | E11: 3.6 | F11: 3.6 | G11: 4.5 | H11: 4.5 | I11: 4.5
A12: =ROW( slr_cm[[#This Row],[row_id]] ) - ROW( slr_cm[[#Headers],[row_id]] ) -> 11 | B12: 2010 | C12: 0 | D12: 3 | E12: 4 | F12: 4 | G12: 5 | H12: 5 | I12: 5
A13: =ROW( slr_cm[[#This Row],[row_id]] ) - ROW( slr_cm[[#Headers],[row_id]] ) -> 12 | B13: 2011 | C13: 0 | D13: 3.3 | E13: 4.4 | F13: 4.6 | G13: 5.5 | H13: 5.6 | I13: 5.6
... A102: =ROW( slr_cm[[#This Row],[row_id]] ) - ROW( slr_cm[[#Headers],[row_id]] ) -> 101 | B102: 2100 | C102: 0 | D102: 30 | E102: 50 | F102: 100 | G102: 150 | H102: 200 | I102: 250

Sheet slrImpacts
A1: row_id | B1: year | C1: sector | D1: variant | E1: impactType | F1: impactYear | G1: Midwest_30 | H1: Midwest_50 | I1: Midwest_100 | J1: Midwest_150 | K1: Midwest_200 | L1: Midwest_250 | M1: Northeast_30 | N1: Northeast_50 | O1: Northeast_100 | P1: Northeast_150 | Q1: Northeast_200 | R1: Northeast_250 | S1: Northern Plains_30 | T1: Northern Plains_50 | U1: Northern Plains_100 | V1: Northern Plains_150 | W1: Northern Plains_200 | X1: Northern Plains_250 | Y1: Northwest_30 | Z1: Northwest_50 | AA1: Northwest_100 | AB1: Northwest_150 | AC1: Northwest_200 | AD1: Northwest_250 | AE1: Southeast_30 | AF1: Southeast_50 | AG1: Southeast_100 | AH1: Southeast_150 | AI1: Southeast_200 | AJ1: Southeast_250 | AK1: Southern Plains_30 | AL1: Southern Plains_50 | AM1: Southern Plains_100 | AN1: Southern Plains_150 | AO1: Southern Plains_200 | AP1: Southern Plains_250 | AQ1: Southwest_30 | AR1: Southwest_50 | AS1: Southwest_100 | AT1: Southwest_150 | AU1: Southwest_200 | AV1: Southwest_250
A2: =ROW( slrImpacts[[#This Row],[row_id]] ) - ROW( slrImpacts[[#Headers],[row_id]] ) -> 1 | B2: 2000 | C2: CoastalProperties | D2: NoAdapt | E2: NA | G2: 0 | H2: 0 | I2: 0 | J2: 0 | K2: 0 | L2: 0 | M2: 0 | N2: 0 | O2: 0 | P2: 0 | Q2: 0 | R2: 0 | S2: 0 | T2: 0 | U2: 0 | V2: 0 | W2: 0 | X2: 0 | Y2: 0 | Z2: 0 | AA2: 0 | AB2: 0 | AC2: 0 | AD2: 0 | AE2: 0 | AF2: 0 | AG2: 0 | AH2: 0 | AI2: 0 | AJ2: 0 | AK2: 0 | AL2: 0 | AM2: 0 | AN2: 0 | AO2: 0 | AP2: 0 | AQ2: 0 | AR2: 0 | AS2: 0 | AT2: 0 | AU2: 0 | AV2: 0
A3: =ROW( slrImpacts[[#This Row],[row_id]] ) - ROW( slrImpacts[[#Headers],[row_id]] ) -> 2 | B3: 2001 | C3: CoastalProperties | D3: NoAdapt | E3: NA | G3: 0 | H3: 0 | I3: 0 | J3: 0 | K3: 0 | L3: 0 | M3: 8.0757539e+08 | N3: 8.1674815e+08 | O3: 8.3921456e+08 | P3: 8.6094066e+08 | Q3: 8.8338527e+08 | R3: 8.8806151e+08 | S3: 0 | T3: 0 | U3: 0 | V3: 0 | W3: 0 | X3: 0 | Y3: 95624079 | Z3: 96731286 | AA3: 98146043 | AB3: 1.0138361e+08 | AC3: 1.0314021e+08 | AD3: 1.0413911e+08 | AE3: 2.2561706e+09 | AF3: 2.2977331e+09 | AG3: 2.4291266e+09 | AH3: 2.5260882e+09 | AI3: 2.6207984e+09 | AJ3: 2.6235138e+09 | AK3: 1.6290366e+08 | AL3: 1.6846959e+08 | AM3: 1.7582794e+08 | AN3: 1.8494824e+08 | AO3: 1.9319302e+08 | AP3: 1.9343977e+08 | AQ3: 1.1935413e+08 | AR3: 1.1940838e+08 | AS3: 1.2868798e+08 | AT3: 1.3756618e+08 | AU3: 1.429314e+08 | AV3: 1.4301656e+08
A4: =ROW( slrImpacts[[#This Row],[row_id]] ) - ROW( slrImpacts[[#Headers],[row_id]] ) -> 3 | B4: 2002 | C4: CoastalProperties | D4: NoAdapt | E4: NA | G4: 0 | H4: 0 | I4: 0 | J4: 0 | K4: 0 | L4: 0 | M4: 8.0757539e+08 | N4: 8.1674815e+08 | O4: 8.3921456e+08 | P4: 8.6094066e+08 | Q4: 8.8338527e+08 | R4: 8.8806151e+08 | S4: 0 | T4: 0 | U4: 0 | V4: 0 | W4: 0 | X4: 0 | Y4: 95624079 | Z4: 96731286 | AA4: 98146043 | AB4: 1.0138361e+08 | AC4: 1.0314021e+08 | AD4: 1.0413911e+08 | AE4: 2.2561706e+09 | AF4: 2.2977331e+09 | AG4: 2.4291266e+09 | AH4: 2.5260882e+09 | AI4: 2.6207984e+09 | AJ4: 2.6235138e+09 | AK4: 1.6290366e+08 | AL4: 1.6846959e+08 | AM4: 1.7582794e+08 | AN4: 1.8494824e+08 | AO4: 1.9319302e+08 | AP4: 1.9343977e+08 | AQ4: 1.1935413e+08 | AR4: 1.1940838e+08 | AS4: 1.2868798e+08 | AT4: 1.3756618e+08 | AU4: 1.429314e+08 | AV4: 1.4301656e+08
A5: =ROW( slrImpacts[[#This Row],[row_id]] ) - ROW( slrImpacts[[#Headers],[row_id]] ) -> 4 | B5: 2003 | C5: CoastalProperties | D5: NoAdapt | E5: NA | G5: 0 | H5: 0 | I5: 0 | J5: 0 | K5: 0 | L5: 0 | M5: 8.0757539e+08 | N5: 8.1674815e+08 | O5: 8.3921456e+08 | P5: 8.6094066e+08 | Q5: 8.8338527e+08 | R5: 8.8806151e+08 | S5: 0 | T5: 0 | U5: 0 | V5: 0 | W5: 0 | X5: 0 | Y5: 95624079 | Z5: 96731286 | AA5: 98146043 | AB5: 1.0138361e+08 | AC5: 1.0314021e+08 | AD5: 1.0413911e+08 | AE5: 2.2561706e+09 | AF5: 2.2977331e+09 | AG5: 2.4291266e+09 | AH5: 2.5260882e+09 | AI5: 2.6207984e+09 | AJ5: 2.6235138e+09 | AK5: 1.6290366e+08 | AL5: 1.6846959e+08 | AM5: 1.7582794e+08 | AN5: 1.8494824e+08 | AO5: 1.9319302e+08 | AP5: 1.9343977e+08 | AQ5: 1.1935413e+08 | AR5: 1.1940838e+08 | AS5: 1.2868798e+08 | AT5: 1.3756618e+08 | AU5: 1.429314e+08 | AV5: 1.4301656e+08
